Workbook

Sheet Index
A7: Tab Name | B7: Description | C7: Link
A8: PL | B8: Profit and Loss | C8: PL!A1
A9: BS | B9: Balance Sheet | C9: BS!A1
A10: CFS | B10: Cash Flow Statement | C10: CFS!A1
A11: Ethanol | B11: Ethanol and DDGS working | C11: Ethanol!A1
A12: Sugar | B12: Sugar plant working | C12: Sugar!A1
A13: Power | B13: Bagasse based plant working | C13: Power!A1
A14: Employee | B14: Employee cost | C14: Employee!A1

Sheet Summary
B2: Particulars | C2: 45747 | D2: =EOMONTH(C2,12) -> 46112 | E2: =EOMONTH(D2,12) -> 46477 | F2: =EOMONTH(E2,12) -> 46843 | G2: =EOMONTH(F2,12) -> 47208 | H2: =EOMONTH(G2,12) -> 47573 | K2: CAGR
B3: Revenue from Operations | C3: =2960217280.04+41806415 -> 3.0020237e+09 | D3: =PL!I$17 -> 8.1107688e+09 | E3: =PL!N17 -> 1.3105576e+10 | F3: =PL!S17 -> 1.3784026e+10 | G3: =PL!X17 -> 1.4622741e+10 | H3: =PL!AC17 -> 1.5649111e+10
B4: Total Revenue | C4: =SUM(C3:C3) -> 3.0020237e+09 | D4: =SUM(D3:D3) -> 8.1107688e+09 | E4: =SUM(E3:E3) -> 1.3105576e+10 | F4: =SUM(F3:F3) -> 1.3784026e+10 | G4: =SUM(G3:G3) -> 1.4622741e+10 | H4: =SUM(H3:H3) -> 1.5649111e+10 | I4: =H4/C4 -> 5.2128541 | K4: =(H4/C4)^(1/5)-1 -> 0.39128183
B6: Expenses:
B7: Cost of materials consumed | C7: =2596066425.97-399258751 -> 2.1968077e+09 | D7: =SUM(D8:D9) -> 6.2159227e+09 | E7: =SUM(E8:E9) -> 9.8303908e+09 | F7: =SUM(F8:F9) -> 9.7282752e+09 | G7: =SUM(G8:G9) -> 1.0221874e+10 | H7: =SUM(H8:H9) -> 1.0952647e+10 | I7: =E7/$E$4 -> 0.75009221 | J7: =F7/$F$4 -> 0.70576442
B8: Sugercane | C8: 0 | D8: =SUM(PL!$I$21:$I$26) -> 2.4107063e+09 | E8: =SUM(PL!$N$21:$N$26) -> 2.1584944e+09 | F8: =SUM(PL!$S$21:$S$26) -> 2.284255e+09 | G8: =SUM(PL!$X$21:$X$26) -> 2.6301462e+09 | H8: =SUM(PL!$AC$21:$AC$26) -> 3.1285798e+09 | I8: =E8/$E$4 -> 0.16470045 | J8: =F8/$F$4 -> 0.16571754
B9: Corn | C9: 0 | D9: =SUM(PL!$I$29:$I$34) -> 3.8052164e+09 | E9: =SUM(PL!$N$29:$N$34) -> 7.6718965e+09 | F9: =SUM(PL!$S$29:$S$34) -> 7.4440202e+09 | G9: =SUM(PL!$X$29:$X$34) -> 7.5917275e+09 | H9: =SUM(PL!$AC$29:$AC$34) -> 7.8240671e+09 | I9: =E9/$E$4 -> 0.58539176 | J9: =F9/$F$4 -> 0.54004688
B10: Salaries Corporate Employees | C10: 84408959 | D10: =PL!$I$37 -> 28022816 | E10: =PL!$N$37 -> 30931945 | F10: =PL!$S$37 -> 34143080 | G10: =PL!$X$37 -> 37687572 | H10: =PL!$AC$37 -> 41600027 | I10: =E10/$E$4 -> 0.0023602125 | J10: =F10/$F$4 -> 0.0024770034
B11: Research Expenses | C11: 0 | D11: =PL!$I$38 -> 4152515.6 | E11: =PL!$N$38 -> 4583600.3 | F11: =PL!$S$38 -> 5059437.1 | G11: =PL!$X$38 -> 5584671.9 | H11: =PL!$AC$38 -> 6164432.8 | I11: =E11/$E$4 -> 0.00034974427 | J11: =F11/$F$4 -> 0.00036705075
B12: Misc Expenses | C12: 0 | D12: =PL!$I$39 -> 20608040 | E12: =PL!$N$39 -> 22306805 | F12: =PL!$S$39 -> 24145603 | G12: =PL!$X$39 -> 26135978 | H12: =PL!$AC$39 -> 28290423 | I12: =E12/$E$4 -> 0.001702085 | J12: =F12/$F$4 -> 0.0017517091
B13: Sales and marketing Expenses | C13: 48003432 | D13: =PL!$I$40 -> 1.2389657e+08 | E13: =PL!$N$40 -> 2.5603886e+08 | F13: =PL!$S$40 -> 2.6315607e+08 | G13: =PL!$X$40 -> 2.7027021e+08 | H13: =PL!$AC$40 -> 2.7738435e+08 | I13: =E13/$E$4 -> 0.019536635 | J13: =F13/$F$4 -> 0.019091379
B14: Total Expenses | C14: =SUM(C7:C13) -> 2.3292201e+09 | D14: =SUM(D7,D10:D13) -> 6.3926026e+09 | E14: =SUM(E7,E10:E13) -> 1.0144252e+10 | F14: =SUM(F7,F10:F13) -> 1.0054779e+10 | G14: =SUM(G7,G10:G13) -> 1.0561552e+10 | H14: =SUM(H7,H10:H13) -> 1.1306086e+10 | K14: =(H14/C14)^(1/5)-1 -> 0.3715775
N15: 3.0020237e+09 | O15: 8.1107688e+09 | P15: 1.3105576e+10 | Q15: 1.3784026e+10 | R15: 1.4622741e+10 | S15: 1.5649111e+10
B16: EBITDA | C16: =C4-C14 -> 6.7280363e+08 | D16: =D4-D14 -> 1.7181662e+09 | E16: =E4-E14 -> 2.9613244e+09 | F16: =F4-F14 -> 3.7292467e+09 | G16: =G4-G14 -> 4.0611889e+09 | H16: =H4-H14 -> 4.3430253e+09 | I16: =H16/C16 -> 6.4551157 | J16: =(H16/D16)^(1/4)-1 -> 0.26090334 | K16: =(H16/C16)^(1/5)-1 -> 0.45204744 | N16: =N15/10^7 -> 300.20237 | O16: =O15/10^7 -> 811.07688 | P16: =P15/10^7 -> 1310.5576 | Q16: =Q15/10^7 -> 1378.4026 | R16: =R15/10^7 -> 1462.2741 | S16: =S15/10^7 -> 1564.9111
B17: Depreciation and Amortization Expense | C17: 126822429 | D17: =PL!I46 -> 3.1687701e+08 | E17: =PL!N46 -> 4.0684539e+08 | F17: =PL!S46 -> 3.4916633e+08 | G17: =PL!X46 -> 2.9966451e+08 | H17: =PL!AC46 -> 2.5718063e+08 | N17: 300.20237 | O17: 811.07688 | P17: 1310.5576 | Q17: 1378.4026 | R17: 1462.2741 | S17: 1564.9111
B18: Financial Costs | C18: 1.1393948e+08 | D18: =PL!I$47 -> 3.7964981e+08 | E18: =PL!N47 -> 2.8096845e+08 | F18: =PL!S47 -> 79287497 | G18: =PL!X47 -> 68670364 | H18: =PL!AC47 -> 57401725 | N18: 6.7280363e+08 | O18: 1.7181662e+09 | P18: 2.9613244e+09 | Q18: 3.7292467e+09 | R18: 4.0611889e+09 | S18: 4.3430253e+09
B19: PBT | C19: =C16-SUM(C17:C18) -> 4.3204172e+08 | D19: =D16-SUM(D17:D18) -> 1.0216394e+09 | E19: =E16-SUM(E17:E18) -> 2.2735106e+09 | F19: =F16-SUM(F17:F18) -> 3.3007928e+09 | G19: =G16-SUM(G17:G18) -> 3.692854e+09 | H19: =H16-SUM(H17:H18) -> 4.0284429e+09 | K19: =(H19/C19)^(1/5)-1 -> 0.56286803 | N19: =N18/10^7 -> 67.280363 | O19: =O18/10^7 -> 171.81662 | P19: =P18/10^7 -> 296.13244 | Q19: =Q18/10^7 -> 372.92467 | R19: =R18/10^7 -> 406.11889 | S19: =S18/10^7 -> 434.30253
B20: less:Taxes | C20: 1.0001958e+08 | D20: =PL!I51 -> 2.5714664e+08 | E20: =PL!N51 -> 5.7224261e+08 | F20: =PL!S51 -> 8.3080956e+08 | G20: =PL!X51 -> 9.2949136e+08 | H20: =PL!AC51 -> 1.0139591e+09 | N20: 67.280363 | O20: 171.81662 | P20: 296.13244 | Q20: 372.92467 | R20: 406.11889 | S20: 434.30253
B21: PAT | C21: =C19-C20 -> 3.3202214e+08 | D21: =D19-D20 -> 7.6449276e+08 | E21: =E19-E20 -> 1.701268e+09 | F21: =F19-F20 -> 2.4699833e+09 | G21: =G19-G20 -> 2.7633627e+09 | H21: =H19-H20 -> 3.0144838e+09 | I21: =H21/C21 -> 9.0791651 | K21: =(H21/C21)^(1/5)-1 -> 0.55456606 | N21: 3.3202214e+08 | O21: 7.6449276e+08 | P21: 1.701268e+09 | Q21: 2.4699833e+09 | R21: 2.7633627e+09 | S21: 3.0144838e+09
N22: =N21/10^7 -> 33.202214 | O22: =O21/10^7 -> 76.449276 | P22: =P21/10^7 -> 170.1268 | Q22: =Q21/10^7 -> 246.99833 | R22: =R21/10^7 -> 276.33627 | S22: =S21/10^7 -> 301.44838
N23: 33.202214 | O23: 76.449276 | P23: 170.1268 | Q23: 246.99833 | R23: 276.33627 | S23: 301.44838
O25: Revenue | P25: EBITDA | Q25: PAT | R25: PAT Margin | S25: EBITDA Margin
N26: 2025 | O26: =$N17 -> 300.20237 | P26: =N20 -> 67.280363 | Q26: =N23 -> 33.202214 | R26: =Q26/O26 -> 0.11059944 | S26: =P26/O26 -> 0.22411669
B27: Ratio | C27: 45747 | D27: =EOMONTH(C27,12) -> 46112 | E27: =EOMONTH(D27,12) -> 46477 | F27: =EOMONTH(E27,12) -> 46843 | G27: =EOMONTH(F27,12) -> 47208 | H27: =EOMONTH(G27,12) -> 47573 | K27: Formula | N27: =N26+1 -> 2026 | O27: =O17 -> 811.07688 | P27: =O20 -> 171.81662 | Q27: =O23 -> 76.449276 | R27: =Q27/O27 -> 0.09425651 | S27: =P27/O27 -> 0.21183765
B28: Profitability | N28: =N27+1 -> 2027 | O28: =P17 -> 1310.5576 | P28: =P20 -> 296.13244 | Q28: =P23 -> 170.1268 | R28: =Q28/O28 -> 0.12981252 | S28: =P28/O28 -> 0.22595911
B29: Operating margins | C29: =C16/C3 -> 0.22411669 | D29: =D16/D3 -> 0.21183765 | E29: =E16/E3 -> 0.22595911 | F29: =F16/F3 -> 0.27054843 | G29: =G16/G3 -> 0.27773103 | H29: =H16/H3 -> 0.27752536 | K29: EBITDA/Sales | N29: =N28+1 -> 2028 | O29: =Q17 -> 1378.4026 | P29: =Q20 -> 372.92467 | Q29: =Q23 -> 246.99833 | R29: =Q29/O29 -> 0.17919172 | S29: =P29/O29 -> 0.27054843
B30: NPM | C30: =C21/C3 -> 0.11059944 | D30: =D21/D3 -> 0.09425651 | E30: =E21/E3 -> 0.12981252 | F30: =F21/F3 -> 0.17919172 | G30: =G21/G3 -> 0.18897706 | H30: =H21/H3 -> 0.19262971 | K30: PAT/Sales | N30: =N29+1 -> 2029 | O30: =R17 -> 1462.2741 | P30: =R20 -> 406.11889 | Q30: =R23 -> 276.33627 | R30: =Q30/O30 -> 0.18897706 | S30: =P30/O30 -> 0.27773103
N31: =N30+1 -> 2030 | O31: =S17 -> 1564.9111 | P31: =S20 -> 434.30253 | Q31: =S23 -> 301.44838 | R31: =Q31/O31 -> 0.19262971 | S31: =P31/O31 -> 0.27752536
B32: Return ratio
B33: Return on Equity | C33: =C21/BS!C41 -> 0.26996963 | D33: =D21/BS!H41 -> 0.38333069 | E33: =E21/BS!L41 -> 0.46034826 | F33: =F21/BS!P41 -> 0.40060752 | G33: =G21/BS!T41 -> 0.30948327 | H33: =H21/BS!X41 -> 0.25239661 | K33: PAT/Total Equity
B34: Return on capital employed | C34: =C16/(BS!C25+BS!C31+BS!C41) -> 0.15509895 | D34: =D16/(BS!H25+BS!H31+BS!H41) -> 0.29495263 | E34: =E16/(BS!L25+BS!L31+BS!L41) -> 0.49027568 | F34: =F16/(BS!P25+BS!P31+BS!P41) -> 0.44730827 | G34: =G16/(BS!T25+BS!T31+BS!T41) -> 0.37201244 | H34: =H16/(BS!X25+BS!X31+BS!X41) -> 0.3161694 | K34: EBITDA/(Total Debt+Equity)
B36: Debt ratio
B37: Debt/equity | C37: =(BS!C25+BS!C31)/BS!C41 -> 2.5271777 | D37: =(BS!H25+BS!H31)/BS!H41 -> 1.920876 | E37: =(BS!L25+BS!L31)/BS!L41 -> 0.63440401 | F37: =(BS!P25+BS!P31)/BS!P41 -> 0.35219479 | G37: =(BS!T25+BS!T31)/BS!T41 -> 0.2226299 | H37: =(BS!X25+BS!X31)/BS!X41 -> 0.15011979 | K37: Total Debt/Equity
B38: interst coverage ratio | C38: =C16/C18 -> 5.9049209 | D38: =D16/D18 -> 4.5256607 | E38: =E16/E18 -> 10.539704 | F38: =F16/F18 -> 47.034486 | G38: =G16/G18 -> 59.140344 | H38: =H16/H18 -> 75.660187 | K38: EBITDA/Finance Cost
B40: Turnover ratio
B41: Fixed assets turnover | C41: =C3/(BS!C16+BS!C17) -> 1.0222773 | D41: =D3/(BS!H16+BS!H17) -> 2.8263207 | E41: =E3/(BS!L16+BS!L17) -> 5.3212368 | F41: =F3/(BS!P16+BS!P17) -> 6.5212311 | G41: =G3/(BS!T16+BS!T17) -> 8.0608222 | H41: =H3/(BS!X16+BS!X17) -> 10.051648 | K41: Sales/Total fixed assets
B42: inventory turnover | C42: =C3/BS!C11 -> 1.8699167 | D42: =D3/BS!H11 -> 6.565099 | E42: =E3/BS!L11 -> 2.8707071 | F42: =F3/BS!P11 -> 2.8492717 | G42: =G3/BS!T11 -> 2.7624593 | H42: =H3/BS!X11 -> 2.7464649 | K42: Sales/ inventory
B43: Receivable turnover | C43: =C3/BS!C10 -> 17.365832 | D43: =D3/BS!H10 -> 12.923054 | E43: =E3/BS!L10 -> 20.228256 | F43: =F3/BS!P10 -> 20.661752 | G43: =G3/BS!T10 -> 21.276137 | H43: =H3/BS!X10 -> 18.422904 | K43: Sales/ Receivable
B44: Payables turnover | C44: Sales/ Paybale | D44: =C3/BS!C26 -> 4.4049521 | E44: =D3/BS!H26 -> 40.46862 | F44: =E3/BS!L26 -> 23466.698 | G44: =F3/BS!P26 -> 22675.977 | H44: =G3/BS!T26 -> 21970.125 | I44: =H3/BS!X26 -> 17381.379
B47: Dupont analysis
B48: Net profit margin | C48: =C21/C3 -> 0.11059944 | D48: =D21/D3 -> 0.09425651 | E48: =E21/E3 -> 0.12981252 | F48: =F21/F3 -> 0.17919172 | G48: =G21/G3 -> 0.18897706 | H48: =H21/H3 -> 0.19262971 | K48: net income/sales
B49: Assets turnover ratio | C49: =C3/BS!C22 -> 0.56528936 | D49: =D3/BS!H22 -> 1.2839925 | E49: =E3/BS!L22 -> 2.0697813 | F49: =F3/BS!P22 -> 1.5974297 | G49: =G3/BS!T22 -> 1.304593 | H49: =H3/BS!X22 -> 1.1155249 | K49: sales/total assets
B50: Equity multiplier | C50: =BS!C22/BS!C41 -> 4.3180849 | D50: =BS!H22/BS!H41 -> 3.1673769 | E50: =BS!L22/BS!L41 -> 1.7133475 | F50: =BS!P22/BS!P41 -> 1.399521 | G50: =BS!T22/BS!T41 -> 1.2553159 | H50: =BS!X22/BS!X41 -> 1.1745756 | K50: total assets/shareholder fund
B55: Justifiation to increased profitability
A57: # | B57: Compared to peers operating in Uttar Pradesh and Maharashtra, which typically report sugar recovery rates of around 10%, our operations in Madhya Pradesh have consistently achieved a higher recovery rate of 11%.
B58: This 1% improvement in yield directly enhances profitability, as it results in higher sugar output from the same quantity of sugarcane — thereby improving revenue without incurring any additional raw material or processing cost.
B59: Since this incremental yield does not require any corresponding increase in input cost, it translates into pure margin expansion, improving both gross and EBITDA margins.
B60: Over time, this operational efficiency becomes a key competitive advantage, especially in a cost-sensitive, commodity-driven industry like sugar.
A62: # | B62: While peers in the sugar industry typically report power generation as a separate revenue stream, Mahakaushal Sugar & Power Industries adopts a more conservative accounting approach by netting power income against operating costs.
B63: Specifically, power generated through bagasse/corn-based cogeneration is primarily used for captive consumption, and the surplus exported to the grid is deducted from the cost of power/fuel instead of being reflected as top-line revenue.
B64: This approach does not understate our profitability — rather, it provides a clearer reflection of net operational efficiency.
B65: It also aligns with the principle of matching income directly with the cost it offsets, ensuring transparency in actual margin performance.
B66: As a result, while our revenue figures may appear lower than peers due to this treatment, our reported margins remain fully comparable, and in fact, better reflect our cost savings from internal power generation.
A68: # | B68: While most leading sugar manufacturers have established their operations in states like Uttar Pradesh, Maharashtra, or Rajasthan.
B69: But Mahakaushal Sugar & Power Ltd. has strategically chosen to situate its manufacturing plant in Madhya Pradesh.
B70: (a region historically underserved in terms of large-scale sugar processing infrastructure.)
B72: This decision appears to be driven by multiple strategic and operational advantages:
A73: # | B73: Significantly lower land acquisition and setup costs compared to UP and Maharashtra, enabling more cost-effective capital deployment.
A74: # | B74: A clear first-mover advantage in regions such as Mandla, Dindori, and Jabalpur, where sugarcane cultivation exists but had previously lacked local monetization avenues.
A75: # | B75: The absence of major competing sugar mills in the vicinity created an opportunity to serve a captive cane-producing farmer base, which would otherwise bear high transport costs to distant mills.
A76: # | B76: This allowed Mahakaushal to build deep-rooted supply chain relationships with local farmers, ensuring reliable raw material sourcing and enhancing long-term operational stability.
B78: By entering an untapped geography with latent agricultural potential, the company has effectively positioned itself to optimize input costs, secure supply,
B79: and contribute to rural economic development - while maintaining strong control over its value chain.

Sheet PL
H1: =365*1.33/4 -> 121.3625
B2: No..of days of operation(days) | E2: =300/4 -> 75 | F2: =300/4 -> 75 | G2: =300/4 -> 75 | H2: =300/4 -> 75 | J2: =300/4 -> 75 | K2: =300/4 -> 75 | L2: =300/4 -> 75 | M2: =300/4 -> 75 | O2: =300/4 -> 75 | P2: =300/4 -> 75 | Q2: =300/4 -> 75 | R2: =300/4 -> 75 | T2: =300/4 -> 75 | U2: =300/4 -> 75 | V2: =300/4 -> 75 | W2: =300/4 -> 75 | Y2: =300/4 -> 75 | Z2: =300/4 -> 75 | AA2: =300/4 -> 75 | AB2: =300/4 -> 75
B3: Column counter | E3: 1 | F3: =E3+1 -> 2 | G3: =F3+1 -> 3 | H3: =G3+1 -> 4 | J3: =H3+1 -> 5 | K3: =J3+1 -> 6 | L3: =K3+1 -> 7 | M3: =L3+1 -> 8 | O3: =M3+1 -> 9 | P3: =O3+1 -> 10 | Q3: =P3+1 -> 11 | R3: =Q3+1 -> 12 | T3: =R3+1 -> 13 | U3: =T3+1 -> 14 | V3: =U3+1 -> 15 | W3: =V3+1 -> 16 | Y3: =W3+1 -> 17 | Z3: =Y3+1 -> 18 | AA3: =Z3+1 -> 19 | AB3: =AA3+1 -> 20
B4: Particulars | E4: 45838 | F4: =EOMONTH(E4,3) -> 45930 | G4: =EOMONTH(F4,3) -> 46022 | H4: =EOMONTH(G4,3) -> 46112 | I4: FY 25-26 | J4: =EOMONTH(H4,3) -> 46203 | K4: =EOMONTH(J4,3) -> 46295 | L4: =EOMONTH(K4,3) -> 46387 | M4: =EOMONTH(L4,3) -> 46477 | N4: FY 26-27 | O4: =EOMONTH(M4,3) -> 46568 | P4: =EOMONTH(O4,3) -> 46660 | Q4: =EOMONTH(P4,3) -> 46752 | R4: =EOMONTH(Q4,3) -> 46843 | S4: FY 27-28 | T4: =EOMONTH(R4,3) -> 46934 | U4: =EOMONTH(T4,3) -> 47026 | V4: =EOMONTH(U4,3) -> 47118 | W4: =EOMONTH(V4,3) -> 47208 | X4: FY 28-29 | Y4: =EOMONTH(W4,3) -> 47299 | Z4: =EOMONTH(Y4,3) -> 47391 | AA4: =EOMONTH(Z4,3) -> 47483 | AB4: =EOMONTH(AA4,3) -> 47573 | AC4: FY 29-30
A6: # | B6: Sale Sugar Plant
B7: Sale of Sugar | E7: =Sugar!E71 -> 7.8696429e+08 | F7: =Sugar!F71 -> 9.4157143e+08 | G7: =Sugar!G71 -> 5.9347857e+08 | H7: =Sugar!H71 -> 5.9060957e+08 | I7: =SUM(E7:H7) -> 2.9126239e+09 | J7: =Sugar!J71 -> 689044500 | K7: =Sugar!K71 -> 620140050 | L7: =Sugar!L71 -> 656942670 | M7: =Sugar!M71 -> 7.1917289e+08 | N7: =SUM(J7:M7) -> 2.6853001e+09 | O7: =Sugar!O71 -> 7.3006945e+08 | P7: =Sugar!P71 -> 6.570625e+08 | Q7: =Sugar!Q71 -> 7.7340417e+08 | R7: =Sugar!R71 -> 8.3025452e+08 | S7: =SUM(O7:R7) -> 2.9907906e+09 | T7: =Sugar!T71 -> 8.4283413e+08 | U7: =Sugar!U71 -> 7.5855072e+08 | V7: =Sugar!V71 -> 8.4401005e+08 | W7: =Sugar!W71 -> 1.0060992e+09 | X7: =SUM(T7:W7) -> 3.4514941e+09 | Y7: =Sugar!Y71 -> 1.0213431e+09 | Z7: =Sugar!Z71 -> 9.1920879e+08 | AA7: =Sugar!AA71 -> 9.2768059e+08 | AB7: =Sugar!AB71 -> 1.2119295e+09 | AC7: =SUM(Y7:AB7) -> 4.080162e+09
B8: Molasses | E8: =Sugar!E72 -> 42900000 | F8: =Sugar!F72 -> 38610000 | G8: =Sugar!G72 -> 1.03224e+08 | H8: =Sugar!H72 -> 106959600 | I8: =SUM(E8:H8) -> 291693600 | J8: =Sugar!J72 -> 35653200 | K8: =Sugar!K72 -> 32087880 | L8: =Sugar!L72 -> 109772256 | M8: =Sugar!M72 -> 1.3229584e+08 | N8: =SUM(J8:M8) -> 3.0980917e+08 | O8: =Sugar!O72 -> 44098613 | P8: =Sugar!P72 -> 39688752 | Q8: =Sugar!Q72 -> 1.3024789e+08 | R8: =Sugar!R72 -> 1.5259318e+08 | S8: =SUM(O8:R8) -> 3.6662844e+08 | T8: =Sugar!T72 -> 50864394 | U8: =Sugar!U72 -> 45777955 | V8: =Sugar!V72 -> 1.4187715e+08 | W8: =Sugar!W72 -> 1.8665117e+08 | X8: =SUM(T8:W8) -> 4.2517067e+08 | Y8: =Sugar!Y72 -> 62217058 | Z8: =Sugar!Z72 -> 55995352 | AA8: =Sugar!AA72 -> 1.5545736e+08 | AB8: =Sugar!AB72 -> 2.264666e+08 | AC8: =SUM(Y8:AB8) -> 5.0013638e+08
B9: Press Mud | E9: =Sugar!E74 -> 0 | F9: =Sugar!F74 -> 0 | G9: =Sugar!G74 -> 9072000 | H9: =Sugar!H74 -> 11088000 | I9: =SUM(E9:H9) -> 20160000 | J9: =Sugar!J74 -> 0 | K9: =Sugar!K74 -> 0 | L9: =Sugar!L74 -> 9720000 | M9: =Sugar!M74 -> 14040000 | N9: =SUM(J9:M9) -> 23760000 | O9: =Sugar!O74 -> 0 | P9: =Sugar!P74 -> 0 | Q9: =Sugar!Q74 -> 11520000 | R9: =Sugar!R74 -> 16128000 | S9: =SUM(O9:R9) -> 27648000 | T9: =Sugar!T74 -> 0 | U9: =Sugar!U74 -> 0 | V9: =Sugar!V74 -> 12528000 | W9: =Sugar!W74 -> 20044800 | X9: =SUM(T9:W9) -> 32572800 | Y9: =Sugar!Y74 -> 0 | Z9: =Sugar!Z74 -> 0 | AA9: =Sugar!AA74 -> 13680000 | AB9: =Sugar!AB74 -> 24624000 | AC9: =SUM(Y9:AB9) -> 38304000
B10: Bagasse | E10: =Sugar!E73 -> 0 | F10: =Sugar!F73 -> 0 | G10: =Sugar!G73 -> 0 | H10: =Sugar!H73 -> 0 | I10: =SUM(E10:H10) -> 0 | J10: =Sugar!J73 -> 0 | K10: =Sugar!K73 -> 0 | L10: =Sugar!L73 -> 0 | M10: =Sugar!M73 -> 0 | N10: =SUM(J10:M10) -> 0 | O10: =Sugar!O73 -> 0 | P10: =Sugar!P73 -> 0 | Q10: =Sugar!Q73 -> 0 | R10: =Sugar!R73 -> 0 | S10: =SUM(O10:R10) -> 0 | T10: =Sugar!T73 -> 0 | U10: =Sugar!U73 -> 0 | V10: =Sugar!V73 -> 0 | W10: =Sugar!W73 -> 0 | X10: =SUM(T10:W10) -> 0 | Y10: =Sugar!Y73 -> 0 | Z10: =Sugar!Z73 -> 0 | AA10: =Sugar!AA73 -> 0 | AB10: =Sugar!AB73 -> 0 | AC10: =SUM(Y10:AB10) -> 0
A12: # | B12: Ethanol Sale | E12: =Ethanol!E31 -> 0 | F12: =Ethanol!F31 -> 0 | G12: =Ethanol!G31 -> 2028068850 | H12: =Ethanol!H31 -> 2.1018168e+09 | I12: =SUM(E12:H12) -> 4.1298857e+09 | J12: =Ethanol!J31 -> 2.1044986e+09 | K12: =Ethanol!K31 -> 2.1045961e+09 | L12: =Ethanol!L31 -> 2.1617283e+09 | M12: =Ethanol!M31 -> 2.1638059e+09 | N12: =SUM(J12:M12) -> 8.5346288e+09 | O12: =Ethanol!O31 -> 2.1638814e+09 | P12: =Ethanol!P31 -> 2.1638841e+09 | Q12: =Ethanol!Q31 -> 2.2210129e+09 | R12: =Ethanol!R31 -> 2.2230904e+09 | S12: =SUM(O12:R12) -> 8.7718688e+09 | T12: =Ethanol!T31 -> 2.2231659e+09 | U12: =Ethanol!U31 -> 2.2231686e+09 | V12: =Ethanol!V31 -> 2.2802974e+09 | W12: =Ethanol!W31 -> 2.2823749e+09 | X12: =SUM(T12:W12) -> 9.0090068e+09 | Y12: =Ethanol!Y31 -> 2.2824504e+09 | Z12: =Ethanol!Z31 -> 2.2824531e+09 | AA12: =Ethanol!AA31 -> 2.3395819e+09 | AB12: =Ethanol!AB31 -> 2.3416594e+09 | AC12: =SUM(Y12:AB12) -> 9.2461448e+09
B13: DDGS Sale | E13: =Ethanol!E43 -> 0 | F13: =Ethanol!F43 -> 0 | G13: =Ethanol!G43 -> 3.7476595e+08 | H13: =Ethanol!H43 -> 3.7663978e+08 | I13: =SUM(E13:H13) -> 7.5140573e+08 | J13: =Ethanol!J43 -> 3.7852298e+08 | K13: =Ethanol!K43 -> 3.8041559e+08 | L13: =Ethanol!L43 -> 3.9308718e+08 | M13: =Ethanol!M43 -> 3.9505262e+08 | N13: =SUM(J13:M13) -> 1.5470784e+09 | O13: =Ethanol!O43 -> 3.9702788e+08 | P13: =Ethanol!P43 -> 3.9901302e+08 | Q13: =Ethanol!Q43 -> 4.1199461e+08 | R13: =Ethanol!R43 -> 4.1405458e+08 | S13: =SUM(O13:R13) -> 1.6220901e+09 | T13: =Ethanol!T43 -> 4.1612486e+08 | U13: =Ethanol!U43 -> 4.1820548e+08 | V13: =Ethanol!V43 -> 4.3150441e+08 | W13: =Ethanol!W43 -> 4.3366194e+08 | X13: =SUM(T13:W13) -> 1.6994967e+09 | Y13: =Ethanol!Y43 -> 4.3583025e+08 | Z13: =Ethanol!Z43 -> 4.380094e+08 | AA13: =Ethanol!AA43 -> 4.516332e+08 | AB13: =Ethanol!AB43 -> 4.5389136e+08 | AC13: =SUM(Y13:AB13) -> 1.7793642e+09
A15: # | B15: Sale of MAEQ Quota | D15: 5000000 | E15: =$D$15/4 -> 1250000 | F15: =$D$15/4 -> 1250000 | G15: =$D$15/4 -> 1250000 | H15: =$D$15/4 -> 1250000 | I15: =SUM(E15:H15) -> 5000000 | J15: =$D$15/4 -> 1250000 | K15: =$D$15/4 -> 1250000 | L15: =$D$15/4 -> 1250000 | M15: =$D$15/4 -> 1250000 | N15: =SUM(J15:M15) -> 5000000 | O15: =$D$15/4 -> 1250000 | P15: =$D$15/4 -> 1250000 | Q15: =$D$15/4 -> 1250000 | R15: =$D$15/4 -> 1250000 | S15: =SUM(O15:R15) -> 5000000 | T15: =$D$15/4 -> 1250000 | U15: =$D$15/4 -> 1250000 | V15: =$D$15/4 -> 1250000 | W15: =$D$15/4 -> 1250000 | X15: =SUM(T15:W15) -> 5000000 | Y15: =$D$15/4 -> 1250000 | Z15: =$D$15/4 -> 1250000 | AA15: =$D$15/4 -> 1250000 | AB15: =$D$15/4 -> 1250000 | AC15: =SUM(Y15:AB15) -> 5000000
A17: # | B17: Total Sales | E17: =SUM(E7:E10,E12:E13,E15:E15) -> 8.3111429e+08 | F17: =SUM(F7:F10,F12:F13,F15:F15) -> 9.8143143e+08 | G17: =SUM(G7:G10,G12:G13,G15:G15) -> 3.1098594e+09 | H17: =SUM(H7:H10,H12:H13,H15:H15) -> 3.1883638e+09 | I17: =SUM(I7:I10,I12:I13,I15) -> 8.1107688e+09 | J17: =SUM(J7:J10,J12:J13,J15:J15) -> 3.2089692e+09 | K17: =SUM(K7:K10,K12:K13,K15:K15) -> 3.1384896e+09 | L17: =SUM(L7:L10,L12:L13,L15:L15) -> 3.3325004e+09 | M17: =SUM(M7:M10,M12:M13,M15:M15) -> 3.4256172e+09 | N17: =SUM(J17:M17) -> 1.3105576e+10 | O17: =SUM(O7:O10,O12:O13,O15:O15) -> 3.3363273e+09 | P17: =SUM(P7:P10,P12:P13,P15:P15) -> 3.2608984e+09 | Q17: =SUM(Q7:Q10,Q12:Q13,Q15:Q15) -> 3.5494296e+09 | R17: =SUM(R7:R10,R12:R13,R15:R15) -> 3.6373706e+09 | S17: =SUM(O17:R17) -> 1.3784026e+10 | T17: =SUM(T7:T10,T12:T13,T15:T15) -> 3.5342393e+09 | U17: =SUM(U7:U10,U12:U13,U15:U15) -> 3.4469528e+09 | V17: =SUM(V7:V10,V12:V13,V15:V15) -> 3.7114671e+09 | W17: =SUM(W7:W10,W12:W13,W15:W15) -> 3.9300819e+09 | X17: =SUM(T17:W17) -> 1.4622741e+10 | Y17: =SUM(Y7:Y10,Y12:Y13,Y15:Y15) -> 3.8030908e+09 | Z17: =SUM(Z7:Z10,Z12:Z13,Z15:Z15) -> 3.6969167e+09 | AA17: =SUM(AA7:AA10,AA12:AA13,AA15:AA15) -> 3.8892831e+09 | AB17: =SUM(AB7:AB10,AB12:AB13,AB15:AB15) -> 4.2598209e+09 | AC17: =SUM(Y17:AB17) -> 1.5649111e+10
A19: # | B19: Operating Cost
B20: Sugar Plant
B21: =Sugar!B78 -> Raw material (sugarcane) | E21: =Sugar!E78 -> 0 | F21: =Sugar!F78 -> 0 | G21: =Sugar!G78 -> 8.316e+08 | H21: =Sugar!H78 -> 1201200000 | I21: =SUM(E21:H21) -> 2032800000 | J21: =Sugar!J78 -> 0 | K21: =Sugar!K78 -> 0 | L21: =Sugar!L78 -> 2178000000 | M21: =Sugar!M78 -> 0 | N21: =SUM(J21:M21) -> 2178000000 | O21: =Sugar!O78 -> 0 | P21: =Sugar!P78 -> 0 | Q21: =Sugar!Q78 -> 2534400000 | R21: =Sugar!R78 -> 0 | S21: =SUM(O21:R21) -> 2534400000 | T21: =Sugar!T78 -> 0 | U21: =Sugar!U78 -> 0 | V21: =Sugar!V78 -> 2985840000 | W21: =Sugar!W78 -> 0 | X21: =SUM(T21:W21) -> 2985840000 | Y21: =Sugar!Y78 -> 0 | Z21: =Sugar!Z78 -> 0 | AA21: =Sugar!AA78 -> 3511200000 | AB21: =Sugar!AB78 -> 0 | AC21: =SUM(Y21:AB21) -> 3511200000
B22: =Sugar!B79 -> Labour Cost | E22: =Sugar!E79 -> 0 | F22: =Sugar!F79 -> 0 | G22: =Sugar!G79 -> 5040000 | H22: =Sugar!H79 -> 6160000 | I22: =SUM(E22:H22) -> 11200000 | J22: =Sugar!J79 -> 0 | K22: =Sugar!K79 -> 0 | L22: =Sugar!L79 -> 5400000 | M22: =Sugar!M79 -> 7800000 | N22: =SUM(J22:M22) -> 13200000 | O22: =Sugar!O79 -> 0 | P22: =Sugar!P79 -> 0 | Q22: =Sugar!Q79 -> 6400000 | R22: =Sugar!R79 -> 8960000 | S22: =SUM(O22:R22) -> 15360000 | T22: =Sugar!T79 -> 0 | U22: =Sugar!U79 -> 0 | V22: =Sugar!V79 -> 6960000 | W22: =Sugar!W79 -> 11136000 | X22: =SUM(T22:W22) -> 18096000 | Y22: =Sugar!Y79 -> 0 | Z22: =Sugar!Z79 -> 0 | AA22: =Sugar!AA79 -> 7600000 | AB22: =Sugar!AB79 -> 13680000 | AC22: =SUM(Y22:AB22) -> 21280000
B23: =Sugar!B80 -> Power Cost | E23: =Sugar!E80 -> 0 | F23: =Sugar!F80 -> 0 | G23: =Sugar!G80 -> -51480000 | H23: =Sugar!H80 -> -62920000 | I23: =SUM(E23:H23) -> -114400000 | J23: =Sugar!J80 -> 0 | K23: =Sugar!K80 -> 0 | L23: =Sugar!L80 -> -51480000 | M23: =Sugar!M80 -> -74360000 | N23: =SUM(J23:M23) -> -125840000 | O23: =Sugar!O80 -> 0 | P23: =Sugar!P80 -> 0 | Q23: =Sugar!Q80 -> -57200000 | R23: =Sugar!R80 -> -80080000 | S23: =SUM(O23:R23) -> -137280000 | T23: =Sugar!T80 -> 0 | U23: =Sugar!U80 -> 0 | V23: =Sugar!V80 -> -57200000 | W23: =Sugar!W80 -> -91520000 | X23: =SUM(T23:W23) -> -148720000 | Y23: =Sugar!Y80 -> 0 | Z23: =Sugar!Z80 -> 0 | AA23: =Sugar!AA80 -> -57200000 | AB23: =Sugar!AB80 -> -102960000 | AC23: =SUM(Y23:AB23) -> -160160000
B24: =Sugar!B81 -> Salary for dedicated Staff | E24: =Sugar!E81 -> 4439070 | F24: =Sugar!F81 -> 4550046.8 | G24: =Sugar!G81 -> 4663797.9 | H24: =Sugar!H81 -> 4780392.9 | I24: =SUM(E24:H24) -> 18433308 | J24: =Sugar!J81 -> 4899902.7 | K24: =Sugar!K81 -> 5022400.3 | L24: =Sugar!L81 -> 5147960.3 | M24: =Sugar!M81 -> 5276659.3 | N24: =SUM(J24:M24) -> 20346922 | O24: =Sugar!O81 -> 5408575.8 | P24: =Sugar!P81 -> 5543790.1 | Q24: =Sugar!Q81 -> 5682384.9 | R24: =Sugar!R81 -> 5824444.5 | S24: =SUM(O24:R24) -> 22459195 | T24: =Sugar!T81 -> 5970055.6 | U24: =Sugar!U81 -> 6119307 | V24: =Sugar!V81 -> 6272289.7 | W24: =Sugar!W81 -> 6429096.9 | X24: =SUM(T24:W24) -> 24790749 | Y24: =Sugar!Y81 -> 6589824.4 | Z24: =Sugar!Z81 -> 6754570 | AA24: =Sugar!AA81 -> 6923434.2 | AB24: =Sugar!AB81 -> 7096520.1 | AC24: =SUM(Y24:AB24) -> 27364349
B25: Change in Inventory | E25: =-(BS!E142-BS!D142+BS!E143-BS!D143+BS!E144-BS!D144+BS!E145-BS!D145+BS!E152-BS!D152) -> 5.9444961e+08 | F25: =-(BS!F142-BS!E142+BS!F143-BS!E143+BS!F144-BS!E144+BS!F145-BS!E145+BS!F152-BS!E152) -> 781625000 | G25: =-(BS!G142-BS!F142+BS!G143-BS!F143+BS!G144-BS!F144+BS!G145-BS!F145+BS!G152-BS!F152) -> -2.712165e+08 | H25: =-(BS!H142-BS!G142+BS!H143-BS!G143+BS!H144-BS!G144+BS!H145-BS!G145+BS!H152-BS!G152) -> -6.6178514e+08 | I25: =SUM(E25:H25) -> 4.4307297e+08 | J25: =-(BS!I142-BS!H142+BS!I143-BS!H143+BS!I144-BS!H144+BS!I145-BS!H145+BS!I152-BS!H152) -> 5.8117939e+08 | K25: =-(BS!J142-BS!I142+BS!J143-BS!I143+BS!J144-BS!I144+BS!J145-BS!I145+BS!J152-BS!I152) -> 5.2306145e+08 | L25: =-(BS!K142-BS!J142+BS!K143-BS!J143+BS!K144-BS!J144+BS!K145-BS!J145+BS!K152-BS!J152) -> -1.6796226e+09 | M25: =-(BS!L142-BS!K142+BS!L143-BS!K143+BS!L144-BS!K144+BS!L145-BS!K145+BS!L152-BS!K152) -> 6.2506919e+08 | N25: =SUM(J25:M25) -> 49687454 | O25: =-(BS!M142-BS!L142+BS!M143-BS!L143+BS!M144-BS!L144+BS!M145-BS!L145+BS!M152-BS!L152) -> 5.5633566e+08 | P25: =-(BS!N142-BS!M142+BS!N143-BS!M143+BS!N144-BS!M144+BS!N145-BS!M145+BS!N152-BS!M152) -> 5.007021e+08 | Q25: =-(BS!O142-BS!N142+BS!O143-BS!N143+BS!O144-BS!N144+BS!O145-BS!N145+BS!O152-BS!N152) -> -1.9518165e+09 | R25: =-(BS!P142-BS!O142+BS!P143-BS!O143+BS!P144-BS!O144+BS!P145-BS!O145+BS!P152-BS!O152) -> 7.1721447e+08 | S25: =SUM(O25:R25) -> -1.7756424e+08 | T25: =-(BS!Q142-BS!P142+BS!Q143-BS!P143+BS!Q144-BS!P144+BS!Q145-BS!P145+BS!Q152-BS!P152) -> 6.4511779e+08 | U25: =-(BS!R142-BS!Q142+BS!R143-BS!Q143+BS!R144-BS!Q144+BS!R145-BS!Q145+BS!R152-BS!Q152) -> 5.8060601e+08 | V25: =-(BS!S142-BS!R142+BS!S143-BS!R143+BS!S144-BS!R144+BS!S145-BS!R145+BS!S152-BS!R152) -> -2.3729225e+09 | W25: =-(BS!T142-BS!S142+BS!T143-BS!S143+BS!T144-BS!S144+BS!T145-BS!S145+BS!T152-BS!S152) -> 8.6567018e+08 | X25: =SUM(T25:W25) -> -2.8152856e+08 | Y25: =-(BS!U142-BS!T142+BS!U143-BS!T143+BS!U144-BS!T144+BS!U145-BS!T145+BS!U152-BS!T152) -> 7.8588207e+08 | Z25: =-(BS!V142-BS!U142+BS!V143-BS!U143+BS!V144-BS!U144+BS!V145-BS!U145+BS!V152-BS!U152) -> 7.0729386e+08 | AA25: =-(BS!W142-BS!V142+BS!W143-BS!V143+BS!W144-BS!V144+BS!W145-BS!V145+BS!W152-BS!V152) -> -2.8563663e+09 | AB25: =-(BS!X142-BS!W142+BS!X143-BS!W143+BS!X144-BS!W144+BS!X145-BS!W145+BS!X152-BS!W152) -> 1.0548458e+09 | AC25: =SUM(Y25:AB25) -> -3.0834456e+08
B26: =Sugar!B82 -> Other Cost | E26: =Sugar!E82 -> 0 | F26: =Sugar!F82 -> 0 | G26: =Sugar!G82 -> 8820000 | H26: =Sugar!H82 -> 10780000 | I26: =SUM(E26:H26) -> 19600000 | J26: =Sugar!J82 -> 0 | K26: =Sugar!K82 -> 0 | L26: =Sugar!L82 -> 9450000 | M26: =Sugar!M82 -> 13650000 | N26: =SUM(J26:M26) -> 23100000 | O26: =Sugar!O82 -> 0 | P26: =Sugar!P82 -> 0 | Q26: =Sugar!Q82 -> 11200000 | R26: =Sugar!R82 -> 15680000 | S26: =SUM(O26:R26) -> 26880000 | T26: =Sugar!T82 -> 0 | U26: =Sugar!U82 -> 0 | V26: =Sugar!V82 -> 12180000 | W26: =Sugar!W82 -> 19488000 | X26: =SUM(T26:W26) -> 31668000 | Y26: =Sugar!Y82 -> 0 | Z26: =Sugar!Z82 -> 0 | AA26: =Sugar!AA82 -> 13300000 | AB26: =Sugar!AB82 -> 23940000 | AC26: =SUM(Y26:AB26) -> 37240000
B27: Cost of Material Consumed -Suger Plant | E27: =SUM(E21:E26) -> 5.9888868e+08 | F27: =SUM(F21:F26) -> 7.8617505e+08 | G27: =SUM(G21:G26) -> 5.274273e+08 | H27: =SUM(H21:H26) -> 4.9821525e+08 | I27: =SUM(I21:I26) -> 2.4107063e+09 | J27: =SUM(J21:J26) -> 5.8607929e+08 | K27: =SUM(K21:K26) -> 5.2808385e+08 | L27: =SUM(L21:L26) -> 4.6689538e+08 | ... AC27: =SUM(AC21:AC26) -> 3.1285798e+09
A28: # | B28: Ethanol plant
B29: =Ethanol!B47 -> Cost of Corn Purchase | E29: =Ethanol!E47 -> 0 | F29: =Ethanol!F47 -> 0 | G29: =Ethanol!G47 -> 1.9192045e+09 | H29: =Ethanol!H47 -> 1.8735092e+09 | I29: =SUM(E29:H29) -> 3.7927137e+09 | J29: =Ethanol!J47 -> 1.8735092e+09 | K29: =Ethanol!K47 -> 1.8735092e+09 | L29: =Ethanol!L47 -> 7.1413459e+09 | M29: =Ethanol!M47 -> 0 | N29: =SUM(J29:M29) -> 1.0888364e+10 | O29: =Ethanol!O47 -> 0 | P29: =Ethanol!P47 -> 0 | Q29: =Ethanol!Q47 -> 7.3369993e+09 | R29: =Ethanol!R47 -> 0 | S29: =SUM(O29:R29) -> 7.3369993e+09 | T29: =Ethanol!T47 -> 0 | U29: =Ethanol!U47 -> 0 | V29: =Ethanol!V47 -> 7.5326526e+09 | W29: =Ethanol!W47 -> 0 | X29: =SUM(T29:W29) -> 7.5326526e+09 | Y29: =Ethanol!Y47 -> 0 | Z29: =Ethanol!Z47 -> 0 | AA29: =Ethanol!AA47 -> 7.7283059e+09 | AB29: =Ethanol!AB47 -> 0 | AC29: =SUM(Y29:AB29) -> 7.7283059e+09
B30: =Ethanol!B48 -> Labour Cost | E30: =Ethanol!E48 -> 0 | F30: =Ethanol!F48 -> 0 | G30: =Ethanol!G48 -> 4569534.6 | H30: =Ethanol!H48 -> 4569534.6 | I30: =SUM(E30:H30) -> 9139069.3 | J30: =Ethanol!J48 -> 4569534.6 | K30: =Ethanol!K48 -> 4569534.6 | L30: =Ethanol!L48 -> 4698253.9 | M30: =Ethanol!M48 -> 4698253.9 | N30: =SUM(J30:M30) -> 18535577 | O30: =Ethanol!O48 -> 4698253.9 | P30: =Ethanol!P48 -> 4698253.9 | Q30: =Ethanol!Q48 -> 4826973.2 | R30: =Ethanol!R48 -> 4826973.2 | S30: =SUM(O30:R30) -> 19050454 | T30: =Ethanol!T48 -> 4826973.2 | U30: =Ethanol!U48 -> 4826973.2 | V30: =Ethanol!V48 -> 4955692.5 | W30: =Ethanol!W48 -> 4955692.5 | X30: =SUM(T30:W30) -> 19565331 | Y30: =Ethanol!Y48 -> 4955692.5 | Z30: =Ethanol!Z48 -> 4955692.5 | AA30: =Ethanol!AA48 -> 5084411.8 | AB30: =Ethanol!AB48 -> 5084411.8 | AC30: =SUM(Y30:AB30) -> 20080208
B31: =Ethanol!B49 -> Power Cost | E31: =Ethanol!E49 -> 0 | F31: =Ethanol!F49 -> 0 | G31: =Ethanol!G49 -> -28737500 | H31: =Ethanol!H49 -> -28737500 | I31: =SUM(E31:H31) -> -57475000 | J31: =Ethanol!J49 -> -28737500 | K31: =Ethanol!K49 -> -28737500 | L31: =Ethanol!L49 -> -28737500 | M31: =Ethanol!M49 -> -28737500 | N31: =SUM(J31:M31) -> -114950000 | O31: =Ethanol!O49 -> -28737500 | P31: =Ethanol!P49 -> 731600.71 | Q31: =Ethanol!Q49 -> -28737500 | R31: =Ethanol!R49 -> -28737500 | S31: =SUM(O31:R31) -> -85480899 | T31: =Ethanol!T49 -> -28737500 | U31: =Ethanol!U49 -> 22382500 | V31: =Ethanol!V49 -> -28737500 | W31: =Ethanol!W49 -> -28737500 | X31: =SUM(T31:W31) -> -63830000 | Y31: =Ethanol!Y49 -> -28737500 | Z31: =Ethanol!Z49 -> -28737500 | AA31: =Ethanol!AA49 -> -28737500 | AB31: =Ethanol!AB49 -> -28737500 | AC31: =SUM(Y31:AB31) -> -114950000
B32: =Ethanol!B50 -> Salary for dedicated Staff | E32: =Ethanol!E50 -> 3465525 | F32: =Ethanol!F50 -> 3552163.1 | G32: =Ethanol!G50 -> 4610168.8 | H32: =Ethanol!H50 -> 5139352.8 | I32: =SUM(E32:H32) -> 16767210 | J32: =Ethanol!J50 -> 5267836.6 | K32: =Ethanol!K50 -> 5399532.6 | L32: =Ethanol!L50 -> 5534520.9 | M32: =Ethanol!M50 -> 5672883.9 | N32: =SUM(J32:M32) -> 21874774 | O32: =Ethanol!O50 -> 5814706 | P32: =Ethanol!P50 -> 5960073.6 | Q32: =Ethanol!Q50 -> 6109075.5 | R32: =Ethanol!R50 -> 6261802.4 | S32: =SUM(O32:R32) -> 24145657 | T32: =Ethanol!T50 -> 6418347.4 | U32: =Ethanol!U50 -> 6578806.1 | V32: =Ethanol!V50 -> 6743276.3 | W32: =Ethanol!W50 -> 6911858.2 | X32: =SUM(T32:W32) -> 26652288 | Y32: =Ethanol!Y50 -> 7084654.6 | Z32: =Ethanol!Z50 -> 7261771 | AA32: =Ethanol!AA50 -> 7443315.3 | AB32: =Ethanol!AB50 -> 7629398.1 | AC32: =SUM(Y32:AB32) -> 29419139
B33: Change in Inventory | E33: =-(BS!E140-BS!D140+BS!E141-BS!D141+BS!E153-BS!D153) -> 0 | F33: =-(BS!F140-BS!E140+BS!F141-BS!E141+BS!F153-BS!E153) -> 0 | G33: =-(BS!G140-BS!F140+BS!G141-BS!F141+BS!G153-BS!F153) -> -70514455 | H33: =-(BS!H140-BS!G140+BS!H141-BS!G141+BS!H153-BS!G153) -> -2564162 | I33: =SUM(E33:H33) -> -73078617 | J33: =-(BS!I140-BS!H140+BS!H141-BS!H141+BS!I153-BS!H153) -> 5129467.2 | K33: =-(BS!J140-BS!I140+BS!J141-BS!I141+BS!J153-BS!I153) -> -3148.6182 | L33: =-(BS!K140-BS!J140+BS!K141-BS!J141+BS!K153-BS!J153) -> -5.0759589e+09 | M33: =-(BS!L140-BS!K140+BS!L141-BS!K141+BS!L153-BS!K153) -> 1.6913043e+09 | N33: =SUM(J33:M33) -> -3.3795282e+09 | O33: =-(BS!M140-BS!L140+BS!L141-BS!L141+BS!M153-BS!L153) -> 1.6910748e+09 | P33: =-(BS!N140-BS!M140+BS!N141-BS!M141+BS!N153-BS!M153) -> 1.6913713e+09 | Q33: =-(BS!O140-BS!N140+BS!O141-BS!N141+BS!O153-BS!N153) -> -5.2149834e+09 | R33: =-(BS!P140-BS!O140+BS!P141-BS!O141+BS!P153-BS!O153) -> 1.737643e+09 | S33: =SUM(O33:R33) -> -94894246 | T33: =-(BS!Q140-BS!P140+BS!P141-BS!P141+BS!Q153-BS!P153) -> 1.7374922e+09 | U33: =-(BS!R140-BS!Q140+BS!R141-BS!Q141+BS!R153-BS!Q153) -> 1.7377103e+09 | V33: =-(BS!S140-BS!R140+BS!S141-BS!R141+BS!S153-BS!R153) -> -5.4729424e+09 | W33: =-(BS!T140-BS!S140+BS!T141-BS!S141+BS!T153-BS!S153) -> 1.8236273e+09 | X33: =SUM(T33:W33) -> -1.7411264e+08 | Y33: =-(BS!U140-BS!T140+BS!T141-BS!T141+BS!U153-BS!T153) -> 1.8241576e+09 | Z33: =-(BS!V140-BS!U140+BS!V141-BS!U141+BS!V153-BS!U153) -> 1.8236947e+09 | AA33: =-(BS!W140-BS!V140+BS!W141-BS!V141+BS!W153-BS!V153) -> -5.6150368e+09 | AB33: =-(BS!X140-BS!W140+BS!X141-BS!W141+BS!X153-BS!W153) -> 1.8709964e+09 | AC33: =SUM(Y33:AB33) -> -96188114
B34: =Ethanol!B51 -> Other Cost | E34: =Ethanol!E51 -> 0 | F34: =Ethanol!F51 -> 0 | G34: =Ethanol!G51 -> 58575000 | H34: =Ethanol!H51 -> 58575000 | I34: =SUM(E34:H34) -> 117150000 | J34: =Ethanol!J51 -> 58575000 | K34: =Ethanol!K51 -> 58575000 | L34: =Ethanol!L51 -> 60225000 | M34: =Ethanol!M51 -> 60225000 | N34: =SUM(J34:M34) -> 237600000 | O34: =Ethanol!O51 -> 60225000 | P34: =Ethanol!P51 -> 60225000 | Q34: =Ethanol!Q51 -> 61875000 | R34: =Ethanol!R51 -> 61875000 | S34: =SUM(O34:R34) -> 244200000 | T34: =Ethanol!T51 -> 61875000 | U34: =Ethanol!U51 -> 61875000 | V34: =Ethanol!V51 -> 63525000 | W34: =Ethanol!W51 -> 63525000 | X34: =SUM(T34:W34) -> 250800000 | Y34: =Ethanol!Y51 -> 63525000 | Z34: =Ethanol!Z51 -> 63525000 | AA34: =Ethanol!AA51 -> 65175000 | AB34: =Ethanol!AB51 -> 65175000 | AC34: =SUM(Y34:AB34) -> 257400000
B35: Cost of Material Consumed for Ethanol Plant | E35: =SUM(E29:E34) -> 3465525 | F35: =SUM(F29:F34) -> 3552163.1 | G35: =SUM(G29:G34) -> 1.8877073e+09 | H35: =SUM(H29:H34) -> 1.9104914e+09 | I35: =SUM(I29:I34) -> 3.8052164e+09 | J35: =SUM(J29:J34) -> 1.9183135e+09 | K35: =SUM(K29:K34) -> 1.9133126e+09 | L35: =SUM(L29:L34) -> 2.1071073e+09 | ... AC35: =SUM(AC29:AC34) -> 7.8240671e+09
B37: Salaries Corporate Employees | C37: 0.03 | E37: =Employee!E28 -> 6748395 | F37: =Employee!F28 -> 6917104.9 | G37: =Employee!G28 -> 7090032.5 | H37: =Employee!H28 -> 7267283.3 | I37: =SUM(E37:H37) -> 28022816 | J37: =Employee!J28 -> 7448965.4 | K37: =Employee!K28 -> 7635189.5 | L37: =Employee!L28 -> 7826069.3 | M37: =Employee!M28 -> 8021721 | N37: =SUM(J37:M37) -> 30931945 | O37: =Employee!O28 -> 8222264 | P37: =Employee!P28 -> 8427820.6 | Q37: =Employee!Q28 -> 8638516.1 | R37: =Employee!R28 -> 8854479 | S37: =SUM(O37:R37) -> 34143080 | T37: =Employee!T28 -> 9075841 | U37: =Employee!U28 -> 9302737 | V37: =Employee!V28 -> 9535305.5 | W37: =Employee!W28 -> 9773688.1 | X37: =SUM(T37:W37) -> 37687572 | Y37: =Employee!Y28 -> 10018030 | Z37: =Employee!Z28 -> 10268481 | AA37: =Employee!AA28 -> 10525193 | AB37: =Employee!AB28 -> 10788323 | AC37: =SUM(Y37:AB37) -> 41600027
B38: Research Expenses | C38: 0.1 | D38: Increase | E38: 1000000 | F38: =E38*(1+$C38/4) -> 1025000 | G38: =F38*(1+$C38/4) -> 1050625 | H38: =G38*(1+$C38/4) -> 1076890.6 | I38: =SUM(E38:H38) -> 4152515.6 | J38: =H38*(1+$C38/4) -> 1103812.9 | K38: =J38*(1+$C38/4) -> 1131408.2 | L38: =K38*(1+$C38/4) -> 1159693.4 | M38: =L38*(1+$C38/4) -> 1188685.8 | N38: =SUM(J38:M38) -> 4583600.3 | O38: =M38*(1+$C38/4) -> 1218402.9 | P38: =O38*(1+$C38/4) -> 1248863 | Q38: =P38*(1+$C38/4) -> 1280084.5 | R38: =Q38*(1+$C38/4) -> 1312086.7 | S38: =SUM(O38:R38) -> 5059437.1 | T38: =R38*(1+$C38/4) -> 1344888.8 | U38: =T38*(1+$C38/4) -> 1378511 | V38: =U38*(1+$C38/4) -> 1412973.8 | W38: =V38*(1+$C38/4) -> 1448298.2 | X38: =SUM(T38:W38) -> 5584671.9 | Y38: =W38*(1+$C38/4) -> 1484505.6 | Z38: =Y38*(1+$C38/4) -> 1521618.3 | AA38: =Z38*(1+$C38/4) -> 1559658.7 | AB38: =AA38*(1+$C38/4) -> 1598650.2 | AC38: =SUM(Y38:AB38) -> 6164432.8
B39: Misc Expenses | C39: 0.02 | D39: Increase | E39: 5000000 | F39: =E39*(1+$C$39) -> 5100000 | G39: =F39*(1+$C$39) -> 5202000 | H39: =G39*(1+$C$39) -> 5306040 | I39: =SUM(E39:H39) -> 20608040 | J39: =H39*(1+$C$39) -> 5412160.8 | K39: =J39*(1+$C$39) -> 5520404 | L39: =K39*(1+$C$39) -> 5630812.1 | M39: =L39*(1+$C$39) -> 5743428.3 | N39: =SUM(J39:M39) -> 22306805 | O39: =M39*(1+$C$39) -> 5858296.9 | P39: =O39*(1+$C$39) -> 5975462.8 | Q39: =P39*(1+$C$39) -> 6094972.1 | R39: =Q39*(1+$C$39) -> 6216871.5 | S39: =SUM(O39:R39) -> 24145603 | T39: =R39*(1+$C$39) -> 6341209 | U39: =T39*(1+$C$39) -> 6468033.2 | V39: =U39*(1+$C$39) -> 6597393.8 | W39: =V39*(1+$C$39) -> 6729341.7 | X39: =SUM(T39:W39) -> 26135978 | Y39: =W39*(1+$C$39) -> 6863928.5 | Z39: =Y39*(1+$C$39) -> 7001207.1 | AA39: =Z39*(1+$C$39) -> 7141231.2 | AB39: =AA39*(1+$C$39) -> 7284055.9 | AC39: =SUM(Y39:AB39) -> 28290423
B40: Sales and Logestics | C40: 0.03 | D40: On Ethanol | E40: =$C40*E12 -> 0 | F40: =$C40*F12 -> 0 | G40: =$C40*G12 -> 60842066 | H40: =$C40*H12 -> 63054504 | I40: =SUM(E40:H40) -> 1.2389657e+08 | J40: =$C40*J12 -> 63134957 | K40: =$C40*K12 -> 63137882 | L40: =$C40*L12 -> 64851849 | M40: =$C40*M12 -> 64914176 | N40: =SUM(J40:M40) -> 2.5603886e+08 | O40: =$C40*O12 -> 64916442 | P40: =$C40*P12 -> 64916524 | Q40: =$C40*Q12 -> 66630388 | R40: =$C40*R12 -> 66692711 | S40: =SUM(O40:R40) -> 2.6315607e+08 | T40: =$C40*T12 -> 66694977 | U40: =$C40*U12 -> 66695059 | V40: =$C40*V12 -> 68408923 | W40: =$C40*W12 -> 68471246 | X40: =SUM(T40:W40) -> 2.7027021e+08 | Y40: =$C40*Y12 -> 68473512 | Z40: =$C40*Z12 -> 68473594 | AA40: =$C40*AA12 -> 70187458 | AB40: =$C40*AB12 -> 70249781 | AC40: =SUM(Y40:AB40) -> 2.7738435e+08
A42: # | B42: Total Cost | E42: =E27+E35+SUM(E37:E40) -> 6.151026e+08 | F42: =F27+F35+SUM(F37:F40) -> 8.0276931e+08 | G42: =G27+G35+SUM(G37:G40) -> 2.4893193e+09 | H42: =H27+H35+SUM(H37:H40) -> 2.4854114e+09 | I42: =I27+I35+SUM(I37:I40) -> 6.3926026e+09 | J42: =J27+J35+SUM(J37:J40) -> 2.5814927e+09 | K42: =K27+K35+SUM(K37:K40) -> 2.5188214e+09 | L42: =L27+L35+SUM(L37:L40) -> 2.6534711e+09 | ... AC42: =AC27+AC35+SUM(AC37:AC40) -> 1.1306086e+10
A44: # | B44: EBITDA | E44: =E17-E42 -> 2.1601169e+08 | F44: =F17-F42 -> 1.7866211e+08 | G44: =G17-G42 -> 6.2054006e+08 | H44: =H17-H42 -> 7.0295237e+08 | I44: =SUM(E44:H44) -> 1.7181662e+09 | J44: =J17-J42 -> 6.2747651e+08 | K44: =K17-K42 -> 6.1966824e+08 | L44: =L17-L42 -> 6.7902929e+08 | M44: =M17-M42 -> 1.0351504e+09 | N44: =SUM(J44:M44) -> 2.9613244e+09 | O44: =O17-O42 -> 9.6129242e+08 | P44: =P17-P42 -> 9.1109761e+08 | Q44: =Q17-Q42 -> 7.520303e+08 | R44: =R17-R42 -> 1.1048263e+09 | S44: =SUM(O44:R44) -> 3.7292467e+09 | T44: =T17-T42 -> 1.0178195e+09 | U44: =U17-U42 -> 9.430096e+08 | V44: =V17-V42 -> 9.3818604e+08 | W44: =W17-W42 -> 1.1621738e+09 | X44: =SUM(T44:W44) -> 4.0611889e+09 | Y44: =Y17-Y42 -> 1.0527935e+09 | Z44: =Z17-Z42 -> 1.0249036e+09 | AA44: =AA17-AA42 -> 1.0121781e+09 | AB44: =AB17-AB42 -> 1.25315e+09 | AC44: =SUM(Y44:AB44) -> 4.3430253e+09
B46: Less: Depreciation | E46: =-(BS!E162+BS!E168) -> 45302310 | F46: =-(BS!F162+BS!F168) -> 43603473 | G46: =-(BS!G162+BS!G168) -> 1.1616368e+08 | H46: =-(BS!H162+BS!H168) -> 1.1180755e+08 | I46: =SUM(E46:H46) -> 3.1687701e+08 | J46: =-(BS!I162+BS!I168) -> 1.0761476e+08 | K46: =-(BS!J162+BS!J168) -> 1.0357921e+08 | L46: =-(BS!K162+BS!K168) -> 99694990 | M46: =-(BS!L162+BS!L168) -> 95956427 | N46: =SUM(J46:M46) -> 4.0684539e+08 | O46: =-(BS!M162+BS!M168) -> 92358061 | P46: =-(BS!N162+BS!N168) -> 88894634 | Q46: =-(BS!O162+BS!O168) -> 85561085 | R46: =-(BS!P162+BS!P168) -> 82352545 | S46: =SUM(O46:R46) -> 3.4916633e+08 | T46: =-(BS!Q162+BS!Q168) -> 79264324 | U46: =-(BS!R162+BS!R168) -> 76291912 | V46: =-(BS!S162+BS!S168) -> 73430965 | W46: =-(BS!T162+BS!T168) -> 70677304 | X46: =SUM(T46:W46) -> 2.9966451e+08 | Y46: =-(BS!U162+BS!U168) -> 68026905 | Z46: =-(BS!V162+BS!V168) -> 65475896 | AA46: =-(BS!W162+BS!W168) -> 63020550 | AB46: =-(BS!X162+BS!X168) -> 60657280 | AC46: =SUM(Y46:AB46) -> 2.5718063e+08
B47: less: interest | E47: =BS!E175 -> 93282407 | F47: =BS!F175 -> 98489477 | G47: =BS!G175 -> 95443826 | H47: =BS!H175 -> 92434099 | I47: =SUM(E47:H47) -> 3.7964981e+08 | J47: =BS!I175 -> 89457413 | K47: =BS!J175 -> 86510959 | L47: =BS!K175 -> 83592007 | M47: =BS!L175 -> 21408071 | N47: =SUM(J47:M47) -> 2.8096845e+08 | O47: =BS!M175 -> 20783039 | P47: =BS!N175 -> 20148630 | Q47: =BS!O175 -> 19504706 | R47: =BS!P175 -> 18851123 | S47: =SUM(O47:R47) -> 79287497 | T47: =BS!Q175 -> 18187736 | U47: =BS!R175 -> 17514398 | V47: =BS!S175 -> 16830960 | W47: =BS!T175 -> 16137270 | X47: =SUM(T47:W47) -> 68670364 | Y47: =BS!U175 -> 15433176 | Z47: =BS!V175 -> 14718519 | AA47: =BS!W175 -> 13993143 | AB47: =BS!X175 -> 13256887 | AC47: =SUM(Y47:AB47) -> 57401725
A49: # | B49: PBT | E49: =E44-E47-E46 -> 77426969 | F49: =F44-F47-F46 -> 36569164 | G49: =G44-G47-G46 -> 4.0893255e+08 | H49: =H44-H47-H46 -> 4.9871072e+08 | I49: =SUM(E49:H49) -> 1.0216394e+09 | J49: =J44-J47-J46 -> 4.3040433e+08 | K49: =K44-K47-K46 -> 4.2957807e+08 | L49: =L44-L47-L46 -> 4.9574229e+08 | M49: =M44-M47-M46 -> 9.1778587e+08 | N49: =SUM(J49:M49) -> 2.2735106e+09 | O49: =O44-O47-O46 -> 8.4815132e+08 | P49: =P44-P47-P46 -> 8.0205435e+08 | Q49: =Q44-Q47-Q46 -> 6.4696451e+08 | R49: =R44-R47-R46 -> 1.0036226e+09 | S49: =SUM(O49:R49) -> 3.3007928e+09 | T49: =T44-T47-T46 -> 9.2036746e+08 | U49: =U44-U47-U46 -> 8.4920329e+08 | V49: =V44-V47-V46 -> 8.4792411e+08 | W49: =W44-W47-W46 -> 1.0753592e+09 | X49: =SUM(T49:W49) -> 3.692854e+09 | Y49: =Y44-Y47-Y46 -> 9.6933345e+08 | Z49: =Z44-Z47-Z46 -> 9.4470923e+08 | AA49: =AA44-AA47-AA46 -> 9.3516445e+08 | AB49: =AB44-AB47-AB46 -> 1.1792358e+09 | AC49: =SUM(Y49:AB49) -> 4.0284429e+09
B51: less: tax | C51: 0.2517 | E51: =E49*$C$51 -> 19488368 | F51: =F49*$C$51 -> 9204458.6 | G51: =G49*$C$51 -> 1.0292832e+08 | H51: =H49*$C$51 -> 1.2552549e+08 | I51: =I49*($C51) -> 2.5714664e+08 | J51: =J49*$C$51 -> 1.0833277e+08 | K51: =K49*$C$51 -> 1.081248e+08 | L51: =L49*$C$51 -> 1.2477834e+08 | M51: =M49*$C$51 -> 2.310067e+08 | N51: =SUM(J51:M51) -> 5.7224261e+08 | O51: =O49*$C$51 -> 2.1347969e+08 | P51: =P49*$C$51 -> 2.0187708e+08 | Q51: =Q49*$C$51 -> 1.6284097e+08 | R51: =R49*$C$51 -> 2.5261182e+08 | S51: =SUM(O51:R51) -> 8.3080956e+08 | T51: =T49*$C$51 -> 2.3165649e+08 | U51: =U49*$C$51 -> 2.1374447e+08 | V51: =V49*$C$51 -> 2.134225e+08 | W51: =W49*$C$51 -> 2.7066791e+08 | X51: =SUM(T51:W51) -> 9.2949136e+08 | Y51: =Y49*$C$51 -> 2.4398123e+08 | Z51: =Z49*$C$51 -> 2.3778331e+08 | AA51: =AA49*$C$51 -> 2.3538089e+08 | AB51: =AB49*$C$51 -> 2.9681365e+08 | AC51: =SUM(Y51:AB51) -> 1.0139591e+09
A53: # | B53: PAT | E53: =E49-E51 -> 57938601 | F53: =F49-F51 -> 27364706 | G53: =G49-G51 -> 3.0600423e+08 | H53: =H49-H51 -> 3.7318523e+08 | I53: =SUM(E53:H53) -> 7.6449276e+08 | J53: =J49-J51 -> 3.2207156e+08 | K53: =K49-K51 -> 3.2145327e+08 | L53: =L49-L51 -> 3.7096396e+08 | M53: =M49-M51 -> 6.8677917e+08 | N53: =SUM(J53:M53) -> 1.701268e+09 | O53: =O49-O51 -> 6.3467164e+08 | P53: =P49-P51 -> 6.0017727e+08 | Q53: =Q49-Q51 -> 4.8412354e+08 | R53: =R49-R51 -> 7.5101083e+08 | S53: =SUM(O53:R53) -> 2.4699833e+09 | T53: =T49-T51 -> 6.8871097e+08 | U53: =U49-U51 -> 6.3545882e+08 | V53: =V49-V51 -> 6.3450161e+08 | W53: =W49-W51 -> 8.0469128e+08 | X53: =SUM(T53:W53) -> 2.7633627e+09 | Y53: =Y49-Y51 -> 7.2535222e+08 | Z53: =Z49-Z51 -> 7.0692591e+08 | AA53: =AA49-AA51 -> 6.9978356e+08 | AB53: =AB49-AB51 -> 8.8242216e+08 | AC53: =SUM(Y53:AB53) -> 3.0144838e+09
E54: =E53/E17 -> 0.069711954 | F54: =F53/F17 -> 0.027882443 | G54: =G53/G17 -> 0.098398091 | H54: =H53/H17 -> 0.117046 | I54: =I53/I17 -> 0.09425651 | J54: =J53/J17 -> 0.10036605 | K54: =K53/K17 -> 0.10242292 | L54: =L53/L17 -> 0.111317 | M54: =M53/M17 -> 0.20048334 | N54: =AVERAGE(J54:M54) -> 0.12864733 | O54: =O53/O17 -> 0.19023063 | P54: =P53/P17 -> 0.18405273 | Q54: =Q53/Q17 -> 0.13639474 | R54: =R53/R17 -> 0.2064708 | S54: =AVERAGE(O54:R54) -> 0.17928723 | T54: =T53/T17 -> 0.19486823 | U54: =U53/U17 -> 0.18435379 | V54: =V53/V17 -> 0.17095709 | W54: =W53/W17 -> 0.20475178 | X54: =AVERAGE(T54:W54) -> 0.18873273 | Y54: =Y53/Y17 -> 0.19072703 | Z54: =Z53/Z17 -> 0.19122041 | AA54: =AA53/AA17 -> 0.1799261 | AB54: =AB53/AB17 -> 0.20715006 | AC54: =AVERAGE(Y54:AB54) -> 0.1922559
B56: GP Suger | E56: =1-SUM(E21:E26)/SUM(E7:E10) -> 0.27832937 | F56: =1-SUM(F21:F26)/SUM(F7:F10) -> 0.19792905 | G56: =1-SUM(G21:G26)/SUM(G7:G10) -> 0.25269722 | H56: =1-SUM(H21:H26)/SUM(H7:H10) -> 0.29695871 | I56: =1-SUM(I21:I26)/SUM(I7:I10) -> 0.25237304 | J56: =1-SUM(J21:J26)/SUM(J7:J10) -> 0.19127756 | K56: =1-SUM(K21:K26)/SUM(K7:K10) -> 0.19033849 | L56: =1-SUM(L21:L26)/SUM(L7:L10) -> 0.39866773 | ... AC56: =1-SUM(AC21:AC26)/SUM(AC7:AC10) -> 0.32261331
B57: GP Ethanol | G57: =1-SUM(G29:G34)/SUM(G12:G13) -> 0.21438324 | H57: =1-SUM(H29:H34)/SUM(H12:H13) -> 0.22916083 | I57: =1-SUM(I29:I34)/SUM(I12:I13) -> 0.22044883 | J57: =1-SUM(J29:J34)/SUM(J12:J13) -> 0.22742775 | K57: =1-SUM(K29:K34)/SUM(K12:K13) -> 0.2300589 | L57: =1-SUM(L29:L34)/SUM(L12:L13) -> 0.1752409 | M57: =1-SUM(M29:M34)/SUM(M12:M13) -> 0.32268119 | N57: =1-SUM(N29:N34)/SUM(N12:N13) -> 0.23902804 | ... AC57: =1-SUM(AC29:AC34)/SUM(AC12:AC13) -> 0.29036681
A59: # | B59: Suger Plant
B60: Revenue | E60: =SUM(E7:E10) -> 8.2986429e+08 | F60: =SUM(F7:F10) -> 9.8018143e+08 | G60: =SUM(G7:G10) -> 7.0577457e+08 | H60: =SUM(H7:H10) -> 7.0865717e+08 | I60: =SUM(I7:I10) -> 3.2244775e+09 | J60: =SUM(J7:J10) -> 724697700 | K60: =SUM(K7:K10) -> 652227930 | L60: =SUM(L7:L10) -> 776434926 | ... AC60: =SUM(AC7:AC10) -> 4.6186024e+09
B61: =B21 -> Raw material (sugarcane) | E61: {=E21:E26} -> 0 | F61: {=F21:F26} -> 0 | G61: {=G21:G26} -> 8.316e+08 | H61: {=H21:H26} -> 1201200000 | I61: {=I21:I26} -> 2032800000 | J61: {=J21:J26} -> 0 | K61: {=K21:K26} -> 0 | L61: {=L21:L26} -> 2178000000 | ... AC61: {=AC21:AC26} -> 3511200000
B62: =B22 -> Labour Cost | E62: 0 | F62: 0 | G62: 5040000 | H62: 6160000 | I62: 11200000 | J62: 0 | K62: 0 | L62: 5400000 | M62: 7800000 | N62: 13200000 | O62: 0 | P62: 0 | Q62: 6400000 | R62: 8960000 | S62: 15360000 | T62: 0 | U62: 0 | V62: 6960000 | W62: 11136000 | X62: 18096000 | Y62: 0 | Z62: 0 | AA62: 7600000 | AB62: 13680000 | AC62: 21280000
B63: =B23 -> Power Cost | E63: 0 | F63: 0 | G63: -51480000 | H63: -62920000 | I63: -114400000 | J63: 0 | K63: 0 | L63: -51480000 | M63: -74360000 | N63: -125840000 | O63: 0 | P63: 0 | Q63: -57200000 | R63: -80080000 | S63: -137280000 | T63: 0 | U63: 0 | V63: -57200000 | W63: -91520000 | X63: -148720000 | Y63: 0 | Z63: 0 | AA63: -57200000 | AB63: -102960000 | AC63: -160160000
B64: =B24 -> Salary for dedicated Staff | E64: 4439070 | F64: 4550046.8 | G64: 4663797.9 | H64: 4780392.9 | I64: 18433308 | J64: 4899902.7 | K64: 5022400.3 | L64: 5147960.3 | M64: 5276659.3 | N64: 20346922 | O64: 5408575.8 | P64: 5543790.1 | Q64: 5682384.9 | R64: 5824444.5 | S64: 22459195 | T64: 5970055.6 | U64: 6119307 | V64: 6272289.7 | W64: 6429096.9 | X64: 24790749 | Y64: 6589824.4 | Z64: 6754570 | AA64: 6923434.2 | AB64: 7096520.1 | AC64: 27364349
B65: =B25 -> Change in Inventory | E65: 5.9444961e+08 | F65: 781625000 | G65: -2.712165e+08 | H65: -6.6178514e+08 | I65: 4.4307297e+08 | J65: 5.8117939e+08 | K65: 5.2306145e+08 | L65: -1.6796226e+09 | M65: 6.2506919e+08 | N65: 49687454 | O65: 5.5633566e+08 | P65: 5.007021e+08 | Q65: -1.9518165e+09 | R65: 7.1721447e+08 | S65: -1.7756424e+08 | T65: 6.4511779e+08 | U65: 5.8060601e+08 | V65: -2.3729225e+09 | W65: 8.6567018e+08 | X65: -2.8152856e+08 | Y65: 7.8588207e+08 | Z65: 7.0729386e+08 | AA65: -2.8563663e+09 | AB65: 1.0548458e+09 | AC65: -3.0834456e+08
B66: =B26 -> Other Cost | E66: 0 | F66: 0 | G66: 8820000 | H66: 10780000 | I66: 19600000 | J66: 0 | K66: 0 | L66: 9450000 | M66: 13650000 | N66: 23100000 | O66: 0 | P66: 0 | Q66: 11200000 | R66: 15680000 | S66: 26880000 | T66: 0 | U66: 0 | V66: 12180000 | W66: 19488000 | X66: 31668000 | Y66: 0 | Z66: 0 | AA66: 13300000 | AB66: 23940000 | AC66: 37240000
B68: =B61 -> Raw material (sugarcane) | E68: =E61/E$60 -> 0 | F68: =F61/F$60 -> 0 | G68: =G61/G$60 -> 1.1782799 | H68: =H61/H$60 -> 1.6950368 | I68: =I61/I$60 -> 0.63042773 | J68: =J61/J$60 -> 0 | K68: =K61/K$60 -> 0 | L68: =L61/L$60 -> 2.8051288 | ... AC68: =AC61/AC$60 -> 0.76022998
B69: =B62 -> Labour Cost | E69: =E62/E$60 -> 0 | F69: =F62/F$60 -> 0 | G69: =G62/G$60 -> 0.0071410904 | H69: =H62/H$60 -> 0.0086924965 | I69: =I62/I$60 -> 0.003473431 | J69: =J62/J$60 -> 0 | K69: =K62/K$60 -> 0 | L69: =L62/L$60 -> 0.0069548649 | ... AC69: =AC62/AC$60 -> 0.0046074544
B70: =B63 -> Power Cost | E70: =E63/E$60 -> 0 | F70: =F63/F$60 -> 0 | G70: =G63/G$60 -> -0.072941137 | H70: =H63/H$60 -> -0.088787643 | I70: =I63/I$60 -> -0.035478617 | J70: =J63/J$60 -> 0 | K70: =K63/K$60 -> 0 | L70: =L63/L$60 -> -0.066303045 | ... AC70: =AC63/AC$60 -> -0.034677157
B71: =B64 -> Salary for dedicated Staff | E71: =E64/E$60 -> 0.0053491518 | F71: =F64/F$60 -> 0.0046420455 | G71: =G64/G$60 -> 0.006608056 | H71: =H64/H$60 -> 0.0067457059 | I71: =I64/I$60 -> 0.0057166805 | J71: =J64/J$60 -> 0.0067613057 | K71: =K64/K$60 -> 0.0077003759 | L71: =L64/L$60 -> 0.0066302533 | ... AC71: =AC64/AC$60 -> 0.0059248115
B72: =B65 -> Change in Inventory | E72: =E65/E$60 -> 0.71632148 | F72: =F65/F$60 -> 0.7974289 | G72: =G65/G$60 -> -0.38428205 | H72: =H65/H$60 -> -0.93385796 | I72: =I65/I$60 -> 0.13740923 | J72: =J65/J$60 -> 0.80196114 | K72: =K65/K$60 -> 0.80196114 | L72: =L65/L$60 -> -2.1632497 | ... AC72: =AC65/AC$60 -> -0.066761443
B73: =B66 -> Other Cost | E73: =E66/E$60 -> 0 | F73: =F66/F$60 -> 0 | G73: =G66/G$60 -> 0.012496908 | H73: =H66/H$60 -> 0.015211869 | I73: =I66/I$60 -> 0.0060785043 | J73: =J66/J$60 -> 0 | K73: =K66/K$60 -> 0 | L73: =L66/L$60 -> 0.012171014 | ... AC73: =AC66/AC$60 -> 0.0080630453
A74: # | B74: Gross Profit | E74: =1-SUM(E68:E73) -> 0.27832937 | F74: =1-SUM(F68:F73) -> 0.19792905 | G74: =1-SUM(G68:G73) -> 0.25269722 | H74: =1-SUM(H68:H73) -> 0.29695871 | I74: =1-SUM(I68:I73) -> 0.25237304 | J74: =1-SUM(J68:J73) -> 0.19127756 | K74: =1-SUM(K68:K73) -> 0.19033849 | L74: =1-SUM(L68:L73) -> 0.39866773 | ... AC74: =1-SUM(AC68:AC73) -> 0.32261331
A76: # | B76: Ethanol Plant
B77: Revenue | E77: =SUM(E12:E13) -> 0 | F77: =SUM(F12:F13) -> 0 | G77: =SUM(G12:G13) -> 2.4028348e+09 | H77: =SUM(H12:H13) -> 2.4784566e+09 | I77: =SUM(I12:I13) -> 4.8812914e+09 | J77: =SUM(J12:J13) -> 2.4830215e+09 | K77: =SUM(K12:K13) -> 2.4850117e+09 | L77: =SUM(L12:L13) -> 2.5548155e+09 | ... AC77: =SUM(AC12:AC13) -> 1.1025509e+10
B78: =B29 -> Cost of Corn Purchase | E78: {=E29:E34} -> 0 | F78: {=F29:F34} -> 0 | G78: {=G29:G34} -> 1.9192045e+09 | H78: {=H29:H34} -> 1.8735092e+09 | I78: {=I29:I34} -> 3.7927137e+09 | J78: {=J29:J34} -> 1.8735092e+09 | K78: {=K29:K34} -> 1.8735092e+09 | L78: {=L29:L34} -> 7.1413459e+09 | ... AC78: {=AC29:AC34} -> 7.7283059e+09
B79: =B30 -> Labour Cost | E79: 0 | F79: 0 | G79: 4569534.6 | H79: 4569534.6 | I79: 9139069.3 | J79: 4569534.6 | K79: 4569534.6 | L79: 4698253.9 | M79: 4698253.9 | N79: 18535577 | O79: 4698253.9 | P79: 4698253.9 | Q79: 4826973.2 | R79: 4826973.2 | S79: 19050454 | T79: 4826973.2 | U79: 4826973.2 | V79: 4955692.5 | W79: 4955692.5 | X79: 19565331 | Y79: 4955692.5 | Z79: 4955692.5 | AA79: 5084411.8 | AB79: 5084411.8 | AC79: 20080208
B80: =B31 -> Power Cost | E80: 0 | F80: 0 | G80: -28737500 | H80: -28737500 | I80: -57475000 | J80: -28737500 | K80: -28737500 | L80: -28737500 | M80: -28737500 | N80: -114950000 | O80: -28737500 | P80: 731600.71 | Q80: -28737500 | R80: -28737500 | S80: -85480899 | T80: -28737500 | U80: 22382500 | V80: -28737500 | W80: -28737500 | X80: -63830000 | Y80: -28737500 | Z80: -28737500 | AA80: -28737500 | AB80: -28737500 | AC80: -114950000
B81: =B32 -> Salary for dedicated Staff | E81: 3465525 | F81: 3552163.1 | G81: 4610168.8 | H81: 5139352.8 | I81: 16767210 | J81: 5267836.6 | K81: 5399532.6 | L81: 5534520.9 | M81: 5672883.9 | N81: 21874774 | O81: 5814706 | P81: 5960073.6 | Q81: 6109075.5 | R81: 6261802.4 | S81: 24145657 | T81: 6418347.4 | U81: 6578806.1 | V81: 6743276.3 | W81: 6911858.2 | X81: 26652288 | Y81: 7084654.6 | Z81: 7261771 | AA81: 7443315.3 | AB81: 7629398.1 | AC81: 29419139
B82: =B33 -> Change in Inventory | E82: 0 | F82: 0 | G82: -70514455 | H82: -2564162 | I82: -73078617 | J82: 5129467.2 | K82: -3148.6182 | L82: -5.0759589e+09 | M82: 1.6913043e+09 | N82: -3.3795282e+09 | O82: 1.6910748e+09 | P82: 1.6913713e+09 | Q82: -5.2149834e+09 | R82: 1.737643e+09 | S82: -94894246 | T82: 1.7374922e+09 | U82: 1.7377103e+09 | V82: -5.4729424e+09 | W82: 1.8236273e+09 | X82: -1.7411264e+08 | Y82: 1.8241576e+09 | Z82: 1.8236947e+09 | AA82: -5.6150368e+09 | AB82: 1.8709964e+09 | AC82: -96188114
B83: =B34 -> Other Cost | E83: 0 | F83: 0 | G83: 58575000 | H83: 58575000 | I83: 117150000 | J83: 58575000 | K83: 58575000 | L83: 60225000 | M83: 60225000 | N83: 237600000 | O83: 60225000 | P83: 60225000 | Q83: 61875000 | R83: 61875000 | S83: 244200000 | T83: 61875000 | U83: 61875000 | V83: 63525000 | W83: 63525000 | X83: 250800000 | Y83: 63525000 | Z83: 63525000 | AA83: 65175000 | AB83: 65175000 | AC83: 257400000
B86: =B78 -> Cost of Corn Purchase | G86: =G78/G$77 -> 0.79872513 | H86: =H78/H$77 -> 0.7559177 | I86: =I78/I$77 -> 0.77698982 | J86: =J78/J$77 -> 0.75452797 | K86: =K78/K$77 -> 0.7539237 | L86: =L78/L$77 -> 2.7952492 | M86: =M78/M$77 -> 0 | N86: =N78/N$77 -> 1.080012 | ... AC86: =AC78/AC$77 -> 0.70094776
B87: =B79 -> Labour Cost | G87: =G79/G$77 -> 0.0019017265 | H87: =H79/H$77 -> 0.0018437017 | I87: =I79/I$77 -> 0.0018722646 | J87: =J79/J$77 -> 0.0018403121 | K87: =K79/K$77 -> 0.0018388383 | L87: =L79/L$77 -> 0.0018389797 | M87: =M79/M$77 -> 0.0018360742 | N87: =N79/N$77 -> 0.0018385356 | ... AC87: =AC79/AC$77 -> 0.00182125
B88: =B80 -> Power Cost | G88: =G80/G$77 -> -0.011959832 | H88: =H80/H$77 -> -0.011594918 | I88: =I80/I$77 -> -0.011774548 | J88: =J80/J$77 -> -0.011573601 | K88: =K80/K$77 -> -0.011564332 | L88: =L80/L$77 -> -0.011248366 | M88: =M80/M$77 -> -0.011230594 | N88: =N80/N$77 -> -0.011401839 | ... AC88: =AC80/AC$77 -> -0.010425822
B89: =B81 -> Salary for dedicated Staff | G89: =G81/G$77 -> 0.0019186374 | H89: =H81/H$77 -> 0.0020736102 | I89: =I81/I$77 -> 0.0034349946 | J89: =J81/J$77 -> 0.0021215429 | K89: =K81/K$77 -> 0.0021728399 | L89: =L81/L$77 -> 0.0021663094 | M89: =M81/M$77 -> 0.0022169588 | N89: =N81/N$77 -> 0.002169749 | ... AC89: =AC81/AC$77 -> 0.0026682794
B90: =B82 -> Change in Inventory | G90: =G82/G$77 -> -0.02934636 | H90: =H82/H$77 -> -0.0010345802 | I90: =I82/I$77 -> -0.014971165 | J90: =J82/J$77 -> 0.0020658167 | K90: =K82/K$77 -> -1.2670436e-06 | L90: =L82/L$77 -> -1.9868201 | M90: =M82/M$77 -> 0.66096048 | N90: =N82/N$77 -> -0.33521389 | ... AC90: =AC82/AC$77 -> -0.0087241427
B91: =B83 -> Other Cost | G91: =G83/G$77 -> 0.024377456 | H91: =H83/H$77 -> 0.02363366 | I91: =I83/I$77 -> 0.023999797 | J91: =J83/J$77 -> 0.02359021 | K91: =K83/K$77 -> 0.023571318 | L91: =L83/L$77 -> 0.023573131 | M91: =M83/M$77 -> 0.023535886 | N91: =N83/N$77 -> 0.023567437 | ... AC91: =AC83/AC$77 -> 0.023345861
B92: Gross Profit | G92: =1-SUM(G86:G91) -> 0.21438324 | H92: =1-SUM(H86:H91) -> 0.22916083 | I92: =1-SUM(I86:I91) -> 0.22044883 | J92: =1-SUM(J86:J91) -> 0.22742775 | K92: =1-SUM(K86:K91) -> 0.2300589 | L92: =1-SUM(L86:L91) -> 0.1752409 | M92: =1-SUM(M86:M91) -> 0.32268119 | N92: =1-SUM(N86:N91) -> 0.23902804 | ... AC92: =1-SUM(AC86:AC91) -> 0.29036681
G93: =G92*G77 -> 5.1512751e+08 | H93: =H92*H77 -> 5.6796517e+08 | I93: =I92*I77 -> 1.076075e+09 | J93: =J92*J77 -> 5.64708e+08 | K93: =K92*K77 -> 5.7169905e+08 | L93: =L92*L77 -> 4.4770817e+08 | M93: =M92*M77 -> 8.256955e+08 | N93: =N92*N77 -> 2.4098107e+09 | ... AC93: =AC92*AC77 -> 3.2014419e+09
B94: Sales Amount
B95: Sugar | I95: =I60+I15 -> 3.2294775e+09 | N95: =N60+N15 -> 3.0238693e+09 | O95: =O60+O15 -> 7.7541806e+08 | P95: =P60+P15 -> 6.9800125e+08 | Q95: =Q60+Q15 -> 9.1642206e+08 | R95: =R60+R15 -> 1.0002257e+09 | S95: =S60+S15 -> 3.3900671e+09 | T95: =T60+T15 -> 8.9494853e+08 | U95: =U60+U15 -> 8.0557867e+08 | ... AC95: =AC60+AC15 -> 4.6236024e+09
B96: Ethanol | I96: =I12 -> 4.1298857e+09 | N96: =N12 -> 8.5346288e+09 | O96: =O12 -> 2.1638814e+09 | P96: =P12 -> 2.1638841e+09 | Q96: =Q12 -> 2.2210129e+09 | R96: =R12 -> 2.2230904e+09 | S96: =S12 -> 8.7718688e+09 | T96: =T12 -> 2.2231659e+09 | U96: =U12 -> 2.2231686e+09 | ... AC96: =AC12 -> 9.2461448e+09
B97: DDGS | I97: =I13 -> 7.5140573e+08 | N97: =N13 -> 1.5470784e+09 | O97: =O13 -> 3.9702788e+08 | P97: =P13 -> 3.9901302e+08 | Q97: =Q13 -> 4.1199461e+08 | R97: =R13 -> 4.1405458e+08 | S97: =S13 -> 1.6220901e+09 | T97: =T13 -> 4.1612486e+08 | U97: =U13 -> 4.1820548e+08 | ... AC97: =AC13 -> 1.7793642e+09
B98: Power | I98: =-I80-I63 -> 171875000 | N98: =-N80-N63 -> 240790000 | O98: =-O80-O63 -> 28737500 | P98: =-P80-P63 -> -731600.71 | Q98: =-Q80-Q63 -> 85937500 | R98: =-R80-R63 -> 108817500 | S98: =-S80-S63 -> 2.227609e+08 | T98: =-T80-T63 -> 28737500 | U98: =-U80-U63 -> -22382500 | ... AC98: =-AC80-AC63 -> 275110000
B99: Total | I99: =SUM(I95:I98) -> 8.2826438e+09 | N99: =SUM(N95:N98) -> 1.3346366e+10 | O99: =SUM(O95:O98) -> 3.3650648e+09 | P99: =SUM(P95:P98) -> 3.2601668e+09 | Q99: =SUM(Q95:Q98) -> 3.6353671e+09 | R99: =SUM(R95:R98) -> 3.7461881e+09 | S99: =SUM(S95:S98) -> 1.4006787e+10 | T99: =SUM(T95:T98) -> 3.5629768e+09 | U99: =SUM(U95:U98) -> 3.4245703e+09 | ... AC99: =SUM(AC95:AC98) -> 1.5924221e+10
B101: Sugar Revenue | I101: =I95 -> 3.2294775e+09 | N101: =N95 -> 3.0238693e+09 | O101: =O95 -> 7.7541806e+08 | P101: =P95 -> 6.9800125e+08 | Q101: =Q95 -> 9.1642206e+08 | R101: =R95 -> 1.0002257e+09 | S101: =S95 -> 3.3900671e+09 | T101: =T95 -> 8.9494853e+08 | U101: =U95 -> 8.0557867e+08 | ... AC101: =AC95 -> 4.6236024e+09
B102: Sugar Gross Profit | I102: =I101*I56 -> 8.1503305e+08 | N102: =N101*N56 -> 8.617999e+08 | O102: =O101*O56 -> 2.1276681e+08 | P102: =P101*P56 -> 1.9084714e+08 | Q102: =Q101*Q56 -> 3.6700674e+08 | R102: =R101*R56 -> 3.3179144e+08 | S102: =S101*S56 -> 1.1024381e+09 | T102: =T101*T56 -> 2.4295002e+08 | U102: =U101*U56 -> 2.1794153e+08 | ... AC102: =AC101*AC56 -> 1.4916357e+09
B103: Sugar Gross Margin | I103: =I56 -> 0.25237304 | N103: =N56 -> 0.28499906 | O103: =O56 -> 0.2743898 | P103: =P56 -> 0.27341948 | Q103: =Q56 -> 0.40047786 | R103: =R56 -> 0.33171657 | S103: =S56 -> 0.32519655 | T103: =T56 -> 0.27146815 | U103: =U56 -> 0.27054035 | ... AC103: =AC56 -> 0.32261331
B104: Sugar EBITDA | I104: =I44-I118 -> 7.9237949e+08 | N104: =N44-N118 -> 8.3646373e+08 | O104: =O44-O118 -> 2.0602434e+08 | P104: =P44-P118 -> 1.8392929e+08 | Q104: =Q44-Q118 -> 3.5974936e+08 | R104: =R44-R118 -> 3.2443507e+08 | S104: =S44-S118 -> 1.0741381e+09 | T104: =T44-T118 -> 2.3547971e+08 | U104: =U44-U118 -> 2.1027872e+08 | ... AC104: =AC44-AC118 -> 1.4569951e+09
B105: Sugar EBITDA Margin | I105: =I104/I101 -> 0.24535842 | N105: =N104/N101 -> 0.27662033 | O105: =O104/O101 -> 0.26569453 | P105: =P104/P101 -> 0.26350854 | Q105: =Q104/Q101 -> 0.3925586 | R105: =R104/R101 -> 0.32436186 | S105: =S104/S101 -> 0.31684862 | T105: =T104/T101 -> 0.26312096 | U105: =U104/U101 -> 0.26102816 | ... AC105: =AC104/AC101 -> 0.3151212
B106: Sugar PAT | I106: =I53-I120 -> 3.8445317e+08 | N106: =N53-N120 -> 4.2004937e+08 | O106: =O53-O120 -> 1.2030262e+08 | P106: =P53-P120 -> 1.0499546e+08 | Q106: =Q53-Q120 -> 2.3775215e+08 | R106: =R53-R120 -> 2.1248248e+08 | S106: =S53-S120 -> 6.7553271e+08 | T106: =T53-T120 -> 1.4704012e+08 | U106: =U53-U120 -> 1.2927346e+08 | ... AC106: =AC53-AC120 -> 9.9610868e+08
B107: Sugar PAT Margin | I107: =I106/I101 -> 0.11904501 | N107: =N106/N101 -> 0.13891122 | O107: =O106/O101 -> 0.15514549 | P107: =P106/P101 -> 0.15042302 | Q107: =Q106/Q101 -> 0.25943521 | R107: =R106/R101 -> 0.21243454 | S107: =S106/S101 -> 0.19926824 | T107: =T106/T101 -> 0.16430008 | U107: =U106/U101 -> 0.16047279 | ... AC107: =AC106/AC101 -> 0.21543995
I108: Revenue | N108: Gross Profit | O108: 2.1276681e+08 | P108: 1.9084714e+08 | Q108: 3.6700674e+08 | R108: 3.3179144e+08 | S108: EBITDA | X108: EBITDA Margin | AC108: PAT | AD108: PAT Margin
I109: =(I101)*(1/10^7) -> 322.94775 | J109: =0*(1/10^7) -> 0 | K109: =0*(1/10^7) -> 0 | L109: =0*(1/10^7) -> 0 | M109: =0*(1/10^7) -> 0 | N109: =(I102)*(1/10^7) -> 81.503305 | O109: =0*(1/10^7) -> 0 | P109: =0*(1/10^7) -> 0 | Q109: =0*(1/10^7) -> 0 | R109: =0*(1/10^7) -> 0 | S109: =(I104)*(1/10^7) -> 79.237949 | X109: =S109/I109 -> 0.24535842 | AC109: =(I106)*(1/10^7) -> 38.445317 | AD109: =AC109/I109 -> 0.11904501
I110: =(N101)*(1/10^7) -> 302.38693 | J110: =0*(1/10^7) -> 0 | K110: =0*(1/10^7) -> 0 | L110: =0*(1/10^7) -> 0 | M110: =0*(1/10^7) -> 0 | N110: =(N102)*(1/10^7) -> 86.17999 | O110: =0*(1/10^7) -> 0 | P110: =0*(1/10^7) -> 0 | Q110: =0*(1/10^7) -> 0 | R110: =0*(1/10^7) -> 0 | S110: =(N104)*(1/10^7) -> 83.646373 | X110: =S110/I110 -> 0.27662033 | AC110: =(N106)*(1/10^7) -> 42.004937 | AD110: =AC110/I110 -> 0.13891122
I111: =(S101)*(1/10^7) -> 339.00671 | J111: =0*(1/10^7) -> 0 | K111: =0*(1/10^7) -> 0 | L111: =0*(1/10^7) -> 0 | M111: =0*(1/10^7) -> 0 | N111: =(S102)*(1/10^7) -> 110.24381 | O111: =0*(1/10^7) -> 0 | P111: =0*(1/10^7) -> 0 | Q111: =0*(1/10^7) -> 0 | R111: =0*(1/10^7) -> 0 | S111: =(S104)*(1/10^7) -> 107.41381 | X111: =S111/I111 -> 0.31684862 | AC111: =(S106)*(1/10^7) -> 67.553271 | AD111: =AC111/I111 -> 0.19926824
I112: =(X101)*(1/10^7) -> 391.42375 | J112: =0*(1/10^7) -> 0 | K112: =0*(1/10^7) -> 0 | L112: =0*(1/10^7) -> 0 | M112: =0*(1/10^7) -> 0 | N112: =(X102)*(1/10^7) -> 128.07273 | O112: =0*(1/10^7) -> 0 | P112: =0*(1/10^7) -> 0 | Q112: =0*(1/10^7) -> 0 | R112: =0*(1/10^7) -> 0 | S112: =(X104)*(1/10^7) -> 124.93872 | X112: =S112/I112 -> 0.31919045 | AC112: =(X106)*(1/10^7) -> 82.466648 | AD112: =AC112/I112 -> 0.21068381
I113: =(AC101)*(1/10^7) -> 462.36024 | J113: =0*(1/10^7) -> 0 | K113: =0*(1/10^7) -> 0 | L113: =0*(1/10^7) -> 0 | M113: =0*(1/10^7) -> 0 | N113: =(AC102)*(1/10^7) -> 149.16357 | O113: =0*(1/10^7) -> 0 | P113: =0*(1/10^7) -> 0 | Q113: =0*(1/10^7) -> 0 | R113: =0*(1/10^7) -> 0 | S113: =(AC104)*(1/10^7) -> 145.69951 | X113: =S113/I113 -> 0.3151212 | AC113: =(AC106)*(1/10^7) -> 99.610868 | AD113: =AC113/I113 -> 0.21543995
B115: Ethanol Revenue | I115: =I96+I97 -> 4.8812914e+09 | N115: =N96+N97 -> 1.0081707e+10 | O115: =O96+O97 -> 2.5609093e+09 | P115: =P96+P97 -> 2.5628972e+09 | Q115: =Q96+Q97 -> 2.6330076e+09 | R115: =R96+R97 -> 2.6371449e+09 | S115: =S96+S97 -> 1.0393959e+10 | T115: =T96+T97 -> 2.6392908e+09 | U115: =U96+U97 -> 2.6413741e+09 | ... AC115: =AC96+AC97 -> 1.1025509e+10
B116: Ethanol Gross Profit | I116: =I115*I117 -> 1.076075e+09 | N116: =N115*N117 -> 2.4098107e+09 | O116: =O115*O117 -> 8.2783401e+08 | P116: =P115*P117 -> 7.9991092e+08 | Q116: =Q115*Q117 -> 4.6691812e+08 | R116: =R115*R117 -> 8.5527567e+08 | S116: =S115*S117 -> 2.9499387e+09 | T116: =T115*T117 -> 8.5741575e+08 | U116: =U115*U117 -> 8.0800059e+08 | ... AC116: =AC115*AC117 -> 3.2014419e+09
B117: Ethanol Gross Margin | I117: =I57 -> 0.22044883 | N117: =N57 -> 0.23902804 | O117: =O57 -> 0.32325784 | P117: =P57 -> 0.31211198 | Q117: =Q57 -> 0.17733262 | R117: =R57 -> 0.3243188 | S117: =S57 -> 0.28381281 | T117: =T57 -> 0.32486597 | U117: =U57 -> 0.30590161 | ... AC117: =AC57 -> 0.29036681
B118: Ethanol EBITDA | I118: =I116-I40-SUM(I37:I39)/2 -> 9.2578673e+08 | N118: =N116-N40-SUM(N37:N39)/2 -> 2.1248607e+09 | O118: =O116-O40-SUM(O37:O39)/2 -> 7.5526809e+08 | P118: =P116-P40-SUM(P37:P39)/2 -> 7.2716832e+08 | Q118: =Q116-Q40-SUM(Q37:Q39)/2 -> 3.9228094e+08 | R118: =R116-R40-SUM(R37:R39)/2 -> 7.8039124e+08 | S118: =S116-S40-SUM(S37:S39)/2 -> 2.6551086e+09 | T118: =T116-T40-SUM(T37:T39)/2 -> 7.8233981e+08 | U118: =U116-U40-SUM(U37:U39)/2 -> 7.3273089e+08 | ... AC118: =AC116-AC40-SUM(AC37:AC39)/2 -> 2.8860301e+09
B119: Ethanol EBITDA Margin | I119: =I118/I115 -> 0.18966021 | N119: =N118/N115 -> 0.21076397 | O119: =O118/O115 -> 0.29492184 | P119: =P118/P115 -> 0.28372903 | Q119: =Q118/Q115 -> 0.14898588 | R119: =R118/R115 -> 0.29592277 | S119: =S118/S115 -> 0.25544729 | T119: =T118/T115 -> 0.29642047 | U119: =U118/U115 -> 0.27740519 | ... AC119: =AC118/AC115 -> 0.26175936
B120: Ethanol PAT | I120: =(I118-(SUM(I46:I47)*0.6))*(1-$C$51) -> 3.800396e+08 | J120: =(J118-(SUM(J46:J47)*0.6))*(1-$C$51) -> -88481466 | K120: =(K118-(SUM(K46:K47)*0.6))*(1-$C$51) -> -85346684 | L120: =(L118-(SUM(L46:L47)*0.6))*(1-$C$51) -> -82292196 | M120: =(M118-(SUM(M46:M47)*0.6))*(1-$C$51) -> -52694313 | N120: =(N118-(SUM(N46:N47)*0.6))*(1-$C$51) -> 1.2812186e+09 | O120: =(O118-(SUM(O46:O47)*0.6))*(1-$C$51) -> 5.1436902e+08 | P120: =(P118-(SUM(P46:P47)*0.6))*(1-$C$51) -> 4.9518181e+08 | ... AC120: =(AC118-(SUM(AC46:AC47)*0.6))*(1-$C$51) -> 2.0183752e+09
...

Sheet BS
C1: =C11/9 -> 1.7838131e+08 | E1: =C1/39000 -> 4573.8796 | F1: =E1/10.75% -> 42547.718
B3: No..of days of operation(days) | C3: 0 | E3: =300/4 -> 75 | F3: =300/4 -> 75 | G3: =300/4 -> 75 | H3: =300/4 -> 75 | I3: =300/4 -> 75 | J3: =300/4 -> 75 | K3: =300/4 -> 75 | L3: =300/4 -> 75 | ... X3: =300/4 -> 75
B4: Column counter | C4: 0 | E4: 1 | F4: =E4+1 -> 2 | G4: =F4+1 -> 3 | H4: =G4+1 -> 4 | I4: =H4+1 -> 5 | J4: =I4+1 -> 6 | K4: =J4+1 -> 7 | L4: =K4+1 -> 8 | M4: =L4+1 -> 9 | ... X4: =W4+1 -> 20
B5: Particulars | C5: 45747 | E5: 45838 | F5: =EOMONTH(E5,3) -> 45930 | G5: =EOMONTH(F5,3) -> 46022 | H5: =EDATE(G5,3) -> 46112 | I5: =EOMONTH(H5,3) -> 46203 | J5: =EOMONTH(I5,3) -> 46295 | K5: =EOMONTH(J5,3) -> 46387 | L5: =EOMONTH(K5,3) -> 46477 | M5: =EOMONTH(L5,3) -> 46568 | N5: =EOMONTH(M5,3) -> 46660 | O5: =EOMONTH(N5,3) -> 46752 | P5: =EOMONTH(O5,3) -> 46843 | ... X5: =EOMONTH(W5,3) -> 47573
A7: # | B7: Current Assets
B8: Cash and bank balances | C8: 24920421 | E8: =CFS!D26 -> 1.0252677e+09 | F8: =CFS!E26 -> 1.5289637e+09 | G8: =CFS!F26 -> 1.116618e+09 | H8: =CFS!G26 -> 1.0132796e+09 | I8: =CFS!I26 -> 1.733431e+09 | J8: =CFS!J26 -> 2.6026177e+09 | K8: =CFS!K26 -> -4.9706501e+09 | L8: =CFS!L26 -> -1.9149498e+09 | M8: =CFS!N26 -> 1.0184113e+09 | N8: =CFS!O26 -> 3.8574247e+09 | O8: =CFS!P26 -> -2.8027944e+09 | P8: =CFS!Q26 -> 4.3952753e+08 | Q8: =CFS!S26 -> 3.5465734e+09 | R8: =CFS!T26 -> 6.5320042e+09 | S8: =CFS!U26 -> -6.7140671e+08 | T8: =CFS!V26 -> 2.8431779e+09 | U8: =CFS!X26 -> 6.0635362e+09 | V8: =CFS!Y26 -> 9.3199294e+09 | W8: =CFS!Z26 -> 1.5401745e+09 | X8: =CFS!AA26 -> 5.3534843e+09
B9: Investments (other than long term invt.) | C9: 0 | E9: =C9 -> 0 | F9: =E9 -> 0 | G9: =F9 -> 0 | H9: =G9 -> 0 | I9: =H9 -> 0 | J9: =I9 -> 0 | K9: =J9 -> 0 | L9: =K9 -> 0 | M9: =L9 -> 0 | ... X9: =W9 -> 0
B10: Trade Receiveables | C10: 1.7286956e+08 | E10: =E70 -> 1.3831071e+08 | F10: =F70 -> 1.6336357e+08 | G10: =G70 -> 7.1600785e+08 | H10: =H70 -> 6.2762015e+08 | I10: =I70 -> 6.4545912e+08 | J10: =J70 -> 6.4482928e+08 | K10: =K70 -> 6.4622925e+08 | L10: =L70 -> 6.4788465e+08 | ... X10: =X70 -> 8.4943783e+08
B11: Inventories | C11: 1.6054318e+09 | E11: =E146+E155 -> 1.0109821e+09 | F11: =F146+F155 -> 2.2935714e+08 | G11: =G146+G155 -> 5.710881e+08 | H11: =H146+H155 -> 1.2354374e+09 | I11: =I146+I155 -> 6.4912854e+08 | J11: =J146+J155 -> 1.2607024e+08 | K11: =K146+K155 -> 6.8816517e+09 | L11: =L146+L155 -> 4.5652782e+09 | ... X11: =X146+X155 -> 5.6979106e+09
B12: Short Term Loans & Advances | C12: 88315120 | E12: =C12 -> 88315120 | F12: =E12 -> 88315120 | G12: =F12 -> 88315120 | H12: =G12 -> 88315120 | I12: =H12 -> 88315120 | J12: =I12 -> 88315120 | K12: =J12 -> 88315120 | L12: =K12 -> 88315120 | M12: =L12 -> 88315120 | ... X12: =W12 -> 88315120
B13: Other Current Assets (including TDS & Adv Tax) | C13: 1.6642346e+08 | E13: =C13 -> 1.6642346e+08 | F13: =E13 -> 1.6642346e+08 | G13: =F13 -> 1.6642346e+08 | H13: =G13 -> 1.6642346e+08 | I13: =H13 -> 1.6642346e+08 | J13: =I13 -> 1.6642346e+08 | K13: =J13 -> 1.6642346e+08 | L13: =K13 -> 1.6642346e+08 | M13: =L13 -> 1.6642346e+08 | ... X13: =W13 -> 1.6642346e+08
A15: # | B15: Non-Current Assets
B16: Progress Ethanol Plant | C16: 1.7285424e+09 | E16: =E169 -> 1.7285424e+09 | F16: =F169 -> 1.9785424e+09 | G16: =G169 -> 1.9043471e+09 | H16: =H169 -> 1.8329341e+09 | I16: =I169 -> 1.7641991e+09 | J16: =J169 -> 1.6980416e+09 | K16: =K169 -> 1.634365e+09 | L16: =L169 -> 1.5730763e+09 | ... X16: =X169 -> 9.9439438e+08
B17: Suger and Power Plant | C17: 1.2080616e+09 | E17: =E163 -> 1.1627593e+09 | F17: =F163 -> 1.1191558e+09 | G17: =G163 -> 1.0771875e+09 | H17: =H163 -> 1.0367929e+09 | I17: =I163 -> 9.979132e+08 | J17: =J163 -> 9.6049146e+08 | K17: =K163 -> 9.2447303e+08 | L17: =L163 -> 8.8980529e+08 | ... X17: =X163 -> 5.624758e+08
B18: Non-current investments | C18: 59760000 | E18: =C18 -> 59760000 | F18: =E18 -> 59760000 | G18: =F18 -> 59760000 | H18: =G18 -> 59760000 | I18: =H18 -> 59760000 | J18: =I18 -> 59760000 | K18: =J18 -> 59760000 | L18: =K18 -> 59760000 | M18: =L18 -> 59760000 | ... X18: =W18 -> 59760000
B19: Long term loans and advances | C19: 128709301 | E19: =C19 -> 128709301 | F19: =E19 -> 128709301 | G19: =F19 -> 128709301 | H19: =G19 -> 128709301 | I19: =H19 -> 128709301 | J19: =I19 -> 128709301 | K19: =J19 -> 128709301 | L19: =K19 -> 128709301 | M19: =L19 -> 128709301 | ... X19: =W19 -> 128709301
B20: Other Non-Current assets | C20: 1.2756287e+08 | E20: =C20 -> 1.2756287e+08 | F20: =E20 -> 1.2756287e+08 | G20: =F20 -> 1.2756287e+08 | H20: =G20 -> 1.2756287e+08 | I20: =H20 -> 1.2756287e+08 | J20: =I20 -> 1.2756287e+08 | K20: =J20 -> 1.2756287e+08 | L20: =K20 -> 1.2756287e+08 | M20: =L20 -> 1.2756287e+08 | ... X20: =W20 -> 1.2756287e+08
A22: # | B22: Total Assets | C22: =(SUM(C8:C13,C16:C20)) -> 5.3105965e+09 | E22: =SUM(E8:E13,E16:E20) -> 5.6366331e+09 | F22: =SUM(F8:F13,F16:F20) -> 5.5901535e+09 | G22: =SUM(G8:G13,G16:G20) -> 5.9560192e+09 | H22: =SUM(H8:H13,H16:H20) -> 6.316835e+09 | I22: =SUM(I8:I13,I16:I20) -> 6.3609017e+09 | J22: =SUM(J8:J13,J16:J20) -> 6.602821e+09 | K22: =SUM(K8:K14,K16:K20) -> 5.6868397e+09 | L22: =SUM(L8:L13,L16:L20) -> 6.3318654e+09 | M22: =SUM(M8:M13,M16:M20) -> 6.9245308e+09 | N22: =SUM(N8:N13,N16:N20) -> 7.4817829e+09 | O22: =SUM(O8:O13,O16:O20) -> 7.9221661e+09 | P22: =SUM(P8:P13,P16:P20) -> 8.6288779e+09 | Q22: =SUM(Q8:Q13,Q16:Q20) -> 9.2729706e+09 | R22: =SUM(R8:R13,R16:R20) -> 9.8628704e+09 | S22: =SUM(S8:S13,S16:S20) -> 1.0450997e+10 | ... X22: =SUM(X8:X13,X16:X20) -> 1.4028474e+10
A24: # | B24: Liabilties
B25: Short-term borrowings | C25: 9.5897433e+08 | H25: =C25 -> 9.5897433e+08 | L25: =H25 -> 9.5897433e+08 | P25: =L25 -> 9.5897433e+08 | T25: =P25 -> 9.5897433e+08 | X25: =T25 -> 9.5897433e+08
B26: Accounts payables | C26: 6.8151108e+08 | E26: =E$124 -> 1009385.8 | F26: =F$124 -> 1034620.5 | G26: =G$124 -> 1.3614197e+08 | H26: =H$124 -> 2.0042119e+08 | I26: =I$124 -> 495275.27 | J26: =J$124 -> 498099.64 | K26: =K$124 -> 643063.72 | L26: =L$124 -> 558475.52 | ... X26: =X$124 -> 900337.73
B27: Other current liabilities | C27: 99667052 | E27: =C27 -> 99667052 | F27: =E27 -> 99667052 | G27: =F27 -> 99667052 | H27: =G27 -> 99667052 | I27: =H27 -> 99667052 | J27: =I27 -> 99667052 | K27: =J27 -> 99667052 | L27: =K27 -> 99667052 | M27: =L27 -> 99667052 | ... X27: =W27 -> 99667052
B28: Short-Term Provisions | C28: 1.816263e+08 | E28: =C28 -> 1.816263e+08 | F28: =E28 -> 1.816263e+08 | G28: =F28 -> 1.816263e+08 | H28: =G28 -> 1.816263e+08 | I28: =H28 -> 1.816263e+08 | J28: =I28 -> 1.816263e+08 | K28: =J28 -> 1.816263e+08 | L28: =K28 -> 1.816263e+08 | M28: =L28 -> 1.816263e+08 | ... X28: =W28 -> 1.816263e+08
A30: # | B30: Non-Current liabilities
B31: Long term Debt obligations | C31: =2149075099.33 -> 2.1490751e+09 | E31: =E177 -> 3.0976747e+09 | F31: =F177 -> 3.0238052e+09 | G31: =G177 -> 2.9485594e+09 | H31: =H177 -> 2.8719107e+09 | I31: =I177 -> 2.7938318e+09 | J31: =J177 -> 2.714295e+09 | K31: =K177 -> 1.4272048e+09 | L31: =L177 -> 1.3855359e+09 | ... X31: =X177 -> 8.3397241e+08
B32: Deferred Tax Liability | C32: 9892721.3 | E32: =C32 -> 9892721.3 | F32: =E32 -> 9892721.3 | G32: =F32 -> 9892721.3 | H32: =G32 -> 9892721.3 | I32: =H32 -> 9892721.3 | J32: =I32 -> 9892721.3 | K32: =J32 -> 9892721.3 | L32: =K32 -> 9892721.3 | M32: =L32 -> 9892721.3 | ... X32: =W32 -> 9892721.3
A34: # | B34: Total Liabilities | C34: =SUM(C25:C32) -> 4.0807466e+09 | E34: =SUM(E25:E32) -> 3.3898702e+09 | F34: =SUM(F25:F32) -> 3.3160259e+09 | G34: =SUM(G25:G32) -> 3.3758874e+09 | H34: =SUM(H25:H32) -> 4.3224922e+09 | I34: =SUM(I25:I32) -> 3.0855131e+09 | J34: =SUM(J25:J32) -> 3.0059791e+09 | K34: =SUM(K25:K32) -> 1.7190339e+09 | L34: =SUM(L25:L32) -> 2.6362548e+09 | ... X34: =SUM(X25:X32) -> 2.0850331e+09
B36: Equity
B37: Share Capital | C37: 57179000 | E37: =C37 -> 57179000 | F37: =E37 -> 57179000 | G37: =F37 -> 57179000 | H37: =G37 -> 57179000 | I37: =H37 -> 57179000 | J37: =I37 -> 57179000 | K37: =J37 -> 57179000 | L37: =K37 -> 57179000 | M37: =L37 -> 57179000 | ... X37: =W37 -> 57179000
B38: General Reserve | C38: 1.1568989e+09 | E38: =C38+PL!E53 -> 1.2148375e+09 | F38: =E38+PL!F53 -> 1.2422022e+09 | G38: =F38+PL!G53 -> 1.5482064e+09 | H38: =G38+PL!H53 -> 1.9213917e+09 | I38: =H38+PL!J53 -> 2.2434632e+09 | J38: =I38+PL!K53 -> 2.5649165e+09 | K38: =J38+PL!L53 -> 2.9358805e+09 | L38: =K38+PL!M53 -> 3.6226596e+09 | M38: =L38+PL!O53 -> 4.2573313e+09 | N38: =M38+PL!P53 -> 4.8575085e+09 | O38: =N38+PL!Q53 -> 5.3416321e+09 | P38: =O38+PL!R53 -> 6.0926429e+09 | Q38: =P38+PL!T53 -> 6.7813539e+09 | R38: =Q38+PL!U53 -> 7.4168127e+09 | S38: =R38+PL!V53 -> 8.0513143e+09 | T38: =S38+PL!W53 -> 8.8560056e+09 | U38: =T38+PL!Y53 -> 9.5813578e+09 | V38: =U38+PL!Z53 -> 1.0288284e+10 | W38: =V38+PL!AA53 -> 1.0988067e+10 | X38: =W38+PL!AB53 -> 1.1870489e+10
B39: Share application money pending allotment | C39: 15772050 | E39: =C39 -> 15772050 | F39: =E39 -> 15772050 | G39: =F39 -> 15772050 | H39: =G39 -> 15772050 | I39: =H39 -> 15772050 | J39: =I39 -> 15772050 | K39: =J39 -> 15772050 | L39: =K39 -> 15772050 | M39: =L39 -> 15772050 | ... X39: =W39 -> 15772050
A41: # | B41: Total Equity | C41: =SUM(C37:C39) -> 1.22985e+09 | E41: =SUM(E37:E39) -> 1.2877886e+09 | F41: =SUM(F37:F39) -> 1.3151533e+09 | G41: =SUM(G37:G39) -> 1.6211575e+09 | H41: =SUM(H37:H39) -> 1.9943427e+09 | I41: =SUM(I37:I39) -> 2.3164143e+09 | J41: =SUM(J37:J39) -> 2.6378675e+09 | K41: =SUM(K37:K39) -> 3.0088315e+09 | L41: =SUM(L37:L39) -> 3.6956107e+09 | ... X41: =SUM(X37:X39) -> 1.194344e+10
B43: Total Equity and Liability | C43: =SUM(C34,C41) -> 5.3105965e+09 | E43: =SUM(E34,E41) -> 4.6776587e+09 | F43: =SUM(F34,F41) -> 4.6311791e+09 | G43: =SUM(G34,G41) -> 4.9970449e+09 | H43: =SUM(H34,H41) -> 6.316835e+09 | I43: =SUM(I34,I41) -> 5.4019274e+09 | J43: =SUM(J34,J41) -> 5.6438467e+09 | K43: =SUM(K34,K41) -> 4.7278654e+09 | L43: =SUM(L34,L41) -> 6.3318654e+09 | ... X43: =SUM(X34,X41) -> 1.4028474e+10
B44: check sum | C44: =C22-C43 -> 0 | E44: =E22-E43 -> 9.5897433e+08 | F44: =F22-F43 -> 9.5897433e+08 | G44: =G22-G43 -> 9.5897433e+08 | H44: =H22-H43 -> 0 | I44: =I22-I43 -> 9.5897433e+08 | J44: =J22-J43 -> 9.5897433e+08 | K44: =K22-K43 -> 9.5897433e+08 | L44: =L22-L43 -> 0 | ... X44: =X22-X43 -> 0
B47: CA | C47: =SUM(C9:C13) -> 2.0330399e+09 | E47: =SUM(E9:E13) -> 1.4040314e+09 | F47: =SUM(F9:F13) -> 6.4745929e+08 | G47: =SUM(G9:G13) -> 1.5418345e+09 | H47: =SUM(H9:H13) -> 2.1177961e+09 | I47: =SUM(I9:I13) -> 1.5493262e+09 | J47: =SUM(J9:J13) -> 1.0256381e+09 | K47: =SUM(K9:K13) -> 7.7826195e+09 | L47: =SUM(L9:L13) -> 5.4679014e+09 | ... X47: =SUM(X9:X13) -> 6.802087e+09
B48: CL | C48: =SUM(C26:C28) -> 9.6280443e+08 | E48: =SUM(E26:E28) -> 2.8230273e+08 | F48: =SUM(F26:F28) -> 2.8232797e+08 | G48: =SUM(G26:G28) -> 4.1743532e+08 | H48: =SUM(H26:H28) -> 4.8171453e+08 | I48: =SUM(I26:I28) -> 2.8178862e+08 | J48: =SUM(J26:J28) -> 2.8179145e+08 | K48: =SUM(K26:K28) -> 2.8193641e+08 | L48: =SUM(L26:L28) -> 2.8185182e+08 | ... X48: =SUM(X26:X28) -> 2.8219368e+08
B49: NWC | C49: =C47-C48 -> 1.0702355e+09 | E49: =E47-E48 -> 1.1217287e+09 | F49: =F47-F48 -> 3.6513132e+08 | G49: =G47-G48 -> 1.1243992e+09 | H49: =H47-H48 -> 1.6360816e+09 | I49: =I47-I48 -> 1.2675376e+09 | J49: =J47-J48 -> 7.4384665e+08 | K49: =K47-K48 -> 7.5006831e+09 | L49: =L47-L48 -> 5.1860496e+09 | ... X49: =X47-X48 -> 6.5198933e+09
B50: Ch. In NWC | E50: =E49-C49 -> 51493239 | F50: =F49-E49 -> -7.5659738e+08 | G50: =G49-F49 -> 7.5926788e+08 | H50: =H49-G49 -> 5.1168239e+08 | I50: =I49-H49 -> -3.6854398e+08 | J50: =J49-I49 -> -5.2369097e+08 | K50: =K49-J49 -> 6.7568365e+09 | L50: =L49-K49 -> -2.3146335e+09 | M50: =M49-L49 -> -2.2486253e+09 | ... X50: =X49-W49 -> -2.9200504e+09
A52: # | B52: Receivables
B53: No..of days of operation(days) | E53: =360/4 -> 90 | F53: =360/4 -> 90 | G53: =360/4 -> 90 | H53: =360/4 -> 90 | I53: =360/4 -> 90 | J53: =360/4 -> 90 | K53: =360/4 -> 90 | L53: =360/4 -> 90 | ... T53: =360/4 -> 90 | U53: =PL!Y2 -> 75 | V53: =PL!Z2 -> 75 | W53: =PL!AA2 -> 75 | X53: =PL!AB2 -> 75
B54: Receivable turnover ratio(days) - Ethanol | E54: 26 | F54: =E54 -> 26 | G54: =F54 -> 26 | H54: =G54 -> 26 | I54: =H54 -> 26 | J54: =I54 -> 26 | K54: =J54 -> 26 | L54: =K54 -> 26 | M54: =L54 -> 26 | ... X54: =W54 -> 26
B55: Receivable turnover ratio(days) - DDGS | E55: 3 | F55: =E55 -> 3 | G55: =F55 -> 3 | H55: =G55 -> 3 | I55: 7 | J55: =I55 -> 7 | K55: 3 | L55: =K55 -> 3 | M55: =L55 -> 3 | N55: =M55 -> 3 | O55: =N55 -> 3 | P55: =O55 -> 3 | Q55: =P55 -> 3 | R55: =Q55 -> 3 | S55: =R55 -> 3 | ... X55: =W55 -> 3
B56: Receivable turnover ratio(days) - Sugar | E56: 15 | F56: =E56 -> 15 | G56: =F56 -> 15 | H56: 1 | I56: =H56 -> 1 | J56: =I56 -> 1 | K56: =J56 -> 1 | L56: =K56 -> 1 | M56: =L56 -> 1 | N56: =M56 -> 1 | O56: =N56 -> 1 | P56: =O56 -> 1 | ... X56: =W56 -> 1
B57: Receivable turnover ratio(days) - Molasses | E57: 15 | F57: =E57 -> 15 | G57: =F57 -> 15 | H57: 1 | I57: =H57 -> 1 | J57: =I57 -> 1 | K57: =J57 -> 1 | L57: =K57 -> 1 | M57: =L57 -> 1 | N57: =M57 -> 1 | O57: =N57 -> 1 | P57: =O57 -> 1 | ... X57: =W57 -> 1
B58: Receivable turnover ratio(days) - Press Mud | E58: 15 | F58: =E58 -> 15 | G58: =F58 -> 15 | H58: 1 | I58: =H58 -> 1 | J58: =I58 -> 1 | K58: =J58 -> 1 | L58: =K58 -> 1 | M58: =L58 -> 1 | N58: =M58 -> 1 | O58: =N58 -> 1 | P58: =O58 -> 1 | ... X58: =W58 -> 1
B59: Receivable turnover ratio(days) - Bagasse | E59: 15 | F59: =E59 -> 15 | G59: =F59 -> 15 | H59: 1 | I59: =H59 -> 1 | J59: =I59 -> 1 | K59: =J59 -> 1 | L59: =K59 -> 1 | M59: =L59 -> 1 | N59: =M59 -> 1 | O59: =N59 -> 1 | P59: =O59 -> 1 | ... X59: =W59 -> 1
B60: Receivable turnover ratio(days) - Power | E60: 30 | F60: =E60 -> 30 | G60: =F60 -> 30 | H60: 15 | I60: =H60 -> 15 | J60: =I60 -> 15 | K60: =J60 -> 15 | L60: =K60 -> 15 | M60: =L60 -> 15 | N60: =M60 -> 15 | O60: =N60 -> 15 | P60: =O60 -> 15 | ... X60: =W60 -> 15
A62: # | B62: Receivables
B63: Ethanol | E63: =E54/E$53*E73 -> 0 | F63: =F54/F$53*F73 -> 0 | G63: =G54/G$53*G73 -> 5.8588656e+08 | H63: =H54/H$53*H73 -> 6.0719152e+08 | I63: =I54/I$53*I73 -> 6.0796625e+08 | J63: =J54/J$53*J73 -> 6.0799442e+08 | K63: =K54/K$53*K73 -> 6.2449929e+08 | L63: =L54/L$53*L73 -> 6.2509947e+08 | ... X63: =X54/X$53*X73 -> 8.1177524e+08
B64: DDGS | E64: =E55/E$53*E74 -> 0 | F64: =F55/F$53*F74 -> 0 | G64: =G55/G$53*G74 -> 12492198 | H64: =H55/H$53*H74 -> 12554659 | I64: =I55/I$53*I74 -> 29440676 | J64: =J55/J$53*J74 -> 29587879 | K64: =K55/K$53*K74 -> 13102906 | L64: =L55/L$53*L74 -> 13168421 | ... X64: =X55/X$53*X74 -> 18155654
B65: Sugar | E65: =E56/E$53*E75 -> 1.3116071e+08 | F65: =F56/F$53*F75 -> 1.5692857e+08 | G65: =G56/G$53*G75 -> 98913095 | H65: =H56/H$53*H75 -> 6562328.6 | I65: =I56/I$53*I75 -> 7656050 | J65: =J56/J$53*J75 -> 6890445 | K65: =K56/K$53*K75 -> 7299363 | L65: =L56/L$53*L75 -> 7990809.9 | ... X65: =X56/X$53*X75 -> 16159060
B66: Molasses | E66: =E57/E$53*E76 -> 7150000 | F66: =F57/F$53*F76 -> 6435000 | G66: =G57/G$53*G76 -> 17204000 | H66: =H57/H$53*H76 -> 1188440 | I66: =I57/I$53*I76 -> 396146.67 | J66: =J57/J$53*J76 -> 356532 | K66: =K57/K$53*K76 -> 1219691.7 | L66: =L57/L$53*L76 -> 1469953.8 | ... X66: =X57/X$53*X76 -> 3019554.7
B67: Press Mud | E67: =E58/E$53*E77 -> 0 | F67: =F58/F$53*F77 -> 0 | G67: =G58/G$53*G77 -> 1512000 | H67: =H58/H$53*H77 -> 123200 | I67: =I58/I$53*I77 -> 0 | J67: =J58/J$53*J77 -> 0 | K67: =K58/K$53*K77 -> 108000 | L67: =L58/L$53*L77 -> 156000 | ... X67: =X58/X$53*X77 -> 328320
B68: Bagasse | E68: =E59/E$53*E78 -> 0 | F68: =F59/F$53*F78 -> 0 | G68: =G59/G$53*G78 -> 0 | H68: =H59/H$53*H78 -> 0 | I68: =I59/I$53*I78 -> 0 | J68: =J59/J$53*J78 -> 0 | K68: =K59/K$53*K78 -> 0 | L68: =L59/L$53*L78 -> 0 | ... X68: =X59/X$53*X78 -> 0
B69: Power
B70: Total | E70: =SUM(E63:E69) -> 1.3831071e+08 | F70: =SUM(F63:F69) -> 1.6336357e+08 | G70: =SUM(G63:G69) -> 7.1600785e+08 | H70: =SUM(H63:H69) -> 6.2762015e+08 | I70: =SUM(I63:I69) -> 6.4545912e+08 | J70: =SUM(J63:J69) -> 6.4482928e+08 | K70: =SUM(K63:K69) -> 6.4622925e+08 | L70: =SUM(L63:L69) -> 6.4788465e+08 | ... X70: =SUM(X63:X69) -> 8.4943783e+08
B72: Sales Amount
B73: =B63 -> Ethanol | E73: =PL!E12 -> 0 | F73: =PL!F12 -> 0 | G73: =PL!G12 -> 2028068850 | H73: =PL!H12 -> 2.1018168e+09 | I73: =PL!J12 -> 2.1044986e+09 | J73: =PL!K12 -> 2.1045961e+09 | K73: =PL!L12 -> 2.1617283e+09 | L73: =PL!M12 -> 2.1638059e+09 | M73: =PL!O12 -> 2.1638814e+09 | N73: =PL!P12 -> 2.1638841e+09 | O73: =PL!Q12 -> 2.2210129e+09 | P73: =PL!R12 -> 2.2230904e+09 | Q73: =PL!T12 -> 2.2231659e+09 | R73: =PL!U12 -> 2.2231686e+09 | S73: =PL!V12 -> 2.2802974e+09 | T73: =PL!W12 -> 2.2823749e+09 | U73: =PL!Y12 -> 2.2824504e+09 | V73: =PL!Z12 -> 2.2824531e+09 | W73: =PL!AA12 -> 2.3395819e+09 | X73: =PL!AB12 -> 2.3416594e+09
B74: =B64 -> DDGS | E74: =PL!E13 -> 0 | F74: =PL!F13 -> 0 | G74: =PL!G13 -> 3.7476595e+08 | H74: =PL!H13 -> 3.7663978e+08 | I74: =PL!J13 -> 3.7852298e+08 | J74: =PL!K13 -> 3.8041559e+08 | K74: =PL!L13 -> 3.9308718e+08 | L74: =PL!M13 -> 3.9505262e+08 | M74: =PL!O13 -> 3.9702788e+08 | N74: =PL!P13 -> 3.9901302e+08 | O74: =PL!Q13 -> 4.1199461e+08 | P74: =PL!R13 -> 4.1405458e+08 | Q74: =PL!T13 -> 4.1612486e+08 | R74: =PL!U13 -> 4.1820548e+08 | S74: =PL!V13 -> 4.3150441e+08 | T74: =PL!W13 -> 4.3366194e+08 | U74: =PL!Y13 -> 4.3583025e+08 | V74: =PL!Z13 -> 4.380094e+08 | W74: =PL!AA13 -> 4.516332e+08 | X74: =PL!AB13 -> 4.5389136e+08
B75: =B65 -> Sugar | E75: =PL!E7 -> 7.8696429e+08 | F75: =PL!F7 -> 9.4157143e+08 | G75: =PL!G7 -> 5.9347857e+08 | H75: =PL!H7 -> 5.9060957e+08 | I75: =PL!J7 -> 689044500 | J75: =PL!K7 -> 620140050 | K75: =PL!L7 -> 656942670 | L75: =PL!M7 -> 7.1917289e+08 | M75: =PL!O7 -> 7.3006945e+08 | N75: =PL!P7 -> 6.570625e+08 | O75: =PL!Q7 -> 7.7340417e+08 | P75: =PL!R7 -> 8.3025452e+08 | Q75: =PL!T7 -> 8.4283413e+08 | R75: =PL!U7 -> 7.5855072e+08 | S75: =PL!V7 -> 8.4401005e+08 | T75: =PL!W7 -> 1.0060992e+09 | U75: =PL!Y7 -> 1.0213431e+09 | V75: =PL!Z7 -> 9.1920879e+08 | W75: =PL!AA7 -> 9.2768059e+08 | X75: =PL!AB7 -> 1.2119295e+09
B76: =B66 -> Molasses | E76: =PL!E8 -> 42900000 | F76: =PL!F8 -> 38610000 | G76: =PL!G8 -> 1.03224e+08 | H76: =PL!H8 -> 106959600 | I76: =PL!J8 -> 35653200 | J76: =PL!K8 -> 32087880 | K76: =PL!L8 -> 109772256 | L76: =PL!M8 -> 1.3229584e+08 | M76: =PL!O8 -> 44098613 | N76: =PL!P8 -> 39688752 | O76: =PL!Q8 -> 1.3024789e+08 | P76: =PL!R8 -> 1.5259318e+08 | Q76: =PL!T8 -> 50864394 | R76: =PL!U8 -> 45777955 | S76: =PL!V8 -> 1.4187715e+08 | T76: =PL!W8 -> 1.8665117e+08 | U76: =PL!Y8 -> 62217058 | V76: =PL!Z8 -> 55995352 | W76: =PL!AA8 -> 1.5545736e+08 | X76: =PL!AB8 -> 2.264666e+08
B77: =B67 -> Press Mud | E77: =PL!E9 -> 0 | F77: =PL!F9 -> 0 | G77: =PL!G9 -> 9072000 | H77: =PL!H9 -> 11088000 | I77: =PL!J9 -> 0 | J77: =PL!K9 -> 0 | K77: =PL!L9 -> 9720000 | L77: =PL!M9 -> 14040000 | M77: =PL!O9 -> 0 | N77: =PL!P9 -> 0 | O77: =PL!Q9 -> 11520000 | P77: =PL!R9 -> 16128000 | Q77: =PL!T9 -> 0 | R77: =PL!U9 -> 0 | S77: =PL!V9 -> 12528000 | T77: =PL!W9 -> 20044800 | U77: =PL!Y9 -> 0 | V77: =PL!Z9 -> 0 | W77: =PL!AA9 -> 13680000 | X77: =PL!AB9 -> 24624000
B78: =B68 -> Bagasse | E78: =PL!E10 -> 0 | F78: =PL!F10 -> 0 | G78: =PL!G10 -> 0 | H78: =PL!H10 -> 0 | I78: =PL!J10 -> 0 | J78: =PL!K10 -> 0 | K78: =PL!L10 -> 0 | L78: =PL!M10 -> 0 | M78: =PL!O10 -> 0 | N78: =PL!P10 -> 0 | O78: =PL!Q10 -> 0 | P78: =PL!R10 -> 0 | Q78: =PL!T10 -> 0 | R78: =PL!U10 -> 0 | S78: =PL!V10 -> 0 | T78: =PL!W10 -> 0 | U78: =PL!Y10 -> 0 | V78: =PL!Z10 -> 0 | W78: =PL!AA10 -> 0 | X78: =PL!AB10 -> 0
B79: =B69 -> Power
A81: # | B81: Payables Days
B82: =PL!B20 -> Sugar Plant
B83: =PL!B21 -> Raw material (sugarcane) | E83: 15 | F83: =E83 -> 15 | G83: =F83 -> 15 | H83: =G83 -> 15 | I83: =H83 -> 15 | J83: =I83 -> 15 | K83: 0 | L83: =K83 -> 0 | M83: =L83 -> 0 | N83: =M83 -> 0 | O83: =N83 -> 0 | P83: =O83 -> 0 | Q83: =P83 -> 0 | R83: =Q83 -> 0 | S83: =R83 -> 0 | ... X83: =W83 -> 0
B84: =PL!B22 -> Labour Cost | E84: 15 | F84: =E84 -> 15 | G84: =F84 -> 15 | H84: 1 | I84: =H84 -> 1 | J84: =I84 -> 1 | K84: =J84 -> 1 | L84: =K84 -> 1 | M84: =L84 -> 1 | N84: =M84 -> 1 | O84: =N84 -> 1 | P84: =O84 -> 1 | ... X84: =W84 -> 1
B85: =PL!B23 -> Power Cost | E85: 15 | F85: =E85 -> 15 | G85: =F85 -> 15 | H85: 1 | I85: =H85 -> 1 | J85: =I85 -> 1 | K85: =J85 -> 1 | L85: =K85 -> 1 | M85: =L85 -> 1 | N85: =M85 -> 1 | O85: =N85 -> 1 | P85: =O85 -> 1 | ... X85: =W85 -> 1
B86: =PL!B24 -> Salary for dedicated Staff | E86: 15 | F86: =E86 -> 15 | G86: =F86 -> 15 | H86: 1 | I86: =H86 -> 1 | J86: =I86 -> 1 | K86: =J86 -> 1 | L86: =K86 -> 1 | M86: =L86 -> 1 | N86: =M86 -> 1 | O86: =N86 -> 1 | P86: =O86 -> 1 | ... X86: =W86 -> 1
B87: =PL!B26 -> Other Cost | E87: 15 | F87: =E87 -> 15 | G87: =F87 -> 15 | H87: 3 | I87: =H87 -> 3 | J87: =I87 -> 3 | K87: =J87 -> 3 | L87: =K87 -> 3 | M87: =L87 -> 3 | N87: =M87 -> 3 | O87: =N87 -> 3 | P87: =O87 -> 3 | ... X87: =W87 -> 3
A89: # | B89: Payables Amount
B90: =B$53 -> No..of days of operation(days) | C90: =C$53 -> 0 | D90: =D$53 -> 0 | E90: =E$53 -> 90 | F90: =F$53 -> 90 | G90: =G$53 -> 90 | H90: =H$53 -> 90 | I90: =I$53 -> 90 | ... Y90: =Y$53 -> 0
B91: =PL!B$21&" "&"Cost" -> Raw material (sugarcane) Cost | C91: =PL!C$21 -> 0 | D91: =PL!D$21 -> 0 | E91: =PL!E$21 -> 0 | F91: =PL!F$21 -> 0 | G91: =PL!G$21 -> 8.316e+08 | H91: =PL!H$21 -> 1201200000 | I91: =PL!J$21 -> 0 | J91: =PL!K$21 -> 0 | K91: =PL!L$21 -> 2178000000 | L91: =PL!M$21 -> 0 | M91: =PL!O$21 -> 0 | N91: =PL!P$21 -> 0 | O91: =PL!Q$21 -> 2534400000 | P91: =PL!R$21 -> 0 | Q91: =PL!T$21 -> 0 | R91: =PL!U$21 -> 0 | S91: =PL!V$21 -> 2985840000 | T91: =PL!W$21 -> 0 | U91: =PL!Y$21 -> 0 | V91: =PL!Z$21 -> 0 | W91: =PL!AA$21 -> 3511200000 | X91: =PL!AB$21 -> 0
B92: =PL!B$22 -> Labour Cost | C92: =PL!C$22 -> 0 | D92: =PL!D$22 -> 0 | E92: =PL!E$22 -> 0 | F92: =PL!F$22 -> 0 | G92: =PL!G$22 -> 5040000 | H92: =PL!H$22 -> 6160000 | I92: =PL!J$22 -> 0 | J92: =PL!K$22 -> 0 | K92: =PL!L$22 -> 5400000 | L92: =PL!M$22 -> 7800000 | M92: =PL!O$22 -> 0 | N92: =PL!P$22 -> 0 | O92: =PL!Q$22 -> 6400000 | P92: =PL!R$22 -> 8960000 | Q92: =PL!T$22 -> 0 | R92: =PL!U$22 -> 0 | S92: =PL!V$22 -> 6960000 | T92: =PL!W$22 -> 11136000 | U92: =PL!Y$22 -> 0 | V92: =PL!Z$22 -> 0 | W92: =PL!AA$22 -> 7600000 | X92: =PL!AB$22 -> 13680000
B93: =PL!B$23 -> Power Cost | C93: =PL!C$23 -> 0 | D93: =PL!D$23 -> 0 | E93: =PL!E$23 -> 0 | F93: =PL!F$23 -> 0 | G93: =PL!G$23 -> -51480000 | H93: =PL!H$23 -> -62920000 | I93: =PL!J$23 -> 0 | J93: =PL!K$23 -> 0 | K93: =PL!L$23 -> -51480000 | L93: =PL!M$23 -> -74360000 | M93: =PL!O$23 -> 0 | N93: =PL!P$23 -> 0 | O93: =PL!Q$23 -> -57200000 | P93: =PL!R$23 -> -80080000 | Q93: =PL!T$23 -> 0 | R93: =PL!U$23 -> 0 | S93: =PL!V$23 -> -57200000 | T93: =PL!W$23 -> -91520000 | U93: =PL!Y$23 -> 0 | V93: =PL!Z$23 -> 0 | W93: =PL!AA$23 -> -57200000 | X93: =PL!AB$23 -> -102960000
B94: =PL!B$24 -> Salary for dedicated Staff | C94: =PL!C$24 -> 0 | D94: =PL!D$24 -> 0 | E94: =PL!E$24 -> 4439070 | F94: =PL!F$24 -> 4550046.8 | G94: =PL!G$24 -> 4663797.9 | H94: =PL!H$24 -> 4780392.9 | I94: =PL!J$24 -> 4899902.7 | J94: =PL!K$24 -> 5022400.3 | K94: =PL!L$24 -> 5147960.3 | L94: =PL!M$24 -> 5276659.3 | M94: =PL!O$24 -> 5408575.8 | N94: =PL!P$24 -> 5543790.1 | O94: =PL!Q$24 -> 5682384.9 | P94: =PL!R$24 -> 5824444.5 | Q94: =PL!T$24 -> 5970055.6 | R94: =PL!U$24 -> 6119307 | S94: =PL!V$24 -> 6272289.7 | T94: =PL!W$24 -> 6429096.9 | U94: =PL!Y$24 -> 6589824.4 | V94: =PL!Z$24 -> 6754570 | W94: =PL!AA$24 -> 6923434.2 | X94: =PL!AB$24 -> 7096520.1
B95: =PL!B$26 -> Other Cost | C95: =PL!C$26 -> 0 | D95: =PL!D$26 -> 0 | E95: =PL!E$26 -> 0 | F95: =PL!F$26 -> 0 | G95: =PL!G$26 -> 8820000 | H95: =PL!H$26 -> 10780000 | I95: =PL!J$26 -> 0 | J95: =PL!K$26 -> 0 | K95: =PL!L$26 -> 9450000 | L95: =PL!M$26 -> 13650000 | M95: =PL!O$26 -> 0 | N95: =PL!P$26 -> 0 | O95: =PL!Q$26 -> 11200000 | P95: =PL!R$26 -> 15680000 | Q95: =PL!T$26 -> 0 | R95: =PL!U$26 -> 0 | S95: =PL!V$26 -> 12180000 | T95: =PL!W$26 -> 19488000 | U95: =PL!Y$26 -> 0 | V95: =PL!Z$26 -> 0 | W95: =PL!AA$26 -> 13300000 | X95: =PL!AB$26 -> 23940000
B96: =B83 -> Raw material (sugarcane) | C96: =SUM(E96:X96) -> 338800000 | E96: =IFERROR(E$91/E$90*E$83,0) -> 0 | F96: =IFERROR(F$91/F$90*F$83,0) -> 0 | G96: =IFERROR(G$91/G$90*G$83,0) -> 1.386e+08 | H96: =IFERROR(H$91/H$90*H$83,0) -> 200200000 | I96: =IFERROR(I$91/I$90*I$83,0) -> 0 | J96: =IFERROR(J$91/J$90*J$83,0) -> 0 | K96: =IFERROR(K$91/K$90*K$83,0) -> 0 | L96: =IFERROR(L$91/L$90*L$83,0) -> 0 | ... X96: =IFERROR(X$91/X$90*X$83,0) -> 0
B97: =B84 -> Labour Cost | C97: =SUM(E97:X97) -> 1710577.8 | E97: =E$92/E$90*E$84 -> 0 | F97: =IFERROR(F$92/F$90*F$84,0) -> 0 | G97: =IFERROR(G$92/G$90*G$84,0) -> 840000 | H97: =IFERROR(H$92/H$90*H$84,0) -> 68444.444 | I97: =IFERROR(I$92/I$90*I$84,0) -> 0 | J97: =IFERROR(J$92/J$90*J$84,0) -> 0 | K97: =IFERROR(K$92/K$90*K$84,0) -> 60000 | L97: =IFERROR(L$92/L$90*L$84,0) -> 86666.667 | M97: =IFERROR(M$92/M$90*M$84,0) -> 0 | ... X97: =IFERROR(X$92/X$90*X$84,0) -> 182400
B98: =B85 -> Power Cost | C98: =SUM(E98:X98) -> -15990578 | E98: =IFERROR(E$93/E$90*E$85,0) -> 0 | F98: =IFERROR(F$93/F$90*F$85,0) -> 0 | G98: =IFERROR(G$93/G$90*G$85,0) -> -8580000 | H98: =IFERROR(H$93/H$90*H$85,0) -> -699111.11 | I98: =IFERROR(I$93/I$90*I$85,0) -> 0 | J98: =IFERROR(J$93/J$90*J$85,0) -> 0 | K98: =IFERROR(K$93/K$90*K$85,0) -> -572000 | L98: =IFERROR(L$93/L$90*L$85,0) -> -826222.22 | ... X98: =IFERROR(X$93/X$90*X$85,0) -> -1372800
B99: =B86 -> Salary for dedicated Staff | C99: =SUM(E99:X99) -> 3444535.5 | E99: =IFERROR(E$94/E$90*E$86,0) -> 739845 | F99: =IFERROR(F$94/F$90*F$86,0) -> 758341.12 | G99: =IFERROR(G$94/G$90*G$86,0) -> 777299.65 | H99: =IFERROR(H$94/H$90*H$86,0) -> 53115.476 | I99: =IFERROR(I$94/I$90*I$86,0) -> 54443.363 | J99: =IFERROR(J$94/J$90*J$86,0) -> 55804.447 | K99: =IFERROR(K$94/K$90*K$86,0) -> 57199.558 | L99: =IFERROR(L$94/L$90*L$86,0) -> 58629.547 | ... X99: =IFERROR(X$94/X$90*X$86,0) -> 94620.268
B100: =B87 -> Other Cost | C100: =SUM(E100:X100) -> 6040533.3 | E100: =IFERROR(E$95/E$90*E$87,0) -> 0 | F100: =IFERROR(F$95/F$90*F$87,0) -> 0 | G100: =IFERROR(G$95/G$90*G$87,0) -> 1470000 | H100: =IFERROR(H$95/H$90*H$87,0) -> 359333.33 | I100: =IFERROR(I$95/I$90*I$87,0) -> 0 | J100: =IFERROR(J$95/J$90*J$87,0) -> 0 | K100: =IFERROR(K$95/K$90*K$87,0) -> 315000 | L100: =IFERROR(L$95/L$90*L$87,0) -> 455000 | ... X100: =IFERROR(X$95/X$90*X$87,0) -> 957600
B101: Total | E101: =SUM(E96:E100) -> 739845 | F101: =SUM(F96:F100) -> 758341.12 | G101: =SUM(G96:G100) -> 1.331073e+08 | H101: =SUM(H96:H100) -> 1.9998178e+08 | I101: =SUM(I96:I100) -> 54443.363 | J101: =SUM(J96:J100) -> 55804.447 | K101: =SUM(K96:K100) -> -139800.44 | L101: =SUM(L96:L100) -> -225926.01 | ... X101: =SUM(X96:X100) -> -138179.73
A103: # | B103: Ethanol plant
B104: Cost of Corn Purchase | E104: 7 | F104: 7 | G104: 7 | H104: 25 | I104: =H104 -> 25 | J104: =I104 -> 25 | K104: =J104 -> 25 | L104: 3 | M104: =L104 -> 3 | N104: =M104 -> 3 | O104: =N104 -> 3 | P104: =O104 -> 3 | Q104: =P104 -> 3 | R104: =Q104 -> 3 | S104: =R104 -> 3 | T104: =S104 -> 3 | ... X104: =W104 -> 3
B105: Labour Cost | E105: 7 | F105: =E105 -> 7 | G105: =F105 -> 7 | H105: 1 | I105: =H105 -> 1 | J105: =I105 -> 1 | K105: =J105 -> 1 | L105: =K105 -> 1 | M105: =L105 -> 1 | N105: =M105 -> 1 | O105: =N105 -> 1 | P105: =O105 -> 1 | ... X105: =W105 -> 1
B106: Power Cost | E106: 7 | F106: =E106 -> 7 | G106: =F106 -> 7 | H106: 1 | I106: 1 | J106: 1 | K106: 0 | L106: =K106 -> 0 | M106: =L106 -> 0 | N106: =M106 -> 0 | O106: =N106 -> 0 | P106: =O106 -> 0 | Q106: =P106 -> 0 | R106: =Q106 -> 0 | S106: =R106 -> 0 | ... X106: =W106 -> 0
B107: Salary for dedicated Staff | E107: 7 | F107: =E107 -> 7 | G107: =F107 -> 7 | H107: 1 | I107: =H107 -> 1 | J107: =I107 -> 1 | K107: =J107 -> 1 | L107: =K107 -> 1 | M107: =L107 -> 1 | N107: =M107 -> 1 | O107: =N107 -> 1 | P107: =O107 -> 1 | ... X107: =W107 -> 1
B108: Other Cost | E108: 7 | F108: =E108 -> 7 | G108: =F108 -> 7 | H108: 1 | I108: =H108 -> 1 | J108: =I108 -> 1 | K108: =J108 -> 1 | L108: =K108 -> 1 | M108: =L108 -> 1 | N108: =M108 -> 1 | O108: =N108 -> 1 | P108: =O108 -> 1 | ... X108: =W108 -> 1
A110: # | B110: Ethanol Plant
B111: =B$53 -> No..of days of operation(days) | C111: =C$53 -> 0 | D111: =D$53 -> 0 | E111: =E$53 -> 90 | F111: =F$53 -> 90 | G111: =G$53 -> 90 | H111: =H$53 -> 90 | I111: =I$53 -> 90 | ... Y111: =Y$53 -> 0
B112: =PL!B$29 -> Cost of Corn Purchase | C112: =PL!C$29 -> 0 | D112: =PL!D$29 -> 0 | E112: =PL!E$29 -> 0 | F112: =PL!F$29 -> 0 | G112: =PL!G$29 -> 1.9192045e+09 | H112: =PL!H$29 -> 1.8735092e+09 | I112: =PL!J$29 -> 1.8735092e+09 | J112: =PL!K$29 -> 1.8735092e+09 | K112: =PL!L$29 -> 7.1413459e+09 | L112: =PL!M$29 -> 0 | M112: =PL!O$29 -> 0 | N112: =PL!P$29 -> 0 | O112: =PL!Q$29 -> 7.3369993e+09 | P112: =PL!R$29 -> 0 | Q112: =PL!T$29 -> 0 | R112: =PL!U$29 -> 0 | S112: =PL!V$29 -> 7.5326526e+09 | T112: =PL!W$29 -> 0 | U112: =PL!Y$29 -> 0 | V112: =PL!Z$29 -> 0 | W112: =PL!AA$29 -> 7.7283059e+09 | X112: =PL!AB$29 -> 0
B113: =PL!B$30 -> Labour Cost | C113: =PL!C$30 -> 0 | D113: =PL!D$30 -> 0 | E113: =PL!E$30 -> 0 | F113: =PL!F$30 -> 0 | G113: =PL!G$30 -> 4569534.6 | H113: =PL!H$30 -> 4569534.6 | I113: =PL!J$30 -> 4569534.6 | J113: =PL!K$30 -> 4569534.6 | K113: =PL!L$30 -> 4698253.9 | L113: =PL!M$30 -> 4698253.9 | M113: =PL!O$30 -> 4698253.9 | N113: =PL!P$30 -> 4698253.9 | O113: =PL!Q$30 -> 4826973.2 | P113: =PL!R$30 -> 4826973.2 | Q113: =PL!T$30 -> 4826973.2 | R113: =PL!U$30 -> 4826973.2 | S113: =PL!V$30 -> 4955692.5 | T113: =PL!W$30 -> 4955692.5 | U113: =PL!Y$30 -> 4955692.5 | V113: =PL!Z$30 -> 4955692.5 | W113: =PL!AA$30 -> 5084411.8 | X113: =PL!AB$30 -> 5084411.8
B114: =PL!B$31 -> Power Cost | C114: =PL!C$31 -> 0 | D114: =PL!D$31 -> 0 | E114: =PL!E$31 -> 0 | F114: =PL!F$31 -> 0 | G114: =PL!G$31 -> -28737500 | H114: =PL!H$31 -> -28737500 | I114: =PL!J$31 -> -28737500 | J114: =PL!K$31 -> -28737500 | K114: =PL!L$31 -> -28737500 | L114: =PL!M$31 -> -28737500 | M114: =PL!O$31 -> -28737500 | N114: =PL!P$31 -> 731600.71 | O114: =PL!Q$31 -> -28737500 | P114: =PL!R$31 -> -28737500 | Q114: =PL!T$31 -> -28737500 | R114: =PL!U$31 -> 22382500 | S114: =PL!V$31 -> -28737500 | T114: =PL!W$31 -> -28737500 | U114: =PL!Y$31 -> -28737500 | V114: =PL!Z$31 -> -28737500 | W114: =PL!AA$31 -> -28737500 | X114: =PL!AB$31 -> -28737500
B115: =PL!B$32 -> Salary for dedicated Staff | C115: =PL!C$32 -> 0 | D115: =PL!D$32 -> 0 | E115: =PL!E$32 -> 3465525 | F115: =PL!F$32 -> 3552163.1 | G115: =PL!G$32 -> 4610168.8 | H115: =PL!H$32 -> 5139352.8 | I115: =PL!J$32 -> 5267836.6 | J115: =PL!K$32 -> 5399532.6 | K115: =PL!L$32 -> 5534520.9 | L115: =PL!M$32 -> 5672883.9 | M115: =PL!O$32 -> 5814706 | N115: =PL!P$32 -> 5960073.6 | O115: =PL!Q$32 -> 6109075.5 | P115: =PL!R$32 -> 6261802.4 | Q115: =PL!T$32 -> 6418347.4 | R115: =PL!U$32 -> 6578806.1 | S115: =PL!V$32 -> 6743276.3 | T115: =PL!W$32 -> 6911858.2 | U115: =PL!Y$32 -> 7084654.6 | V115: =PL!Z$32 -> 7261771 | W115: =PL!AA$32 -> 7443315.3 | X115: =PL!AB$32 -> 7629398.1
B116: =PL!B$34 -> Other Cost | C116: =PL!C$34 -> 0 | D116: =PL!D$34 -> 0 | E116: =PL!E$34 -> 0 | F116: =PL!F$34 -> 0 | G116: =PL!G$34 -> 58575000 | H116: =PL!H$34 -> 58575000 | I116: =PL!J$34 -> 58575000 | J116: =PL!K$34 -> 58575000 | K116: =PL!L$34 -> 60225000 | L116: =PL!M$34 -> 60225000 | M116: =PL!O$34 -> 60225000 | N116: =PL!P$34 -> 60225000 | O116: =PL!Q$34 -> 61875000 | P116: =PL!R$34 -> 61875000 | Q116: =PL!T$34 -> 61875000 | R116: =PL!U$34 -> 61875000 | S116: =PL!V$34 -> 63525000 | T116: =PL!W$34 -> 63525000 | U116: =PL!Y$34 -> 63525000 | V116: =PL!Z$34 -> 63525000 | W116: =PL!AA$34 -> 65175000 | X116: =PL!AB$34 -> 65175000
B117: Payables for Corn | C117: =SUM(E117:X117) -> 0 | E117: =IFERROR(E$112/E$111*#REF!,0) -> 0 | F117: =IFERROR(F$112/F$111*#REF!,0) -> 0 | G117: =IFERROR(G$112/G$111*#REF!,0) -> 0 | H117: =IFERROR(H$112/H$111*#REF!,0) -> 0 | I117: =IFERROR(I$112/I$111*#REF!,0) -> 0 | J117: =IFERROR(J$112/J$111*#REF!,0) -> 0 | K117: =IFERROR(K$112/K$111*#REF!,0) -> 0 | L117: =IFERROR(L$112/L$111*#REF!,0) -> 0 | ... X117: =IFERROR(X$112/X$111*#REF!,0) -> 0
B118: Labour Cost | C118: =SUM(E118:X118) -> 1308932.1 | E118: =IFERROR(E$113/E$111*E$105,0) -> 0 | F118: =IFERROR(F$113/F$111*F$105,0) -> 0 | G118: =IFERROR(G$113/G$111*G$105,0) -> 355408.25 | H118: =IFERROR(H$113/H$111*H$105,0) -> 50772.607 | I118: =IFERROR(I$113/I$111*I$105,0) -> 50772.607 | J118: =IFERROR(J$113/J$111*J$105,0) -> 50772.607 | K118: =IFERROR(K$113/K$111*K$105,0) -> 52202.821 | L118: =IFERROR(L$113/L$111*L$105,0) -> 52202.821 | ... X118: =IFERROR(X$113/X$111*X$105,0) -> 67792.157
B119: Power Cost | C119: =SUM(E119:X119) -> -3193055.6 | E119: =IFERROR(E$114/E$111*E$106,0) -> 0 | F119: =IFERROR(F$114/F$111*F$106,0) -> 0 | G119: =IFERROR(G$114/G$111*G$106,0) -> -2235138.9 | H119: =IFERROR(H$114/H$111*H$106,0) -> -319305.56 | I119: =IFERROR(I$114/I$111*I$106,0) -> -319305.56 | J119: =IFERROR(J$114/J$111*J$106,0) -> -319305.56 | K119: =IFERROR(K$114/K$111*K$106,0) -> 0 | L119: =IFERROR(L$114/L$111*L$106,0) -> 0 | ... X119: =IFERROR(X$114/X$111*X$106,0) -> 0
...

Sheet CFS
B1: No..of days of operation(days) | D1: =300/4 -> 75 | E1: =300/4 -> 75 | F1: =300/4 -> 75 | G1: =300/4 -> 75 | I1: =300/4 -> 75 | J1: =300/4 -> 75 | K1: =300/4 -> 75 | L1: =300/4 -> 75 | N1: =300/4 -> 75 | O1: =300/4 -> 75 | P1: =300/4 -> 75 | Q1: =300/4 -> 75 | S1: =300/4 -> 75 | T1: =300/4 -> 75 | U1: =300/4 -> 75 | V1: =300/4 -> 75 | X1: =300/4 -> 75 | Y1: =300/4 -> 75 | Z1: =300/4 -> 75 | AA1: =300/4 -> 75
B2: Column counter | D2: 1 | E2: =D2+1 -> 2 | F2: =E2+1 -> 3 | G2: =F2+1 -> 4 | I2: =G2+1 -> 5 | J2: =I2+1 -> 6 | K2: =J2+1 -> 7 | L2: =K2+1 -> 8 | N2: =L2+1 -> 9 | O2: =N2+1 -> 10 | P2: =O2+1 -> 11 | Q2: =P2+1 -> 12 | S2: =Q2+1 -> 13 | T2: =S2+1 -> 14 | U2: =T2+1 -> 15 | V2: =U2+1 -> 16 | X2: =V2+1 -> 17 | Y2: =X2+1 -> 18 | Z2: =Y2+1 -> 19 | AA2: =Z2+1 -> 20
B3: Particulars | D3: 45838 | E3: =EOMONTH(D3,3) -> 45930 | F3: =EOMONTH(E3,3) -> 46022 | G3: =EOMONTH(F3,3) -> 46112 | I3: =EOMONTH(G3,3) -> 46203 | J3: =EOMONTH(I3,3) -> 46295 | K3: =EOMONTH(J3,3) -> 46387 | L3: =EOMONTH(K3,3) -> 46477 | N3: =EOMONTH(L3,3) -> 46568 | O3: =EOMONTH(N3,3) -> 46660 | P3: =EOMONTH(O3,3) -> 46752 | Q3: =EOMONTH(P3,3) -> 46843 | S3: =EOMONTH(Q3,3) -> 46934 | T3: =EOMONTH(S3,3) -> 47026 | U3: =EOMONTH(T3,3) -> 47118 | V3: =EOMONTH(U3,3) -> 47208 | X3: =EOMONTH(V3,3) -> 47299 | Y3: =EOMONTH(X3,3) -> 47391 | Z3: =EOMONTH(Y3,3) -> 47483 | AA3: =EOMONTH(Z3,3) -> 47573
A5: # | B5: Cash From Operation
B6: Net Profits | D6: =PL!E53 -> 57938601 | E6: =PL!F53 -> 27364706 | F6: =PL!G53 -> 3.0600423e+08 | G6: =PL!H53 -> 3.7318523e+08 | I6: =PL!J53 -> 3.2207156e+08 | J6: =PL!K53 -> 3.2145327e+08 | K6: =PL!L53 -> 3.7096396e+08 | L6: =PL!M53 -> 6.8677917e+08 | N6: =PL!O53 -> 6.3467164e+08 | O6: =PL!P53 -> 6.0017727e+08 | P6: =PL!Q53 -> 4.8412354e+08 | Q6: =PL!R53 -> 7.5101083e+08 | S6: =PL!T53 -> 6.8871097e+08 | T6: =PL!U53 -> 6.3545882e+08 | U6: =PL!V53 -> 6.3450161e+08 | V6: =PL!W53 -> 8.0469128e+08 | X6: =PL!Y53 -> 7.2535222e+08 | Y6: =PL!Z53 -> 7.0692591e+08 | Z6: =PL!AA53 -> 6.9978356e+08 | AA6: =PL!AB53 -> 8.8242216e+08
B7: Add: D&A | D7: =PL!E46 -> 45302310 | E7: =PL!F46 -> 43603473 | F7: =PL!G46 -> 1.1616368e+08 | G7: =PL!H46 -> 1.1180755e+08 | I7: =PL!J46 -> 1.0761476e+08 | J7: =PL!K46 -> 1.0357921e+08 | K7: =PL!L46 -> 99694990 | L7: =PL!M46 -> 95956427 | N7: =PL!O46 -> 92358061 | O7: =PL!P46 -> 88894634 | P7: =PL!Q46 -> 85561085 | Q7: =PL!R46 -> 82352545 | S7: =PL!T46 -> 79264324 | T7: =PL!U46 -> 76291912 | U7: =PL!V46 -> 73430965 | V7: =PL!W46 -> 70677304 | X7: =PL!Y46 -> 68026905 | Y7: =PL!Z46 -> 65475896 | Z7: =PL!AA46 -> 63020550 | AA7: =PL!AB46 -> 60657280
B8: Add:interest Cost | D8: =PL!E47 -> 93282407 | E8: =PL!F47 -> 98489477 | F8: =PL!G47 -> 95443826 | G8: =PL!H47 -> 92434099 | I8: =PL!J47 -> 89457413 | J8: =PL!K47 -> 86510959 | K8: =PL!L47 -> 83592007 | L8: =PL!M47 -> 21408071 | N8: =PL!O47 -> 20783039 | O8: =PL!P47 -> 20148630 | P8: =PL!Q47 -> 19504706 | Q8: =PL!R47 -> 18851123 | S8: =PL!T47 -> 18187736 | T8: =PL!U47 -> 17514398 | U8: =PL!V47 -> 16830960 | V8: =PL!W47 -> 16137270 | X8: =PL!Y47 -> 15433176 | Y8: =PL!Z47 -> 14718519 | Z8: =PL!AA47 -> 13993143 | AA8: =PL!AB47 -> 13256887
B9: Change in WC | D9: =-BS!E50 -> -51493239 | E9: =-BS!F50 -> 7.5659738e+08 | F9: =-BS!G50 -> -7.5926788e+08 | G9: =-BS!H50 -> -5.1168239e+08 | I9: =-BS!I50 -> 3.6854398e+08 | J9: =-BS!J50 -> 5.2369097e+08 | K9: =-BS!K50 -> -6.7568365e+09 | L9: =-BS!L50 -> 2.3146335e+09 | N9: =-BS!M50 -> 2.2486253e+09 | O9: =-BS!N50 -> 2.1928698e+09 | P9: =-BS!O50 -> -7.1863315e+09 | Q9: =-BS!P50 -> 2.4531843e+09 | S9: =-BS!Q50 -> 2.3839598e+09 | T9: =-BS!R50 -> 2.3192426e+09 | U9: =-BS!S50 -> -7.8650975e+09 | V9: =-BS!T50 -> 2.6861557e+09 | X9: =-BS!U50 -> 2.4746229e+09 | Y9: =-BS!V50 -> 2.5323498e+09 | Z9: =-BS!W50 -> -8.4934752e+09 | AA9: =-BS!X50 -> 2.9200504e+09
B10: Cash From Operation | D10: =SUM(D6:D9) -> 1.4503008e+08 | E10: =SUM(E6:E9) -> 9.2605503e+08 | F10: =SUM(F6:F9) -> -2.4165615e+08 | G10: =SUM(G6:G9) -> 65744491 | I10: =SUM(I6:I9) -> 8.8768771e+08 | J10: =SUM(J6:J9) -> 1.0352344e+09 | K10: =SUM(K6:K9) -> -6.2025855e+09 | L10: =SUM(L6:L9) -> 3.1187772e+09 | N10: =SUM(N6:N9) -> 2.996438e+09 | O10: =SUM(O6:O9) -> 2.9020903e+09 | P10: =SUM(P6:P9) -> -6.5971422e+09 | Q10: =SUM(Q6:Q9) -> 3.3053988e+09 | S10: =SUM(S6:S9) -> 3.1701228e+09 | T10: =SUM(T6:T9) -> 3.0485077e+09 | U10: =SUM(U6:U9) -> -7.140334e+09 | V10: =SUM(V6:V9) -> 3.5776615e+09 | X10: =SUM(X6:X9) -> 3.2834352e+09 | Y10: =SUM(Y6:Y9) -> 3.3194701e+09 | Z10: =SUM(Z6:Z9) -> -7.716678e+09 | AA10: =SUM(AA6:AA9) -> 3.8763867e+09
A12: # | B12: Cash From Investing Activities
B13: Suger and power Plant | D13: =-(BS!E17-BS!C17-BS!E162) -> -7.4505806e-09 | E13: =-(BS!F17-BS!E17-BS!F162) -> 9.6857548e-08 | F13: =-(BS!G17-BS!F17-BS!G162) -> 0 | G13: =-(BS!H17-BS!G17-BS!H162) -> 5.2154064e-08 | I13: =-(BS!I17-BS!H17-BS!I162) -> 5.2154064e-08 | J13: =-(BS!J17-BS!I17-BS!J162) -> 2.9802322e-08 | K13: =-(BS!K17-BS!J17-BS!K162) -> -1.4901161e-08 | L13: =-(BS!L17-BS!K17-BS!L162) -> -2.9802322e-08 | N13: =-(BS!M17-BS!L17-BS!M162) -> -1.8626451e-08 | O13: =-(BS!N17-BS!M17-BS!N162) -> -5.9604645e-08 | P13: =-(BS!O17-BS!N17-BS!O162) -> 5.5879354e-08 | Q13: =-(BS!P17-BS!O17-BS!P162) -> -3.7252903e-08 | S13: =-(BS!Q17-BS!P17-BS!Q162) -> -3.7252903e-09 | T13: =-(BS!R17-BS!Q17-BS!R162) -> -1.1175871e-08 | U13: =-(BS!S17-BS!R17-BS!S162) -> -1.4901161e-08 | V13: =-(BS!T17-BS!S17-BS!T162) -> -4.0978193e-08 | X13: =-(BS!U17-BS!T17-BS!U162) -> -4.4703484e-08 | Y13: =-(BS!V17-BS!U17-BS!V162) -> -1.4901161e-08 | Z13: =-(BS!W17-BS!V17-BS!W162) -> -2.9802322e-08 | AA13: =-(BS!X17-BS!W17-BS!X162) -> 5.2154064e-08
B14: Ethanol Plant | D14: =-(BS!E16-BS!C16-BS!E168) -> 0 | E14: =-(BS!F16-BS!E16-BS!F168) -> -250000000 | F14: =-(BS!G16-BS!F16-BS!G168) -> 4.4703484e-08 | G14: =-(BS!H16-BS!G16-BS!H168) -> 7.4505806e-08 | I14: =-(BS!I16-BS!H16-BS!I168) -> -2.9802322e-08 | J14: =-(BS!J16-BS!I16-BS!J168) -> -6.7055225e-08 | K14: =-(BS!K16-BS!J16-BS!K168) -> -1.4901161e-08 | L14: =-(BS!L16-BS!K16-BS!L168) -> 5.9604645e-08 | N14: =-(BS!M16-BS!L16-BS!M168) -> 1.0430813e-07 | O14: =-(BS!N16-BS!M16-BS!N168) -> -4.4703484e-08 | P14: =-(BS!O16-BS!N16-BS!O168) -> -2.9802322e-08 | Q14: =-(BS!P16-BS!O16-BS!P168) -> -8.1956387e-08 | S14: =-(BS!Q16-BS!P16-BS!Q168) -> 1.1920929e-07 | T14: =-(BS!R16-BS!Q16-BS!R168) -> -8.9406967e-08 | U14: =-(BS!S16-BS!R16-BS!S168) -> -2.2351742e-08 | V14: =-(BS!T16-BS!S16-BS!T168) -> -2.9802322e-08 | X14: =-(BS!U16-BS!T16-BS!U168) -> -4.4703484e-08 | Y14: =-(BS!V16-BS!U16-BS!V168) -> 5.2154064e-08 | Z14: =-(BS!W16-BS!V16-BS!W168) -> -7.4505806e-09 | AA14: =-(BS!X16-BS!W16-BS!X168) -> -5.2154064e-08
B15: Cash From Investing Activities | D15: =SUM(D13:D14) -> -7.4505806e-09 | E15: =SUM(E13:E14) -> -2.5e+08 | F15: =SUM(F13:F14) -> 4.4703484e-08 | G15: =SUM(G13:G14) -> 1.2665987e-07 | I15: =SUM(I13:I14) -> 2.2351742e-08 | J15: =SUM(J13:J14) -> -3.7252903e-08 | K15: =SUM(K13:K14) -> -2.9802322e-08 | L15: =SUM(L13:L14) -> 2.9802322e-08 | N15: =SUM(N13:N14) -> 8.5681677e-08 | O15: =SUM(O13:O14) -> -1.0430813e-07 | P15: =SUM(P13:P14) -> 2.6077032e-08 | Q15: =SUM(Q13:Q14) -> -1.1920929e-07 | S15: =SUM(S13:S14) -> 1.15484e-07 | T15: =SUM(T13:T14) -> -1.0058284e-07 | U15: =SUM(U13:U14) -> -3.7252903e-08 | V15: =SUM(V13:V14) -> -7.0780516e-08 | X15: =SUM(X13:X14) -> -8.9406967e-08 | Y15: =SUM(Y13:Y14) -> 3.7252903e-08 | Z15: =SUM(Z13:Z14) -> -3.7252903e-08 | AA15: =SUM(AA13:AA14) -> 0
A17: # | B17: Cash From Financing Activities
B18: Equity Raised/(repaid) | D18: =BS!E37-BS!C37+BS!E39-BS!C39 -> 0 | E18: =BS!F37-BS!E37+BS!F39-BS!E39 -> 0 | F18: =BS!G37-BS!F37+BS!G39-BS!F39 -> 0 | G18: =BS!H37-BS!G37+BS!H39-BS!G39 -> 0 | I18: =BS!I37-BS!H37+BS!I39-BS!H39 -> 0 | J18: =BS!J37-BS!I37+BS!J39-BS!I39 -> 0 | K18: =BS!K37-BS!J37+BS!K39-BS!J39 -> 0 | L18: =BS!L37-BS!K37+BS!L39-BS!K39 -> 0 | N18: =BS!M37-BS!L37+BS!M39-BS!L39 -> 0 | O18: =BS!N37-BS!M37+BS!N39-BS!M39 -> 0 | P18: =BS!O37-BS!N37+BS!O39-BS!N39 -> 0 | Q18: =BS!P37-BS!O37+BS!P39-BS!O39 -> 0 | S18: =BS!Q37-BS!P37+BS!Q39-BS!P39 -> 0 | T18: =BS!R37-BS!Q37+BS!R39-BS!Q39 -> 0 | U18: =BS!S37-BS!R37+BS!S39-BS!R39 -> 0 | V18: =BS!T37-BS!S37+BS!T39-BS!S39 -> 0 | X18: =BS!U37-BS!T37+BS!U39-BS!T39 -> 0 | Y18: =BS!V37-BS!U37+BS!V39-BS!U39 -> 0 | Z18: =BS!W37-BS!V37+BS!W39-BS!V39 -> 0 | AA18: =BS!X37-BS!W37+BS!X39-BS!W39 -> 0
B19: Less:Interest on Debt | D19: =-D8 -> -93282407 | E19: =-E8 -> -98489477 | F19: =-F8 -> -95443826 | G19: =-G8 -> -92434099 | I19: =-I8 -> -89457413 | J19: =-J8 -> -86510959 | K19: =-K8 -> -83592007 | L19: =-L8 -> -21408071 | N19: =-N8 -> -20783039 | O19: =-O8 -> -20148630 | P19: =-P8 -> -19504706 | Q19: =-Q8 -> -18851123 | S19: =-S8 -> -18187736 | T19: =-T8 -> -17514398 | U19: =-U8 -> -16830960 | V19: =-V8 -> -16137270 | X19: =-X8 -> -15433176 | Y19: =-Y8 -> -14718519 | Z19: =-Z8 -> -13993143 | AA19: =-AA8 -> -13256887
B20: Debt Raised/(repaid) | D20: =BS!E31-BS!C31 -> 9.4859964e+08 | E20: =BS!F31-BS!E31 -> -73869545 | F20: =BS!G31-BS!F31 -> -75245800 | G20: =BS!H31-BS!G31 -> -76648734 | I20: =BS!I31-BS!H31 -> -78078883 | J20: =BS!J31-BS!I31 -> -79536793 | K20: =BS!K31-BS!J31 -> -1.2870902e+09 | L20: =BS!L31-BS!K31 -> -41668852 | N20: =BS!M31-BS!L31 -> -42293884 | O20: =BS!N31-BS!M31 -> -42928293 | P20: =BS!O31-BS!N31 -> -43572217 | Q20: =BS!P31-BS!O31 -> -44225800 | S20: =BS!Q31-BS!P31 -> -44889187 | T20: =BS!R31-BS!Q31 -> -45562525 | U20: =BS!S31-BS!R31 -> -46245963 | V20: =BS!T31-BS!S31 -> -46939653 | X20: =BS!U31-BS!T31 -> -47643747 | Y20: =BS!V31-BS!U31 -> -48358404 | Z20: =BS!W31-BS!V31 -> -49083780 | AA20: =BS!X31-BS!W31 -> -49820036
B21: Cash From Financing Activity | D21: =SUM(D18:D20) -> 8.5531723e+08 | E21: =SUM(E18:E20) -> -1.7235902e+08 | F21: =SUM(F18:F20) -> -1.7068963e+08 | G21: =SUM(G18:G20) -> -1.6908283e+08 | I21: =SUM(I18:I20) -> -1.675363e+08 | J21: =SUM(J18:J20) -> -1.6604775e+08 | K21: =SUM(K18:K20) -> -1.3706822e+09 | L21: =SUM(L18:L20) -> -63076923 | N21: =SUM(N18:N20) -> -63076923 | O21: =SUM(O18:O20) -> -63076923 | P21: =SUM(P18:P20) -> -63076923 | Q21: =SUM(Q18:Q20) -> -63076923 | S21: =SUM(S18:S20) -> -63076923 | T21: =SUM(T18:T20) -> -63076923 | U21: =SUM(U18:U20) -> -63076923 | V21: =SUM(V18:V20) -> -63076923 | X21: =SUM(X18:X20) -> -63076923 | Y21: =SUM(Y18:Y20) -> -63076923 | Z21: =SUM(Z18:Z20) -> -63076923 | AA21: =SUM(AA18:AA20) -> -63076923
A23: # | B23: Cash Schedule
B24: Opening Cash Bal | D24: =C26 -> 24920421 | E24: =D26 -> 1.0252677e+09 | F24: =E26 -> 1.5289637e+09 | G24: =F26 -> 1.116618e+09 | I24: =G26 -> 1.0132796e+09 | J24: =I26 -> 1.733431e+09 | K24: =J26 -> 2.6026177e+09 | L24: =K26 -> -4.9706501e+09 | N24: =L26 -> -1.9149498e+09 | O24: =N26 -> 1.0184113e+09 | P24: =O26 -> 3.8574247e+09 | Q24: =P26 -> -2.8027944e+09 | S24: =Q26 -> 4.3952753e+08 | T24: =S26 -> 3.5465734e+09 | U24: =T26 -> 6.5320042e+09 | V24: =U26 -> -6.7140671e+08 | X24: =V26 -> 2.8431779e+09 | Y24: =X26 -> 6.0635362e+09 | Z24: =Y26 -> 9.3199294e+09 | AA24: =Z26 -> 1.5401745e+09
B25: Add: Change in Cash during the year | D25: =D21+D15+D10 -> 1.0003473e+09 | E25: =E21+E15+E10 -> 5.0369601e+08 | F25: =F21+F15+F10 -> -4.1234577e+08 | G25: =G21+G15+G10 -> -1.0333834e+08 | I25: =I21+I15+I10 -> 7.2015142e+08 | J25: =J21+J15+J10 -> 8.6918666e+08 | K25: =K21+K15+K10 -> -7.5732678e+09 | L25: =L21+L15+L10 -> 3.0557003e+09 | N25: =N21+N15+N10 -> 2.9333611e+09 | O25: =O21+O15+O10 -> 2.8390134e+09 | P25: =P21+P15+P10 -> -6.6602191e+09 | Q25: =Q21+Q15+Q10 -> 3.2423219e+09 | S25: =S21+S15+S10 -> 3.1070459e+09 | T25: =T21+T15+T10 -> 2.9854308e+09 | U25: =U21+U15+U10 -> -7.2034109e+09 | V25: =V21+V15+V10 -> 3.5145846e+09 | X25: =X21+X15+X10 -> 3.2203583e+09 | Y25: =Y21+Y15+Y10 -> 3.2563932e+09 | Z25: =Z21+Z15+Z10 -> -7.7797549e+09 | AA25: =AA21+AA15+AA10 -> 3.8133098e+09
B26: Closing Cash Bal | C26: =BS!C8 -> 24920421 | D26: =SUM(D24:D25) -> 1.0252677e+09 | E26: =SUM(E24:E25) -> 1.5289637e+09 | F26: =SUM(F24:F25) -> 1.116618e+09 | G26: =SUM(G24:G25) -> 1.0132796e+09 | I26: =SUM(I24:I25) -> 1.733431e+09 | J26: =SUM(J24:J25) -> 2.6026177e+09 | K26: =SUM(K24:K25) -> -4.9706501e+09 | L26: =SUM(L24:L25) -> -1.9149498e+09 | N26: =SUM(N24:N25) -> 1.0184113e+09 | O26: =SUM(O24:O25) -> 3.8574247e+09 | P26: =SUM(P24:P25) -> -2.8027944e+09 | Q26: =SUM(Q24:Q25) -> 4.3952753e+08 | S26: =SUM(S24:S25) -> 3.5465734e+09 | T26: =SUM(T24:T25) -> 6.5320042e+09 | U26: =SUM(U24:U25) -> -6.7140671e+08 | V26: =SUM(V24:V25) -> 2.8431779e+09 | X26: =SUM(X24:X25) -> 6.0635362e+09 | Y26: =SUM(Y24:Y25) -> 9.3199294e+09 | Z26: =SUM(Z24:Z25) -> 1.5401745e+09 | AA26: =SUM(AA24:AA25) -> 5.3534843e+09
C28: =MIN(C26:AA26) -> -4.9706501e+09
B29: Opening Cash Balance
B30: Cash Generated During the year before Debt Infusion
B31: Minimum Cash Balance Required
A33: # | B33: BREAKUP OF 25 CR(equity)
B34: Ethanol Plant Capitalisation | C34: =-E14 -> 250000000
B35: WC Equity | C35: 100000000
B36: Total | C36: =SUM(C34:C35) -> 350000000
A38: # | B38: BREAKUP OF IPO FUND RAISE + DEBT FUND RAISE
B39: Working Capital | C39: =-K9 -> 6.7568365e+09
B40: Precurement Center Capitalisation | C40: =-SUM(K13:K14) -> 2.9802322e-08
B41: Repayment of Debt | C41: =-SUM(K20) -> 1.2870902e+09
B42: Total Requirement | C42: =SUM(C39:C41) -> 8.0439267e+09
B44: Sourced from Interal Funds | C44: =K24+K6+K7 -> 3.0732767e+09
A45: # | B45: Funding Requirement | C45: =SUM(C39:C41)-C44 -> 4.9706501e+09

Sheet Ethanol
B1: No..of days of operation(days) | E1: 0 | F1: 0 | G1: =330/4 -> 82.5 | H1: =330/4 -> 82.5 | J1: =H1 -> 82.5 | K1: =J1 -> 82.5 | L1: =G1 -> 82.5 | M1: =H1 -> 82.5 | O1: =J1 -> 82.5 | P1: =K1 -> 82.5 | Q1: =L1 -> 82.5 | R1: =M1 -> 82.5 | T1: =O1 -> 82.5 | U1: =P1 -> 82.5 | V1: =Q1 -> 82.5 | W1: =R1 -> 82.5 | Y1: =T1 -> 82.5 | Z1: =U1 -> 82.5 | AA1: =V1 -> 82.5 | AB1: =W1 -> 82.5
B2: Column counter | E2: 1 | F2: =E2+1 -> 2 | G2: =F2+1 -> 3 | H2: =G2+1 -> 4 | J2: =H2+1 -> 5 | K2: =J2+1 -> 6 | L2: =K2+1 -> 7 | M2: =L2+1 -> 8 | O2: =M2+1 -> 9 | P2: =O2+1 -> 10 | Q2: =P2+1 -> 11 | R2: =Q2+1 -> 12 | T2: =R2+1 -> 13 | U2: =T2+1 -> 14 | V2: =U2+1 -> 15 | W2: =V2+1 -> 16 | Y2: =W2+1 -> 17 | Z2: =Y2+1 -> 18 | AA2: =Z2+1 -> 19 | AB2: =AA2+1 -> 20
B3: Production quaterly | E3: 45838 | F3: =EOMONTH(E3,3) -> 45930 | G3: =EOMONTH(F3,3) -> 46022 | H3: =EDATE(G3,3) -> 46112 | I3: FY 25-26 | J3: =EOMONTH(H3,3) -> 46203 | K3: =EOMONTH(J3,3) -> 46295 | L3: =EOMONTH(K3,3) -> 46387 | M3: =EDATE(L3,3) -> 46477 | N3: FY 26-27 | O3: =EOMONTH(M3,3) -> 46568 | P3: =EOMONTH(O3,3) -> 46660 | Q3: =EOMONTH(P3,3) -> 46752 | R3: =EOMONTH(Q3,3) -> 46843 | S3: FY 27-28 | T3: =EOMONTH(R3,3) -> 46934 | U3: =EOMONTH(T3,3) -> 47026 | V3: =EOMONTH(U3,3) -> 47118 | W3: =EOMONTH(V3,3) -> 47208 | X3: FY 28-29 | Y3: =EOMONTH(W3,3) -> 47299 | Z3: =EOMONTH(Y3,3) -> 47391 | AA3: =EOMONTH(Z3,3) -> 47483 | AB3: =EDATE(AA3,3) -> 47573 | AC3: FY 29-30
AF4: 72 | AG4: =AF4*AE4 -> 0
A5: # | B5: Corn Consumpton | C5: 0.6 | AE5: 280 | AF5: 14 | AG5: =AF5*AE5 -> 3920
B6: Starch required | C6: Kl | E6: =E14/56.82% -> 0 | F6: =F14/56.82% -> 0 | G6: =G14/56.82% -> 51544.351 | H6: =H14/56.82% -> 51544.351 | J6: =J14/56.82% -> 51544.351 | K6: =K14/56.82% -> 51544.351 | L6: =L14/56.82% -> 52996.304 | M6: =M14/56.82% -> 52996.304 | O6: =O14/56.82% -> 52996.304 | P6: =P14/56.82% -> 52996.304 | Q6: =Q14/56.82% -> 54448.258 | R6: =R14/56.82% -> 54448.258 | T6: =T14/56.82% -> 54448.258 | U6: =U14/56.82% -> 54448.258 | V6: =V14/56.82% -> 55900.211 | W6: =W14/56.82% -> 55900.211 | Y6: =Y14/56.82% -> 55900.211 | Z6: =Z14/56.82% -> 55900.211 | AA6: =AA14/56.82% -> 57352.165 | AB6: =AB14/56.82% -> 57352.165
B7: =B5 -> Corn Consumpton | E7: =(E6/$C5)/E11 -> 0 | F7: =(F6/$C5)/F11 -> 0 | G7: =(G6/$C5)/G11 -> 91390.693 | H7: =(H6/$C5)/H11 -> 91390.693 | J7: =(J6/$C5)/J11 -> 91390.693 | K7: =(K6/$C5)/K11 -> 91390.693 | L7: =(L6/$C5)/L11 -> 93965.078 | M7: =(M6/$C5)/M11 -> 93965.078 | O7: =(O6/$C5)/O11 -> 93965.078 | P7: =(P6/$C5)/P11 -> 93965.078 | Q7: =(Q6/$C5)/Q11 -> 96539.464 | R7: =(R6/$C5)/R11 -> 96539.464 | T7: =(T6/$C5)/T11 -> 96539.464 | U7: =(U6/$C5)/U11 -> 96539.464 | V7: =(V6/$C5)/V11 -> 99113.85 | W7: =(W6/$C5)/W11 -> 99113.85 | Y7: =(Y6/$C5)/Y11 -> 99113.85 | Z7: =(Z6/$C5)/Z11 -> 99113.85 | AA7: =(AA6/$C5)/AA11 -> 101688.24 | AB7: =(AB6/$C5)/AB11 -> 101688.24
B9: Capacity Increase | E9: =350/400 -> 0.875 | F9: =E9 -> 0.875 | G9: =(355/400) -> 0.8875 | H9: =(355/400) -> 0.8875 | J9: =G9 -> 0.8875 | K9: =H9 -> 0.8875 | L9: =(365/400) -> 0.9125 | M9: =L9 -> 0.9125 | O9: =L9 -> 0.9125 | P9: =M9 -> 0.9125 | Q9: =(375/400) -> 0.9375 | R9: =(375/400) -> 0.9375 | T9: =Q9 -> 0.9375 | U9: =R9 -> 0.9375 | V9: =(385/400) -> 0.9625 | W9: =(385/400) -> 0.9625 | Y9: =V9 -> 0.9625 | Z9: =W9 -> 0.9625 | AA9: =(395/400) -> 0.9875 | AB9: =(395/400) -> 0.9875
B10: Plant Capacity Ethonol | C10: 400 | D10: KLD | E10: =$C10*E1*E9 -> 0 | F10: =$C10*F1*F9 -> 0 | G10: =$C10*G1*G9 -> 29287.5 | H10: =$C10*H1*H9 -> 29287.5 | J10: =$C10*J1*J9 -> 29287.5 | K10: =$C10*K1*K9 -> 29287.5 | L10: =$C10*L1*L9 -> 30112.5 | M10: =$C10*M1*M9 -> 30112.5 | O10: =$C10*O1*O9 -> 30112.5 | P10: =$C10*P1*P9 -> 30112.5 | Q10: =$C10*Q1*Q9 -> 30937.5 | R10: =$C10*R1*R9 -> 30937.5 | T10: =$C10*T1*T9 -> 30937.5 | U10: =$C10*U1*U9 -> 30937.5 | V10: =$C10*V1*V9 -> 31762.5 | W10: =$C10*W1*W9 -> 31762.5 | Y10: =$C10*Y1*Y9 -> 31762.5 | Z10: =$C10*Z1*Z9 -> 31762.5 | AA10: =$C10*AA1*AA9 -> 32587.5 | AB10: =$C10*AB1*AB9 -> 32587.5
B11: Fermentation effeciency | C11: 0.94 | E11: =$C$11 -> 0.94 | F11: =$C$11 -> 0.94 | G11: =$C$11 -> 0.94 | H11: =$C$11 -> 0.94 | J11: =$C$11 -> 0.94 | K11: =$C$11 -> 0.94 | L11: =$C$11 -> 0.94 | M11: =$C$11 -> 0.94 | O11: =$C$11 -> 0.94 | P11: =$C$11 -> 0.94 | Q11: =$C$11 -> 0.94 | R11: =$C$11 -> 0.94 | T11: =$C$11 -> 0.94 | U11: =$C$11 -> 0.94 | V11: =$C$11 -> 0.94 | W11: =$C$11 -> 0.94 | Y11: =$C$11 -> 0.94 | Z11: =$C$11 -> 0.94 | AA11: =$C$11 -> 0.94 | AB11: =$C$11 -> 0.94
B12: Starch Percentage | C12: 0.6
B14: Enthonol Production | D14: liters | E14: =E10 -> 0 | F14: =F10 -> 0 | G14: =G10 -> 29287.5 | H14: =H10 -> 29287.5 | J14: =J10 -> 29287.5 | K14: =K10 -> 29287.5 | L14: =L10 -> 30112.5 | M14: =M10 -> 30112.5 | O14: =O10 -> 30112.5 | P14: =P10 -> 30112.5 | Q14: =Q10 -> 30937.5 | R14: =R10 -> 30937.5 | T14: =T10 -> 30937.5 | U14: =U10 -> 30937.5 | V14: =V10 -> 31762.5 | W14: =W10 -> 31762.5 | Y14: =Y10 -> 31762.5 | Z14: =Z10 -> 31762.5 | AA14: =AA10 -> 32587.5 | AB14: =AB10 -> 32587.5
B15: Rate | C15: 71.86 | D15: per liter | E15: =$C$15*1000 -> 71860 | F15: =E15 -> 71860 | G15: =F15 -> 71860 | H15: =G15 -> 71860 | J15: =H15 -> 71860 | K15: =J15 -> 71860 | L15: =K15 -> 71860 | M15: =L15 -> 71860 | O15: =M15 -> 71860 | P15: =O15 -> 71860 | Q15: =P15 -> 71860 | R15: =Q15 -> 71860 | T15: =R15 -> 71860 | U15: =T15 -> 71860 | V15: =U15 -> 71860 | W15: =V15 -> 71860 | Y15: =W15 -> 71860 | Z15: =Y15 -> 71860 | AA15: =Z15 -> 71860 | AB15: =AA15 -> 71860
B16: Ethanol Price Inflation | C16: 0 | D16: pa | E16: 1 | F16: =E16*(1+$C16/4) -> 1 | G16: =F16*(1+$C16/4) -> 1 | H16: =G16*(1+$C16/4) -> 1 | J16: =H16*(1+$C16/4) -> 1 | K16: =J16*(1+$C16/4) -> 1 | L16: =K16*(1+$C16/4) -> 1 | M16: =L16*(1+$C16/4) -> 1 | O16: =M16*(1+$C16/4) -> 1 | P16: =O16*(1+$C16/4) -> 1 | Q16: =P16*(1+$C16/4) -> 1 | R16: =Q16*(1+$C16/4) -> 1 | T16: =R16*(1+$C16/4) -> 1 | U16: =T16*(1+$C16/4) -> 1 | V16: =U16*(1+$C16/4) -> 1 | W16: =V16*(1+$C16/4) -> 1 | Y16: =W16*(1+$C16/4) -> 1 | Z16: =Y16*(1+$C16/4) -> 1 | AA16: =Z16*(1+$C16/4) -> 1 | AB16: =AA16*(1+$C16/4) -> 1
A18: # | B18: Ethanol
B19: Opening Stock | E19: 0 | F19: =E22 -> 0 | G19: =F22 -> 0 | H19: =G22 -> 1065 | J19: =H22 -> 1103.7273 | K19: =J22 -> 1105.1355 | L19: =K22 -> 1105.1867 | M19: =L22 -> 1135.1886 | O19: =M22 -> 1136.2796 | P19: =O22 -> 1136.3193 | Q19: =P22 -> 1136.3207 | R19: =Q22 -> 1166.3208 | T19: =R22 -> 1167.4117 | U19: =T22 -> 1167.4513 | V19: =U22 -> 1167.4528 | W19: =V22 -> 1197.4528 | Y19: =W22 -> 1198.5437 | Z19: =Y22 -> 1198.5834 | AA19: =Z22 -> 1198.5849 | AB19: =AA22 -> 1228.5849
B20: Add: production | E20: =E14 -> 0 | F20: =F14 -> 0 | G20: =G14 -> 29287.5 | H20: =H14 -> 29287.5 | J20: =J14 -> 29287.5 | K20: =K14 -> 29287.5 | L20: =L14 -> 30112.5 | M20: =M14 -> 30112.5 | O20: =O14 -> 30112.5 | P20: =P14 -> 30112.5 | Q20: =Q14 -> 30937.5 | R20: =R14 -> 30937.5 | T20: =T14 -> 30937.5 | U20: =U14 -> 30937.5 | V20: =V14 -> 31762.5 | W20: =W14 -> 31762.5 | Y20: =Y14 -> 31762.5 | Z20: =Z14 -> 31762.5 | AA20: =AA14 -> 32587.5 | AB20: =AB14 -> 32587.5
B21: Less: Sales | E21: =IFERROR(SUM(E19:E20)*((E$1-$C$22)/E1),0) -> 0 | F21: =IFERROR(SUM(F19:F20)*((F$1-$C$22)/F1),0) -> 0 | G21: =IFERROR(SUM(G19:G20)*((G$1-$C$22)/G1),0) -> 28222.5 | H21: =IFERROR(SUM(H19:H20)*((H$1-$C$22)/H1),0) -> 29248.773 | I21: =IFERROR(SUM(I19:I20)*((I$1-$C$22)/I1),0) -> 0 | J21: =IFERROR(SUM(J19:J20)*((J$1-$C$22)/J1),0) -> 29286.092 | K21: =IFERROR(SUM(K19:K20)*((K$1-$C$22)/K1),0) -> 29287.449 | L21: =IFERROR(SUM(L19:L20)*((L$1-$C$22)/L1),0) -> 30082.498 | ... AC21: =IFERROR(SUM(AC19:AC20)*((AC$1-$C$22)/AC1),0) -> 0
B22: Closing Stock | C22: 3 | E22: =E19+E20-E21 -> 0 | F22: =F19+F20-F21 -> 0 | G22: =G19+G20-G21 -> 1065 | H22: =H19+H20-H21 -> 1103.7273 | J22: =J19+J20-J21 -> 1105.1355 | K22: =K19+K20-K21 -> 1105.1867 | L22: =L19+L20-L21 -> 1135.1886 | M22: =M19+M20-M21 -> 1136.2796 | O22: =O19+O20-O21 -> 1136.3193 | P22: =P19+P20-P21 -> 1136.3207 | Q22: =Q19+Q20-Q21 -> 1166.3208 | R22: =R19+R20-R21 -> 1167.4117 | T22: =T19+T20-T21 -> 1167.4513 | U22: =U19+U20-U21 -> 1167.4528 | V22: =V19+V20-V21 -> 1197.4528 | W22: =W19+W20-W21 -> 1198.5437 | Y22: =Y19+Y20-Y21 -> 1198.5834 | Z22: =Z19+Z20-Z21 -> 1198.5849 | AA22: =AA19+AA20-AA21 -> 1228.5849 | AB22: =AB19+AB20-AB21 -> 1229.6758
B24: Corn Stock | C24: tons
B25: =B19 -> Opening Stock | E25: 0 | F25: =E29 -> 0 | G25: =F29 -> 0 | H25: =G29 -> 0 | J25: =H29 -> 0 | K25: =J29 -> 0 | L25: =K29 -> 0 | M25: =L29 -> 281895.23 | O25: =M29 -> 187930.16 | P25: =O29 -> 93965.078 | Q25: =P29 -> 0 | R25: =Q29 -> 289618.39 | T25: =R29 -> 193078.93 | U25: =T29 -> 96539.464 | V25: =U29 -> 0 | W25: =V29 -> 297341.55 | Y25: =W29 -> 198227.7 | Z25: =Y29 -> 99113.85 | AA25: =Z29 -> 0 | AB25: =AA29 -> 305064.71
B26: Purchase | E26: =0 -> 0 | F26: =0 -> 0 | G26: =G7 -> 91390.693 | H26: =H7 -> 91390.693 | J26: =J7 -> 91390.693 | K26: =K7 -> 91390.693 | L26: =SUM(L7:M7,O7:P7) -> 375860.31 | Q26: =SUM(Q7:R7,T7:U7) -> 386157.86 | V26: =SUM(V7:W7,Y7:Z7) -> 396455.4 | AA26: =SUM(AA7:AB7)*2 -> 406752.94
B27: Total Available | E27: =SUM(E25:E26) -> 0 | F27: =SUM(F25:F26) -> 0 | G27: =SUM(G25:G26) -> 91390.693 | H27: =SUM(H25:H26) -> 91390.693 | J27: =SUM(J25:J26) -> 91390.693 | K27: =SUM(K25:K26) -> 91390.693 | L27: =SUM(L25:L26) -> 375860.31 | M27: =SUM(M25:M26) -> 281895.23 | O27: =SUM(O25:O26) -> 187930.16 | P27: =SUM(P25:P26) -> 93965.078 | Q27: =SUM(Q25:Q26) -> 386157.86 | R27: =SUM(R25:R26) -> 289618.39 | T27: =SUM(T25:T26) -> 193078.93 | U27: =SUM(U25:U26) -> 96539.464 | V27: =SUM(V25:V26) -> 396455.4 | W27: =SUM(W25:W26) -> 297341.55 | Y27: =SUM(Y25:Y26) -> 198227.7 | Z27: =SUM(Z25:Z26) -> 99113.85 | AA27: =SUM(AA25:AA26) -> 406752.94 | AB27: =SUM(AB25:AB26) -> 305064.71
B28: Less: Consumed | E28: =E7 -> 0 | F28: =F7 -> 0 | G28: =G7 -> 91390.693 | H28: =H7 -> 91390.693 | J28: =J7 -> 91390.693 | K28: =K7 -> 91390.693 | L28: =L7 -> 93965.078 | M28: =M7 -> 93965.078 | O28: =O7 -> 93965.078 | P28: =P7 -> 93965.078 | Q28: =Q7 -> 96539.464 | R28: =R7 -> 96539.464 | T28: =T7 -> 96539.464 | U28: =U7 -> 96539.464 | V28: =V7 -> 99113.85 | W28: =W7 -> 99113.85 | Y28: =Y7 -> 99113.85 | Z28: =Z7 -> 99113.85 | AA28: =AA7 -> 101688.24 | AB28: =AB7 -> 101688.24
B29: Closing Stock | E29: =E27-E28 -> 0 | F29: =F27-F28 -> 0 | G29: =G27-G28 -> 0 | H29: =H27-H28 -> 0 | J29: =J27-J28 -> 0 | K29: =K27-K28 -> 0 | L29: =L27-L28 -> 281895.23 | M29: =M27-M28 -> 187930.16 | O29: =O27-O28 -> 93965.078 | P29: =P27-P28 -> 0 | Q29: =Q27-Q28 -> 289618.39 | R29: =R27-R28 -> 193078.93 | T29: =T27-T28 -> 96539.464 | U29: =U27-U28 -> 0 | V29: =V27-V28 -> 297341.55 | W29: =W27-W28 -> 198227.7 | Y29: =Y27-Y28 -> 99113.85 | Z29: =Z27-Z28 -> 0 | AA29: =AA27-AA28 -> 305064.71 | AB29: =AB27-AB28 -> 203376.47
A31: # | B31: Ethanol sale value | D31: Rs | E31: =E21*E15*E16 -> 0 | F31: =F21*F15*F16 -> 0 | G31: =G21*G15*G16 -> 2028068850 | H31: =H21*H15*H16 -> 2.1018168e+09 | J31: =J21*J15*J16 -> 2.1044986e+09 | K31: =K21*K15*K16 -> 2.1045961e+09 | L31: =L21*L15*L16 -> 2.1617283e+09 | M31: =M21*M15*M16 -> 2.1638059e+09 | N31: =SUM(J31:M31) -> 8.5346288e+09 | O31: =O21*O15*O16 -> 2.1638814e+09 | P31: =P21*P15*P16 -> 2.1638841e+09 | Q31: =Q21*Q15*Q16 -> 2.2210129e+09 | R31: =R21*R15*R16 -> 2.2230904e+09 | T31: =T21*T15*T16 -> 2.2231659e+09 | U31: =U21*U15*U16 -> 2.2231686e+09 | V31: =V21*V15*V16 -> 2.2802974e+09 | W31: =W21*W15*W16 -> 2.2823749e+09 | Y31: =Y21*Y15*Y16 -> 2.2824504e+09 | Z31: =Z21*Z15*Z16 -> 2.2824531e+09 | AA31: =AA21*AA15*AA16 -> 2.3395819e+09 | AB31: =AB21*AB15*AB16 -> 2.3416594e+09
B33: DDGS Production | C33: 280 | D33: tons | E33: =$C$33*E7/1000 -> 0 | F33: =$C$33*F7/1000 -> 0 | G33: =$C$33*G7/1000 -> 25589.394 | H33: =$C$33*H7/1000 -> 25589.394 | J33: =$C$33*J7/1000 -> 25589.394 | K33: =$C$33*K7/1000 -> 25589.394 | L33: =$C$33*L7/1000 -> 26310.222 | M33: =$C$33*M7/1000 -> 26310.222 | O33: =$C$33*O7/1000 -> 26310.222 | P33: =$C$33*P7/1000 -> 26310.222 | Q33: =$C$33*Q7/1000 -> 27031.05 | R33: =$C$33*R7/1000 -> 27031.05 | T33: =$C$33*T7/1000 -> 27031.05 | U33: =$C$33*U7/1000 -> 27031.05 | V33: =$C$33*V7/1000 -> 27751.878 | W33: =$C$33*W7/1000 -> 27751.878 | Y33: =$C$33*Y7/1000 -> 27751.878 | Z33: =$C$33*Z7/1000 -> 27751.878 | AA33: =$C$33*AA7/1000 -> 28472.706 | AB33: =$C$33*AB7/1000 -> 28472.706
B34: Price per Kg | C34: 14.5 | E34: =C34*1000 -> 14500 | F34: =E34 -> 14500 | G34: =F34 -> 14500 | H34: =G34 -> 14500 | J34: =H34 -> 14500 | K34: =J34 -> 14500 | L34: =K34 -> 14500 | M34: =L34 -> 14500 | O34: =M34 -> 14500 | P34: =O34 -> 14500 | Q34: =P34 -> 14500 | R34: =Q34 -> 14500 | T34: =R34 -> 14500 | U34: =T34 -> 14500 | V34: =U34 -> 14500 | W34: =V34 -> 14500 | Y34: =W34 -> 14500 | Z34: =Y34 -> 14500 | AA34: =Z34 -> 14500 | AB34: =AA34 -> 14500
B35: DDGS price Inflation | C35: 0.02 | E35: 1 | F35: =E35*(1+$C35/4) -> 1.005 | G35: =F35*(1+$C35/4) -> 1.010025 | H35: =G35*(1+$C35/4) -> 1.0150751 | J35: =H35*(1+$C35/4) -> 1.0201505 | K35: =J35*(1+$C35/4) -> 1.0252513 | L35: =K35*(1+$C35/4) -> 1.0303775 | M35: =L35*(1+$C35/4) -> 1.0355294 | O35: =M35*(1+$C35/4) -> 1.040707 | P35: =O35*(1+$C35/4) -> 1.0459106 | Q35: =P35*(1+$C35/4) -> 1.0511401 | R35: =Q35*(1+$C35/4) -> 1.0563958 | T35: =R35*(1+$C35/4) -> 1.0616778 | U35: =T35*(1+$C35/4) -> 1.0669862 | V35: =U35*(1+$C35/4) -> 1.0723211 | W35: =V35*(1+$C35/4) -> 1.0776827 | Y35: =W35*(1+$C35/4) -> 1.0830712 | Z35: =Y35*(1+$C35/4) -> 1.0884865 | AA35: =Z35*(1+$C35/4) -> 1.0939289 | AB35: =AA35*(1+$C35/4) -> 1.0993986
B37: DDGS
B38: Opening Stock | E38: 0 | F38: =E41 -> 0 | G38: =F41 -> 0 | H38: =G41 -> 0 | J38: =H41 -> 0 | K38: =J41 -> 0 | L38: =K41 -> 0 | M38: =L41 -> 0 | O38: =M41 -> 0 | P38: =O41 -> 0 | Q38: =P41 -> 0 | R38: =Q41 -> 0 | T38: =R41 -> 0 | U38: =T41 -> 0 | V38: =U41 -> 0 | W38: =V41 -> 0 | Y38: =W41 -> 0 | Z38: =Y41 -> 0 | AA38: =Z41 -> 0 | AB38: =AA41 -> 0
B39: Add: production | E39: =E33 -> 0 | F39: =F33 -> 0 | G39: =G33 -> 25589.394 | H39: =H33 -> 25589.394 | J39: =J33 -> 25589.394 | K39: =K33 -> 25589.394 | L39: =L33 -> 26310.222 | M39: =M33 -> 26310.222 | O39: =O33 -> 26310.222 | P39: =P33 -> 26310.222 | Q39: =Q33 -> 27031.05 | R39: =R33 -> 27031.05 | T39: =T33 -> 27031.05 | U39: =U33 -> 27031.05 | V39: =V33 -> 27751.878 | W39: =W33 -> 27751.878 | Y39: =Y33 -> 27751.878 | Z39: =Z33 -> 27751.878 | AA39: =AA33 -> 28472.706 | AB39: =AB33 -> 28472.706
B40: Less: Sales | E40: =IFERROR(SUM(E38:E39)*((E$1-$C$41)/E1),0) -> 0 | F40: =IFERROR(SUM(F38:F39)*((F$1-$C$41)/F1),0) -> 0 | G40: =IFERROR(SUM(G38:G39)*((G$1-$C$41)/G1),0) -> 25589.394 | H40: =IFERROR(SUM(H38:H39)*((H$1-$C$41)/H1),0) -> 25589.394 | I40: =IFERROR(SUM(I38:I39)*((I$1-$C$41)/I1),0) -> 0 | J40: =IFERROR(SUM(J38:J39)*((J$1-$C$41)/J1),0) -> 25589.394 | K40: =IFERROR(SUM(K38:K39)*((K$1-$C$41)/K1),0) -> 25589.394 | L40: =IFERROR(SUM(L38:L39)*((L$1-$C$41)/L1),0) -> 26310.222 | ... AC40: =IFERROR(SUM(AC38:AC39)*((AC$1-$C$41)/AC1),0) -> 0
B41: Closing Stock | C41: 0 | D41: Days | E41: =E38+E39-E40 -> 0 | F41: =F38+F39-F40 -> 0 | G41: =G38+G39-G40 -> 0 | H41: =H38+H39-H40 -> 0 | J41: =J38+J39-J40 -> 0 | K41: =K38+K39-K40 -> 0 | L41: =L38+L39-L40 -> 0 | M41: =M38+M39-M40 -> 0 | O41: =O38+O39-O40 -> 0 | P41: =P38+P39-P40 -> 0 | Q41: =Q38+Q39-Q40 -> 0 | R41: =R38+R39-R40 -> 0 | T41: =T38+T39-T40 -> 0 | U41: =U38+U39-U40 -> 0 | V41: =V38+V39-V40 -> 0 | W41: =W38+W39-W40 -> 0 | Y41: =Y38+Y39-Y40 -> 0 | Z41: =Z38+Z39-Z40 -> 0 | AA41: =AA38+AA39-AA40 -> 0 | AB41: =AB38+AB39-AB40 -> 0
A43: # | B43: DDGS Sale value | E43: =E40*E34*E35 -> 0 | F43: =F40*F34*F35 -> 0 | G43: =G40*G34*G35 -> 3.7476595e+08 | H43: =H40*H34*H35 -> 3.7663978e+08 | J43: =J40*J34*J35 -> 3.7852298e+08 | K43: =K40*K34*K35 -> 3.8041559e+08 | L43: =L40*L34*L35 -> 3.9308718e+08 | M43: =M40*M34*M35 -> 3.9505262e+08 | N43: =SUM(J43:M43) -> 1.5470784e+09 | O43: =O40*O34*O35 -> 3.9702788e+08 | P43: =P40*P34*P35 -> 3.9901302e+08 | Q43: =Q40*Q34*Q35 -> 4.1199461e+08 | R43: =R40*R34*R35 -> 4.1405458e+08 | T43: =T40*T34*T35 -> 4.1612486e+08 | U43: =U40*U34*U35 -> 4.1820548e+08 | V43: =V40*V34*V35 -> 4.3150441e+08 | W43: =W40*W34*W35 -> 4.3366194e+08 | Y43: =Y40*Y34*Y35 -> 4.3583025e+08 | Z43: =Z40*Z34*Z35 -> 4.380094e+08 | AA43: =AA40*AA34*AA35 -> 4.516332e+08 | AB43: =AB40*AB34*AB35 -> 4.5389136e+08
B45: Cost of Corn | G45: 21000 | H45: 20500 | J45: =H45 -> 20500 | K45: =J45 -> 20500 | L45: 19000 | M45: =H45 -> 20500 | N45: =SUM(N43,N31) -> 1.0081707e+10 | O45: 21000 | P45: 21000 | Q45: 19000 | R45: =M45 -> 20500 | T45: 21000 | U45: 21000 | V45: 19000 | W45: =R45 -> 20500 | Y45: 21000 | Z45: 21000 | AA45: 19000 | AB45: =W45 -> 20500
B47: Cost of Corn Purchase | C47: 20000 | D47: per ton | E47: =E45*E$26 -> 0 | F47: =F45*F$26 -> 0 | G47: =G45*G$26 -> 1.9192045e+09 | H47: =H45*H$26 -> 1.8735092e+09 | J47: =J45*J$26 -> 1.8735092e+09 | K47: =K45*K$26 -> 1.8735092e+09 | L47: =L45*L$26 -> 7.1413459e+09 | M47: =M45*M$26 -> 0 | O47: =O45*O$26 -> 0 | P47: =P45*P$26 -> 0 | Q47: =Q45*Q$26 -> 7.3369993e+09 | R47: =R45*R$26 -> 0 | T47: =T45*T$26 -> 0 | U47: =U45*U$26 -> 0 | V47: =V45*V$26 -> 7.5326526e+09 | W47: =W45*W$26 -> 0 | Y47: =Y45*Y$26 -> 0 | Z47: =Z45*Z$26 -> 0 | AA47: =AA45*AA$26 -> 7.7283059e+09 | AB47: =AB45*AB$26 -> 0
B48: Labour Cost | C48: 50 | D48: per ton | E48: =$C48*E$7 -> 0 | F48: =$C48*F$7 -> 0 | G48: =$C48*G$7 -> 4569534.6 | H48: =$C48*H$7 -> 4569534.6 | J48: =$C48*J$7 -> 4569534.6 | K48: =$C48*K$7 -> 4569534.6 | L48: =$C48*L$7 -> 4698253.9 | M48: =$C48*M$7 -> 4698253.9 | O48: =$C48*O$7 -> 4698253.9 | P48: =$C48*P$7 -> 4698253.9 | Q48: =$C48*Q$7 -> 4826973.2 | R48: =$C48*R$7 -> 4826973.2 | T48: =$C48*T$7 -> 4826973.2 | U48: =$C48*U$7 -> 4826973.2 | V48: =$C48*V$7 -> 4955692.5 | W48: =$C48*W$7 -> 4955692.5 | Y48: =$C48*Y$7 -> 4955692.5 | Z48: =$C48*Z$7 -> 4955692.5 | AA48: =$C48*AA$7 -> 5084411.8 | AB48: =$C48*AB$7 -> 5084411.8
B49: Power Cost | E49: =Power!E55 -> 0 | F49: =Power!F55 -> 0 | G49: =Power!G55 -> -28737500 | H49: =Power!H55 -> -28737500 | J49: =Power!J55 -> -28737500 | K49: =Power!K55 -> -28737500 | L49: =Power!L55 -> -28737500 | M49: =Power!M55 -> -28737500 | O49: =Power!O55 -> -28737500 | P49: =Power!P55 -> 731600.71 | Q49: =Power!Q55 -> -28737500 | R49: =Power!R55 -> -28737500 | T49: =Power!T55 -> -28737500 | U49: =Power!U55 -> 22382500 | V49: =Power!V55 -> -28737500 | W49: =Power!W55 -> -28737500 | Y49: =Power!Y55 -> -28737500 | Z49: =Power!Z55 -> -28737500 | AA49: =Power!AA55 -> -28737500 | AB49: =Power!AB55 -> -28737500
B50: Salary for dedicated Staff | E50: =Employee!E30 -> 3465525 | F50: =Employee!F30 -> 3552163.1 | G50: =Employee!G30 -> 4610168.8 | H50: =Employee!H30 -> 5139352.8 | I50: =Employee!I30 -> 16767210 | J50: =Employee!J30 -> 5267836.6 | K50: =Employee!K30 -> 5399532.6 | L50: =Employee!L30 -> 5534520.9 | ... AC50: =Employee!AC30 -> 29419139
B51: =Sugar!B82 -> Other Cost | C51: 2000 | D51: per kld | E51: =$C51*E$20 -> 0 | F51: =$C51*F$20 -> 0 | G51: =$C51*G$20 -> 58575000 | H51: =$C51*H$20 -> 58575000 | J51: =$C51*J$20 -> 58575000 | K51: =$C51*K$20 -> 58575000 | L51: =$C51*L$20 -> 60225000 | M51: =$C51*M$20 -> 60225000 | O51: =$C51*O$20 -> 60225000 | P51: =$C51*P$20 -> 60225000 | Q51: =$C51*Q$20 -> 61875000 | R51: =$C51*R$20 -> 61875000 | T51: =$C51*T$20 -> 61875000 | U51: =$C51*U$20 -> 61875000 | V51: =$C51*V$20 -> 63525000 | W51: =$C51*W$20 -> 63525000 | Y51: =$C51*Y$20 -> 63525000 | Z51: =$C51*Z$20 -> 63525000 | AA51: =$C51*AA$20 -> 65175000 | AB51: =$C51*AB$20 -> 65175000
N52: =SUM(J47:M51) -> 1.1051425e+10
N53: =-N45-N52 -> -2.1133132e+10
B54: Power Cost per ltr | G54: =G49/(G20*1000) -> -0.98122066 | H54: =H49/(H20*1000) -> -0.98122066 | J54: =J49/(J20*1000) -> -0.98122066 | K54: =K49/(K20*1000) -> -0.98122066 | L54: =L49/(L20*1000) -> -0.9543379 | M54: =M49/(M20*1000) -> -0.9543379 | O54: =O49/(O20*1000) -> -0.9543379 | P54: =P49/(P20*1000) -> 0.024295582 | Q54: =Q49/(Q20*1000) -> -0.92888889 | R54: =R49/(R20*1000) -> -0.92888889 | T54: =T49/(T20*1000) -> -0.92888889 | U54: =U49/(U20*1000) -> 0.72347475 | V54: =V49/(V20*1000) -> -0.9047619 | W54: =W49/(W20*1000) -> -0.9047619 | Y54: =Y49/(Y20*1000) -> -0.9047619 | Z54: =Z49/(Z20*1000) -> -0.9047619 | AA54: =AA49/(AA20*1000) -> -0.88185654 | AB54: =AB49/(AB20*1000) -> -0.88185654
B55: Per ltr cost of Ethonol | E55: =G55 -> 66.210756 | F55: =E55 -> 66.210756 | G55: =SUM(E47:H51)/SUM(E20:H20)/1000 -> 66.210756 | H55: =G55 -> 66.210756 | J55: =L55 -> 61.484901 | K55: =J55 -> 61.484901 | L55: =(SUM(J47:M51)-SUM(J47:K47))/SUM(J20:M20)/1000 -> 61.484901 | M55: =L55 -> 61.484901 | O55: =Q55 -> 61.743771 | P55: =O55 -> 61.743771 | Q55: =SUM(O47:R51)/SUM(O20:R20)/1000 -> 61.743771 | R55: =Q55 -> 61.743771 | T55: =V55 -> 61.92855 | U55: =T55 -> 61.92855 | V55: =SUM(T47:W51)/SUM(T20:W20)/1000 -> 61.92855 | W55: =V55 -> 61.92855 | Y55: =AA55 -> 61.540445 | Z55: =Y55 -> 61.540445 | AA55: =SUM(Y47:AB51)/SUM(Y20:AB20)/1000 -> 61.540445 | AB55: =AA55 -> 61.540445

Sheet Sugar
B1: No..of days of operation(days) | E1: 0 | F1: 0 | G1: =330/4 -> 82.5 | H1: =330/4 -> 82.5 | J1: =H1 -> 82.5 | K1: =J1 -> 82.5 | L1: =G1 -> 82.5 | M1: =H1 -> 82.5 | O1: =J1 -> 82.5 | P1: =K1 -> 82.5 | Q1: =L1 -> 82.5 | R1: =M1 -> 82.5 | T1: =O1 -> 82.5 | U1: =P1 -> 82.5 | V1: =Q1 -> 82.5 | W1: =R1 -> 82.5 | Y1: =T1 -> 82.5 | Z1: =U1 -> 82.5 | AA1: =V1 -> 82.5 | AB1: =W1 -> 82.5
B2: Column counter | E2: 1 | F2: =E2+1 -> 2 | G2: =F2+1 -> 3 | H2: =G2+1 -> 4 | J2: =H2+1 -> 5 | K2: =J2+1 -> 6 | L2: =K2+1 -> 7 | M2: =L2+1 -> 8 | O2: =M2+1 -> 9 | P2: =O2+1 -> 10 | Q2: =P2+1 -> 11 | R2: =Q2+1 -> 12 | T2: =R2+1 -> 13 | U2: =T2+1 -> 14 | V2: =U2+1 -> 15 | W2: =V2+1 -> 16 | Y2: =W2+1 -> 17 | Z2: =Y2+1 -> 18 | AA2: =Z2+1 -> 19 | AB2: =AA2+1 -> 20
B3: Production quaterly | E3: 45838 | F3: =EOMONTH(E3,3) -> 45930 | G3: =EOMONTH(F3,3) -> 46022 | H3: =EOMONTH(G3,3) -> 46112 | J3: =EOMONTH(H3,3) -> 46203 | K3: =EOMONTH(J3,3) -> 46295 | L3: =EOMONTH(K3,3) -> 46387 | M3: =EOMONTH(L3,3) -> 46477 | O3: =EOMONTH(M3,3) -> 46568 | P3: =EOMONTH(O3,3) -> 46660 | Q3: =EOMONTH(P3,3) -> 46752 | R3: =EOMONTH(Q3,3) -> 46843 | T3: =EOMONTH(R3,3) -> 46934 | U3: =EOMONTH(T3,3) -> 47026 | V3: =EOMONTH(U3,3) -> 47118 | W3: =EOMONTH(V3,3) -> 47208 | Y3: =EOMONTH(W3,3) -> 47299 | Z3: =EOMONTH(Y3,3) -> 47391 | AA3: =EOMONTH(Z3,3) -> 47483 | AB3: =EOMONTH(AA3,3) -> 47573
B5: Sugar Production
B6: Days of Production | E6: 0 | F6: 0 | G6: 45 | H6: 55 | J6: 0 | K6: 0 | L6: 45 | M6: 65 | O6: 0 | P6: 0 | Q6: 50 | R6: 70 | T6: 0 | U6: 0 | V6: 50 | W6: 80 | Y6: 0 | Z6: 0 | AA6: 50 | AB6: 90
C7: 550000
B8: Effeceincy | C8: =C7/C23 -> 68.75
B9: Day capacity | C9: 8000
B10: Max crushing | C10: 1000000
C11: =C10/C9 -> 125
C12: 140
C13: =C12*C9*95% -> 1064000
B15: Plant Effeciency Factor | E15: 0 | F15: 0 | G15: 0.7 | H15: 0.7 | J15: 0 | K15: 0 | L15: 0.75 | M15: 0.75 | O15: 0 | P15: 0 | Q15: 0.8 | R15: 0.8 | T15: 0 | U15: 0 | V15: 0.87 | W15: 0.87 | Y15: 0 | Z15: 0 | AA15: 0.95 | AB15: 0.95
B17: Suger Production | E17: 0 | F17: 0 | G17: 0.1 | H17: 0.1175 | J17: 0 | K17: 0 | L17: =G17 -> 0.1 | M17: =H17 -> 0.1175 | O17: 0 | P17: 0 | Q17: =L17 -> 0.1 | R17: =M17 -> 0.1175 | T17: 0 | U17: 0 | V17: =Q17 -> 0.1 | W17: =R17 -> 0.1175 | Y17: 0 | Z17: 0 | AA17: =V17 -> 0.1 | AB17: =W17 -> 0.1175
B18: Molases Production | E18: 0 | F18: 0 | G18: 0.045 | H18: 0.045 | J18: 0 | K18: 0 | L18: 0.045 | M18: 0.045 | O18: 0 | P18: 0 | Q18: 0.045 | R18: 0.045 | T18: 0 | U18: 0 | V18: 0.045 | W18: 0.045 | Y18: 0 | Z18: 0 | AA18: 0.045 | AB18: 0.045
B19: Bagasse producton | E19: 0 | F19: 0 | G19: 0.28 | H19: 0.24 | J19: 0 | K19: 0 | L19: 0.28 | M19: 0.24 | O19: 0 | P19: 0 | Q19: 0.28 | R19: 0.24 | T19: 0 | U19: 0 | V19: 0.28 | W19: 0.24 | Y19: 0 | Z19: 0 | AA19: 0.28 | AB19: 0.24
B20: Press Mud Production | E20: 0 | F20: 0 | G20: 0.03 | H20: 0.03 | J20: 0 | K20: 0 | L20: 0.03 | M20: 0.03 | O20: 0 | P20: 0 | Q20: 0.03 | R20: 0.03 | T20: 0 | U20: 0 | V20: 0.03 | W20: 0.03 | Y20: 0 | Z20: 0 | AA20: 0.03 | AB20: 0.03
B23: Sugarcane processed | C23: 8000 | D23: ton/day | E23: =$C$23*E6*E15 -> 0 | F23: =$C$23*F6*F15 -> 0 | G23: =$C$23*G6*G15 -> 252000 | H23: =$C$23*H6*H15 -> 308000 | I23: =$C$23*I6*I15 -> 0 | J23: =$C$23*J6*J15 -> 0 | K23: =$C$23*K6*K15 -> 0 | L23: =$C$23*L6*L15 -> 270000 | ... AB23: =$C$23*AB6*AB15 -> 684000
B25: Sugar recovery/production | D25: ton/year | E25: 0 | F25: 0 | G25: =G$23*G17 -> 25200 | H25: =H$23*H17 -> 36190 | J25: 0 | K25: 0 | L25: =L$23*L17 -> 27000 | M25: =M$23*M17 -> 45825 | N25: =N$23*N17 -> 0 | O25: 0 | P25: 0 | Q25: =Q$23*Q17 -> 32000 | R25: =R$23*R17 -> 52640 | S25: =S$23*S17 -> 0 | T25: 0 | U25: 0 | V25: =V$23*V17 -> 34800 | W25: =W$23*W17 -> 65424 | X25: =X$23*X17 -> 0 | Y25: 0 | Z25: 0 | AA25: =AA$23*AA17 -> 38000 | AB25: =AB$23*AB17 -> 80370
B26: Molases production | D26: ton/year | E26: 0 | F26: 0 | G26: =G$23*G18 -> 11340 | H26: =H$23*H18 -> 13860 | J26: 0 | K26: 0 | L26: =L$23*L18 -> 12150 | M26: =M$23*M18 -> 17550 | O26: 0 | P26: 0 | Q26: =Q$23*Q18 -> 14400 | R26: =R$23*R18 -> 20160 | T26: 0 | U26: 0 | V26: =V$23*V18 -> 15660 | W26: =W$23*W18 -> 25056 | Y26: 0 | Z26: 0 | AA26: =AA$23*AA18 -> 17100 | AB26: =AB$23*AB18 -> 30780
B27: Bagasse production | D27: ton/year | E27: 0 | F27: 0 | G27: =G$23*G19 -> 70560 | H27: =H$23*H19 -> 73920 | J27: 0 | K27: 0 | L27: =L$23*L19 -> 75600 | M27: =M$23*M19 -> 93600 | O27: 0 | P27: 0 | Q27: =Q$23*Q19 -> 89600 | R27: =R$23*R19 -> 107520 | T27: 0 | U27: 0 | V27: =V$23*V19 -> 97440 | W27: =W$23*W19 -> 133632 | Y27: 0 | Z27: 0 | AA27: =AA$23*AA19 -> 106400 | AB27: =AB$23*AB19 -> 164160
B28: Press Mud Production | D28: ton/year | E28: 0 | F28: 0 | G28: =G$23*G20 -> 7560 | H28: =H$23*H20 -> 9240 | J28: 0 | K28: 0 | L28: =L$23*L20 -> 8100 | M28: =M$23*M20 -> 11700 | O28: 0 | P28: 0 | Q28: =Q$23*Q20 -> 9600 | R28: =R$23*R20 -> 13440 | T28: 0 | U28: 0 | V28: =V$23*V20 -> 10440 | W28: =W$23*W20 -> 16704 | Y28: 0 | Z28: 0 | AA28: =AA$23*AA20 -> 11400 | AB28: =AB$23*AB20 -> 20520
B30: Procurement
A31: # | B31: Sugarcane stock
B33: Opening Stock | C33: 0 | D33: (ton) | E33: =C37 -> 0 | F33: =E37 -> 0 | G33: =F37 -> 0 | H33: =G37 -> 0 | J33: =H37 -> 0 | K33: =J37 -> 0 | L33: =K37 -> 0 | M33: =L37 -> 390000 | O33: =M37 -> 0 | P33: =O37 -> 0 | Q33: =P37 -> 0 | R33: =Q37 -> 448000 | T33: =R37 -> 0 | U33: =T37 -> 0 | V33: =U37 -> 0 | W33: =V37 -> 556800 | Y33: =W37 -> 0 | Z33: =Y37 -> 0 | AA33: =Z37 -> 0 | AB33: =AA37 -> 684000
B34: Add: cane procured | C34: 0 | D34: (ton) | E34: 0 | F34: 0 | G34: =G23 -> 252000 | H34: =H23 -> 308000 | J34: =(($C$23/4)/Ethanol!J$1*55)*J$6 -> 0 | K34: =(($C$23/4)/Ethanol!K$1*55)*K$6 -> 0 | L34: =L23+M23 -> 660000 | O34: =(($C$23/4)/Ethanol!O$1*55)*O$6 -> 0 | P34: =(($C$23/4)/Ethanol!P$1*55)*P$6 -> 0 | Q34: =Q23+R23 -> 768000 | T34: =(($C$23/4)/Ethanol!T$1*55)*T$6 -> 0 | U34: =(($C$23/4)/Ethanol!U$1*55)*U$6 -> 0 | V34: =V23+W23 -> 904800 | Y34: =(($C$23/4)/Ethanol!Y$1*55)*Y$6 -> 0 | Z34: =(($C$23/4)/Ethanol!Z$1*55)*Z$6 -> 0 | AA34: =AA23+AB23 -> 1064000
B35: Total Available | C35: =C33+C34 -> 0 | D35: (ton) | E35: =SUM(E33:E34) -> 0 | F35: =SUM(F33:F34) -> 0 | G35: =SUM(G33:G34) -> 252000 | H35: =SUM(H33:H34) -> 308000 | I35: =SUM(I33:I34) -> 0 | J35: =SUM(J33:J34) -> 0 | K35: =SUM(K33:K34) -> 0 | L35: =SUM(L33:L34) -> 660000 | ... AB35: =SUM(AB33:AB34) -> 684000
B36: Less: Cane crushed | C36: 0 | D36: (ton) | E36: =E23 -> 0 | F36: =F23 -> 0 | G36: =G23 -> 252000 | H36: =H23 -> 308000 | I36: =I23 -> 0 | J36: =J23 -> 0 | K36: =K23 -> 0 | L36: =L23 -> 270000 | ... AB36: =AB23 -> 684000
B37: Closing Stock | C37: =C35-C36 -> 0 | E37: =E35-E36 -> 0 | F37: =F35-F36 -> 0 | G37: =G35-G36 -> 0 | H37: =H35-H36 -> 0 | J37: =J35-J36 -> 0 | K37: =K35-K36 -> 0 | L37: =L35-L36 -> 390000 | M37: =M35-M36 -> 0 | O37: =O35-O36 -> 0 | P37: =P35-P36 -> 0 | Q37: =Q35-Q36 -> 448000 | R37: =R35-R36 -> 0 | T37: =T35-T36 -> 0 | U37: =U35-U36 -> 0 | V37: =V35-V36 -> 556800 | W37: =W35-W36 -> 0 | Y37: =Y35-Y36 -> 0 | Z37: =Z35-Z36 -> 0 | AA37: =AA35-AA36 -> 684000 | AB37: =AB35-AB36 -> 0
B39: Finished Goods
A40: # | B40: Suger
B41: Opening Stock | E41: =D44 -> 50357.143 | F41: =E44 -> 30178.571 | G41: =F44 -> 6035.7143 | H41: =G44 -> 15617.857 | J41: =H44 -> 36265.5 | K41: =J44 -> 18132.75 | L41: =K44 -> 1813.275 | M41: =L44 -> 11525.31 | O41: =M44 -> 38424.708 | P41: =O44 -> 19212.354 | Q41: =P44 -> 1921.2354 | R41: =Q44 -> 13568.494 | T41: =R44 -> 44359.691 | U41: =T44 -> 22179.846 | V41: =U44 -> 2217.9846 | W41: =V44 -> 14807.194 | Y41: =W44 -> 53754.9 | Z41: =Y44 -> 26877.45 | AA41: =Z44 -> 2687.745 | AB41: =AA44 -> 16275.098
B42: Add: production | E42: =E25 -> 0 | F42: =F25 -> 0 | G42: =G25 -> 25200 | H42: =H25 -> 36190 | J42: =J25 -> 0 | K42: =K25 -> 0 | L42: =L25 -> 27000 | M42: =M25 -> 45825 | O42: =O25 -> 0 | P42: =P25 -> 0 | Q42: =Q25 -> 32000 | R42: =R25 -> 52640 | T42: =T25 -> 0 | U42: =U25 -> 0 | V42: =V25 -> 34800 | W42: =W25 -> 65424 | Y42: =Y25 -> 0 | Z42: =Z25 -> 0 | AA42: =AA25 -> 38000 | AB42: =AB25 -> 80370
B43: Less: Sales | E43: =(E41-10000)/2 -> 20178.571 | F43: =SUM(F41:F42)*80% -> 24142.857 | G43: =MIN((G42+G41)*50%,G41+G42) -> 15617.857 | H43: =MIN((H42+H41)*30%,H41+H42) -> 15542.357 | J43: =J41/2 -> 18132.75 | K43: =K41*90% -> 16319.475 | L43: =MIN((L42+L41)*60%,L41+L42) -> 17287.965 | M43: =MIN((M42+M41)*33%,M41+M42) -> 18925.602 | O43: =O41/2 -> 19212.354 | P43: =P41*90% -> 17291.118 | Q43: =MIN((Q42+Q41)*60%,Q41+Q42) -> 20352.741 | R43: =MIN((R42+R41)*33%,R41+R42) -> 21848.803 | T43: =T41/2 -> 22179.846 | U43: =U41*90% -> 19961.861 | V43: =MIN((V42+V41)*60%,V41+V42) -> 22210.791 | W43: =MIN((W42+W41)*33%,W41+W42) -> 26476.294 | Y43: =Y41/2 -> 26877.45 | Z43: =Z41*90% -> 24189.705 | AA43: =MIN((AA42+AA41)*60%,AA41+AA42) -> 24412.647 | AB43: =MIN((AB42+AB41)*33%,AB41+AB42) -> 31892.882
B44: Closing Stock | D44: =C89 -> 50357.143 | E44: =E41+E42-E43 -> 30178.571 | F44: =F41+F42-F43 -> 6035.7143 | G44: =G41+G42-G43 -> 15617.857 | H44: =H41+H42-H43 -> 36265.5 | J44: =J41+J42-J43 -> 18132.75 | K44: =K41+K42-K43 -> 1813.275 | L44: =L41+L42-L43 -> 11525.31 | M44: =M41+M42-M43 -> 38424.708 | O44: =O41+O42-O43 -> 19212.354 | P44: =P41+P42-P43 -> 1921.2354 | Q44: =Q41+Q42-Q43 -> 13568.494 | R44: =R41+R42-R43 -> 44359.691 | T44: =T41+T42-T43 -> 22179.846 | U44: =U41+U42-U43 -> 2217.9846 | V44: =V41+V42-V43 -> 14807.194 | W44: =W41+W42-W43 -> 53754.9 | Y44: =Y41+Y42-Y43 -> 26877.45 | Z44: =Z41+Z42-Z43 -> 2687.745 | AA44: =AA41+AA42-AA43 -> 16275.098 | AB44: =AB41+AB42-AB43 -> 64752.216
A46: # | B46: Molasses
B47: Opening Stock | E47: =D50 -> 7800 | F47: =E50 -> 3900 | G47: =F50 -> 390 | H47: =G50 -> 2346 | J47: =H50 -> 6482.4 | K47: =J50 -> 3241.2 | L47: =K50 -> 324.12 | M47: =L50 -> 2494.824 | O47: =M50 -> 8017.9296 | P47: =O50 -> 4008.9648 | Q47: =P50 -> 400.89648 | R47: =Q50 -> 2960.1793 | T47: =R50 -> 9248.0717 | U47: =T50 -> 4624.0359 | V47: =U50 -> 462.40359 | W47: =V50 -> 3224.4807 | Y47: =W50 -> 11312.192 | Z47: =Y50 -> 5656.0961 | AA47: =Z50 -> 565.60961 | AB47: =AA50 -> 3533.1219
B48: Add: production | E48: =E26 -> 0 | F48: =F26 -> 0 | G48: =G26 -> 11340 | H48: =H26 -> 13860 | J48: =J26 -> 0 | K48: =K26 -> 0 | L48: =L26 -> 12150 | M48: =M26 -> 17550 | O48: =O26 -> 0 | P48: =P26 -> 0 | Q48: =Q26 -> 14400 | R48: =R26 -> 20160 | T48: =T26 -> 0 | U48: =U26 -> 0 | V48: =V26 -> 15660 | W48: =W26 -> 25056 | Y48: =Y26 -> 0 | Z48: =Z26 -> 0 | AA48: =AA26 -> 17100 | AB48: =AB26 -> 30780
B49: Less: Sales | E49: =E47/2 -> 3900 | F49: =F47*90% -> 3510 | G49: =MIN((G48+G47)*80%,G47+G48) -> 9384 | H49: =MIN((H48+H47)*60%,H47+H48) -> 9723.6 | I49: =IFERROR(I$48*(I$1-$C$50)/I$1+I$47,0) -> 0 | J49: =J47/2 -> 3241.2 | K49: =K47*90% -> 2917.08 | L49: =MIN((L48+L47)*80%,L47+L48) -> 9979.296 | M49: =MIN((M48+M47)*60%,M47+M48) -> 12026.894 | N49: =IFERROR(N$48*(N$1-$C$50)/N$1+N$47,0) -> 0 | O49: =O47/2 -> 4008.9648 | P49: =P47*90% -> 3608.0683 | Q49: =MIN((Q48+Q47)*80%,Q47+Q48) -> 11840.717 | R49: =MIN((R48+R47)*60%,R47+R48) -> 13872.108 | S49: =IFERROR(S$48*(S$1-$C$50)/S$1+S$47,0) -> 0 | T49: =T47/2 -> 4624.0359 | U49: =U47*90% -> 4161.6323 | V49: =MIN((V48+V47)*80%,V47+V48) -> 12897.923 | W49: =MIN((W48+W47)*60%,W47+W48) -> 16968.288 | X49: =IFERROR(X$48*(X$1-$C$50)/X$1+X$47,0) -> 0 | Y49: =Y47/2 -> 5656.0961 | Z49: =Z47*90% -> 5090.4865 | AA49: =MIN((AA48+AA47)*80%,AA47+AA48) -> 14132.488 | AB49: =MIN((AB48+AB47)*60%,AB47+AB48) -> 20587.873
B50: Closing Stock | C50: 0 | D50: =C93 -> 7800 | E50: =E47+E48-E49 -> 3900 | F50: =F47+F48-F49 -> 390 | G50: =G47+G48-G49 -> 2346 | H50: =H47+H48-H49 -> 6482.4 | J50: =J47+J48-J49 -> 3241.2 | K50: =K47+K48-K49 -> 324.12 | L50: =L47+L48-L49 -> 2494.824 | M50: =M47+M48-M49 -> 8017.9296 | O50: =O47+O48-O49 -> 4008.9648 | P50: =P47+P48-P49 -> 400.89648 | Q50: =Q47+Q48-Q49 -> 2960.1793 | R50: =R47+R48-R49 -> 9248.0717 | T50: =T47+T48-T49 -> 4624.0359 | U50: =U47+U48-U49 -> 462.40359 | V50: =V47+V48-V49 -> 3224.4807 | W50: =W47+W48-W49 -> 11312.192 | Y50: =Y47+Y48-Y49 -> 5656.0961 | Z50: =Z47+Z48-Z49 -> 565.60961 | AA50: =AA47+AA48-AA49 -> 3533.1219 | AB50: =AB47+AB48-AB49 -> 13725.249
A52: # | B52: Bagasse
B53: Opening Stock | E53: =Power!E70 -> 84859.794 | F53: =Power!F70 -> 84859.794 | G53: =Power!G70 -> 84859.794 | H53: =Power!H70 -> 89169.794 | J53: =Power!J70 -> 88839.794 | K53: =Power!K70 -> 58589.794 | L53: =Power!L70 -> 28339.794 | M53: =Power!M70 -> 37689.794 | O53: =Power!O70 -> 49039.794 | P53: =Power!P70 -> 18789.794 | Q53: =Power!Q70 -> 0 | R53: =Power!R70 -> 19350 | T53: =Power!T70 -> 40620 | U53: =Power!U70 -> 10370 | V53: =Power!V70 -> 0 | W53: =Power!W70 -> 27190 | Y53: =Power!Y70 -> 66572 | Z53: =Power!Z70 -> 36322 | AA53: =Power!AA70 -> 6072 | AB53: =Power!AB70 -> 42222
B54: Add: production | E54: =Power!E71 -> 0 | F54: =Power!F71 -> 0 | G54: =Power!G71 -> 70560 | H54: =Power!H71 -> 73920 | J54: =Power!J71 -> 0 | K54: =Power!K71 -> 0 | L54: =Power!L71 -> 75600 | M54: =Power!M71 -> 93600 | O54: =Power!O71 -> 0 | P54: =Power!P71 -> 0 | Q54: =Power!Q71 -> 89600 | R54: =Power!R71 -> 107520 | T54: =Power!T71 -> 0 | U54: =Power!U71 -> 0 | V54: =Power!V71 -> 97440 | W54: =Power!W71 -> 133632 | Y54: =Power!Y71 -> 0 | Z54: =Power!Z71 -> 0 | AA54: =Power!AA71 -> 106400 | AB54: =Power!AB71 -> 164160
B55: Less: Capital Consumption | E55: =SUM(Power!E72:E73) -> 0 | F55: =SUM(Power!F72:F73) -> 0 | G55: =SUM(Power!G72:G73) -> 66250 | H55: =SUM(Power!H72:H73) -> 74250 | J55: =SUM(Power!J72:J73) -> 30250 | K55: =SUM(Power!K72:K73) -> 30250 | L55: =SUM(Power!L72:L73) -> 66250 | M55: =SUM(Power!M72:M73) -> 82250 | O55: =SUM(Power!O72:O73) -> 30250 | P55: =SUM(Power!P72:P73) -> 18789.794 | Q55: =SUM(Power!Q72:Q73) -> 70250 | R55: =SUM(Power!R72:R73) -> 86250 | T55: =SUM(Power!T72:T73) -> 30250 | U55: =SUM(Power!U72:U73) -> 10370 | V55: =SUM(Power!V72:V73) -> 70250 | W55: =SUM(Power!W72:W73) -> 94250 | Y55: =SUM(Power!Y72:Y73) -> 30250 | Z55: =SUM(Power!Z72:Z73) -> 30250 | AA55: =SUM(Power!AA72:AA73) -> 70250 | AB55: =SUM(Power!AB72:AB73) -> 102250
B56: Less: Sales | E56: 0 | F56: 0 | G56: 0 | H56: 0 | I56: 0 | J56: 0 | K56: 0 | L56: 0 | M56: 0 | N56: 0 | O56: 0 | P56: 0 | Q56: 0 | R56: 0 | S56: 0 | T56: 0 | U56: 0 | V56: 0 | W56: 0 | X56: 0 | Y56: 0 | Z56: 0 | AA56: 0 | AB56: 0
B57: Closing Stock | C57: =C50 -> 0 | E57: =E53+E54-E56-E55 -> 84859.794 | F57: =F53+F54-F56-F55 -> 84859.794 | G57: =G53+G54-G56-G55 -> 89169.794 | H57: =H53+H54-H56-H55 -> 88839.794 | J57: =J53+J54-J56-J55 -> 58589.794 | K57: =K53+K54-K56-K55 -> 28339.794 | L57: =L53+L54-L56-L55 -> 37689.794 | M57: =M53+M54-M56-M55 -> 49039.794 | O57: =O53+O54-O56-O55 -> 18789.794 | P57: =P53+P54-P56-P55 -> 0 | Q57: =Q53+Q54-Q56-Q55 -> 19350 | R57: =R53+R54-R56-R55 -> 40620 | T57: =T53+T54-T56-T55 -> 10370 | U57: =U53+U54-U56-U55 -> 0 | V57: =V53+V54-V56-V55 -> 27190 | W57: =W53+W54-W56-W55 -> 66572 | Y57: =Y53+Y54-Y56-Y55 -> 36322 | Z57: =Z53+Z54-Z56-Z55 -> 6072 | AA57: =AA53+AA54-AA56-AA55 -> 42222 | AB57: =AB53+AB54-AB56-AB55 -> 104132
A59: # | B59: Press Mud
B60: Opening Stock | D60: 118704 | E60: 0 | F60: =E63 -> 0 | G60: =F63 -> 0 | H60: =G63 -> 0 | J60: =H63 -> 0 | K60: =J63 -> 0 | L60: =K63 -> 0 | M60: =L63 -> 0 | O60: =M63 -> 0 | P60: =O63 -> 0 | Q60: =P63 -> 0 | R60: =Q63 -> 0 | T60: =R63 -> 0 | U60: =T63 -> 0 | V60: =U63 -> 0 | W60: =V63 -> 0 | Y60: =W63 -> 0 | Z60: =Y63 -> 0 | AA60: =Z63 -> 0 | AB60: =AA63 -> 0
B61: Add: production | E61: =E28 -> 0 | F61: =F28 -> 0 | G61: =G28 -> 7560 | H61: =H28 -> 9240 | J61: =J28 -> 0 | K61: =K28 -> 0 | L61: =L28 -> 8100 | M61: =M28 -> 11700 | O61: =O28 -> 0 | P61: =P28 -> 0 | Q61: =Q28 -> 9600 | R61: =R28 -> 13440 | T61: =T28 -> 0 | U61: =U28 -> 0 | V61: =V28 -> 10440 | W61: =W28 -> 16704 | Y61: =Y28 -> 0 | Z61: =Z28 -> 0 | AA61: =AA28 -> 11400 | AB61: =AB28 -> 20520
B62: Less: Sales | D62: =SUM(E62:AB62) -> 118704 | E62: =IFERROR(SUM(E60:E61)*((E$1-C$63)/E$1),0) -> 0 | F62: =IFERROR(SUM(F60:F61)*((F$1-D$63)/F$1),0) -> 0 | G62: =IFERROR(SUM(G60:G61)*((G$1-E$63)/G$1),0) -> 7560 | H62: =IFERROR(SUM(H60:H61)*((H$1-F$63)/H$1),0) -> 9240 | I62: =IFERROR(SUM(I60:I61)*((I$1-G$63)/I$1),0) -> 0 | J62: =IFERROR(SUM(J60:J61)*((J$1-H$63)/J$1),0) -> 0 | K62: =IFERROR(SUM(K60:K61)*((K$1-I$63)/K$1),0) -> 0 | L62: =IFERROR(SUM(L60:L61)*((L$1-J$63)/L$1),0) -> 8100 | ... AB62: =IFERROR(SUM(AB60:AB61)*((AB$1-Z$63)/AB$1),0) -> 20520
B63: Closing Stock | C63: =C57 -> 0 | E63: =E60+E61-E62 -> 0 | F63: =F60+F61-F62 -> 0 | G63: =G60+G61-G62 -> 0 | H63: =H60+H61-H62 -> 0 | J63: =J60+J61-J62 -> 0 | K63: =K60+K61-K62 -> 0 | L63: =L60+L61-L62 -> 0 | M63: =M60+M61-M62 -> 0 | O63: =O60+O61-O62 -> 0 | P63: =P60+P61-P62 -> 0 | Q63: =Q60+Q61-Q62 -> 0 | R63: =R60+R61-R62 -> 0 | T63: =T60+T61-T62 -> 0 | U63: =U60+U61-U62 -> 0 | V63: =V60+V61-V62 -> 0 | W63: =W60+W61-W62 -> 0 | Y63: =Y60+Y61-Y62 -> 0 | Z63: =Z60+Z61-Z62 -> 0 | AA63: =AA60+AA61-AA62 -> 0 | AB63: =AB60+AB61-AB62 -> 0
A65: # | B65: Revenue Matrix
B66: Sugar Price | C66: 38 | D66: per kg | E66: 39000 | F66: =E66 -> 39000 | G66: =$C66*1000 -> 38000 | H66: =$C66*1000 -> 38000 | J66: =$C66*1000 -> 38000 | K66: =$C66*1000 -> 38000 | L66: =$C66*1000 -> 38000 | M66: =$C66*1000 -> 38000 | O66: =$C66*1000 -> 38000 | P66: =$C66*1000 -> 38000 | Q66: =$C66*1000 -> 38000 | R66: =$C66*1000 -> 38000 | T66: =$C66*1000 -> 38000 | U66: =$C66*1000 -> 38000 | V66: =$C66*1000 -> 38000 | W66: =$C66*1000 -> 38000 | Y66: =$C66*1000 -> 38000 | Z66: =$C66*1000 -> 38000 | AA66: =$C66*1000 -> 38000 | AB66: =$C66*1000 -> 38000
B67: Molasses Price | C67: 11 | D67: per kg | E67: =$C67*1000 -> 11000 | F67: =$C67*1000 -> 11000 | G67: =$C67*1000 -> 11000 | H67: =$C67*1000 -> 11000 | J67: =$C67*1000 -> 11000 | K67: =$C67*1000 -> 11000 | L67: =$C67*1000 -> 11000 | M67: =$C67*1000 -> 11000 | O67: =$C67*1000 -> 11000 | P67: =$C67*1000 -> 11000 | Q67: =$C67*1000 -> 11000 | R67: =$C67*1000 -> 11000 | T67: =$C67*1000 -> 11000 | U67: =$C67*1000 -> 11000 | V67: =$C67*1000 -> 11000 | W67: =$C67*1000 -> 11000 | Y67: =$C67*1000 -> 11000 | Z67: =$C67*1000 -> 11000 | AA67: =$C67*1000 -> 11000 | AB67: =$C67*1000 -> 11000
B68: Bagasse Price | C68: 2.5 | D68: per kg | E68: =$C68*1000 -> 2500 | F68: =$C68*1000 -> 2500 | G68: =$C68*1000 -> 2500 | H68: =$C68*1000 -> 2500 | J68: =$C68*1000 -> 2500 | K68: =$C68*1000 -> 2500 | L68: =$C68*1000 -> 2500 | M68: =$C68*1000 -> 2500 | O68: =$C68*1000 -> 2500 | P68: =$C68*1000 -> 2500 | Q68: =$C68*1000 -> 2500 | R68: =$C68*1000 -> 2500 | T68: =$C68*1000 -> 2500 | U68: =$C68*1000 -> 2500 | V68: =$C68*1000 -> 2500 | W68: =$C68*1000 -> 2500 | Y68: =$C68*1000 -> 2500 | Z68: =$C68*1000 -> 2500 | AA68: =$C68*1000 -> 2500 | AB68: =$C68*1000 -> 2500
B69: Press Mud Price | C69: 1.2 | D69: per kg | E69: =$C69*1000 -> 1200 | F69: =$C69*1000 -> 1200 | G69: =$C69*1000 -> 1200 | H69: =$C69*1000 -> 1200 | J69: =$C69*1000 -> 1200 | K69: =$C69*1000 -> 1200 | L69: =$C69*1000 -> 1200 | M69: =$C69*1000 -> 1200 | O69: =$C69*1000 -> 1200 | P69: =$C69*1000 -> 1200 | Q69: =$C69*1000 -> 1200 | R69: =$C69*1000 -> 1200 | T69: =$C69*1000 -> 1200 | U69: =$C69*1000 -> 1200 | V69: =$C69*1000 -> 1200 | W69: =$C69*1000 -> 1200 | Y69: =$C69*1000 -> 1200 | Z69: =$C69*1000 -> 1200 | AA69: =$C69*1000 -> 1200 | AB69: =$C69*1000 -> 1200
A71: # | B71: Sale of Sugar | E71: =E66*E43 -> 7.8696429e+08 | F71: =F66*F43 -> 9.4157143e+08 | G71: =G66*G43 -> 5.9347857e+08 | H71: =H66*H43 -> 5.9060957e+08 | J71: =J66*J43 -> 689044500 | K71: =K66*K43 -> 620140050 | L71: =L66*L43 -> 656942670 | M71: =M66*M43 -> 7.1917289e+08 | O71: =O66*O43 -> 7.3006945e+08 | P71: =P66*P43 -> 6.570625e+08 | Q71: =Q66*Q43 -> 7.7340417e+08 | R71: =R66*R43 -> 8.3025452e+08 | T71: =T66*T43 -> 8.4283413e+08 | U71: =U66*U43 -> 7.5855072e+08 | V71: =V66*V43 -> 8.4401005e+08 | W71: =W66*W43 -> 1.0060992e+09 | Y71: =Y66*Y43 -> 1.0213431e+09 | Z71: =Z66*Z43 -> 9.1920879e+08 | AA71: =AA66*AA43 -> 9.2768059e+08 | AB71: =AB66*AB43 -> 1.2119295e+09
B72: Molasses Sale value | E72: =E67*E49 -> 42900000 | F72: =F67*F49 -> 38610000 | G72: =G67*G49 -> 1.03224e+08 | H72: =H67*H49 -> 106959600 | J72: =J67*J49 -> 35653200 | K72: =K67*K49 -> 32087880 | L72: =L67*L49 -> 109772256 | M72: =M67*M49 -> 1.3229584e+08 | O72: =O67*O49 -> 44098613 | P72: =P67*P49 -> 39688752 | Q72: =Q67*Q49 -> 1.3024789e+08 | R72: =R67*R49 -> 1.5259318e+08 | T72: =T67*T49 -> 50864394 | U72: =U67*U49 -> 45777955 | V72: =V67*V49 -> 1.4187715e+08 | W72: =W67*W49 -> 1.8665117e+08 | Y72: =Y67*Y49 -> 62217058 | Z72: =Z67*Z49 -> 55995352 | AA72: =AA67*AA49 -> 1.5545736e+08 | AB72: =AB67*AB49 -> 2.264666e+08
B73: Bagasse Sale Vale | E73: =E68*E56 -> 0 | F73: =F68*F56 -> 0 | G73: =G68*G56 -> 0 | H73: =H68*H56 -> 0 | J73: =J68*J56 -> 0 | K73: =K68*K56 -> 0 | L73: =L68*L56 -> 0 | M73: =M68*M56 -> 0 | O73: =O68*O56 -> 0 | P73: =P68*P56 -> 0 | Q73: =Q68*Q56 -> 0 | R73: =R68*R56 -> 0 | T73: =T68*T56 -> 0 | U73: =U68*U56 -> 0 | V73: =V68*V56 -> 0 | W73: =W68*W56 -> 0 | Y73: =Y68*Y56 -> 0 | Z73: =Z68*Z56 -> 0 | AA73: =AA68*AA56 -> 0 | AB73: =AB68*AB56 -> 0
B74: Press Mud Sale Value | E74: =E69*E62 -> 0 | F74: =F69*F62 -> 0 | G74: =G69*G62 -> 9072000 | H74: =H69*H62 -> 11088000 | J74: =J69*J62 -> 0 | K74: =K69*K62 -> 0 | L74: =L69*L62 -> 9720000 | M74: =M69*M62 -> 14040000 | O74: =O69*O62 -> 0 | P74: =P69*P62 -> 0 | Q74: =Q69*Q62 -> 11520000 | R74: =R69*R62 -> 16128000 | T74: =T69*T62 -> 0 | U74: =U69*U62 -> 0 | V74: =V69*V62 -> 12528000 | W74: =W69*W62 -> 20044800 | Y74: =Y69*Y62 -> 0 | Z74: =Z69*Z62 -> 0 | AA74: =AA69*AA62 -> 13680000 | AB74: =AB69*AB62 -> 24624000
B76: Sugercane Price | G76: 3300 | H76: 3900 | L76: 3300 | M76: 3900 | Q76: 3300 | R76: 3900 | V76: 3300 | W76: 3900 | AA76: 3300 | AB76: 3900
A77: # | B77: Cost of Suger Cane Plant
B78: Raw material (sugarcane) | D78: per ton | E78: =$C78*Sugar!E$34 -> 0 | F78: =$C78*Sugar!F$34 -> 0 | G78: =G76*Sugar!G$34 -> 8.316e+08 | H78: =H76*Sugar!H$34 -> 1201200000 | J78: =$C78*Sugar!J$34 -> 0 | K78: =$C78*Sugar!K$34 -> 0 | L78: =L76*Sugar!L$34 -> 2178000000 | M78: =M76*Sugar!M$34 -> 0 | O78: =$C78*Sugar!O$34 -> 0 | P78: =$C78*Sugar!P$34 -> 0 | Q78: =Q76*Sugar!Q$34 -> 2534400000 | R78: =R76*Sugar!R$34 -> 0 | T78: =$C78*Sugar!T$34 -> 0 | U78: =$C78*Sugar!U$34 -> 0 | V78: =V76*Sugar!V$34 -> 2985840000 | W78: =W76*Sugar!W$34 -> 0 | Y78: =$C78*Sugar!Y$34 -> 0 | Z78: =$C78*Sugar!Z$34 -> 0 | AA78: =AA76*Sugar!AA$34 -> 3511200000 | AB78: =AB76*Sugar!AB$34 -> 0
B79: Labour Cost | C79: 20 | D79: per ton | E79: =$C79*Sugar!E$23 -> 0 | F79: =$C79*Sugar!F$23 -> 0 | G79: =$C79*Sugar!G$23 -> 5040000 | H79: =$C79*Sugar!H$23 -> 6160000 | J79: =$C79*Sugar!J$23 -> 0 | K79: =$C79*Sugar!K$23 -> 0 | L79: =$C79*Sugar!L$23 -> 5400000 | M79: =$C79*Sugar!M$23 -> 7800000 | O79: =$C79*Sugar!O$23 -> 0 | P79: =$C79*Sugar!P$23 -> 0 | Q79: =$C79*Sugar!Q$23 -> 6400000 | R79: =$C79*Sugar!R$23 -> 8960000 | T79: =$C79*Sugar!T$23 -> 0 | U79: =$C79*Sugar!U$23 -> 0 | V79: =$C79*Sugar!V$23 -> 6960000 | W79: =$C79*Sugar!W$23 -> 11136000 | Y79: =$C79*Sugar!Y$23 -> 0 | Z79: =$C79*Sugar!Z$23 -> 0 | AA79: =$C79*Sugar!AA$23 -> 7600000 | AB79: =$C79*Sugar!AB$23 -> 13680000
B80: Power Cost | C80: 0 | D80: per ton | E80: =Power!E35 -> 0 | F80: =Power!F35 -> 0 | G80: =Power!G35 -> -51480000 | H80: =Power!H35 -> -62920000 | J80: =Power!J35 -> 0 | K80: =Power!K35 -> 0 | L80: =Power!L35 -> -51480000 | M80: =Power!M35 -> -74360000 | O80: =Power!O35 -> 0 | P80: =Power!P35 -> 0 | Q80: =Power!Q35 -> -57200000 | R80: =Power!R35 -> -80080000 | T80: =Power!T35 -> 0 | U80: =Power!U35 -> 0 | V80: =Power!V35 -> -57200000 | W80: =Power!W35 -> -91520000 | Y80: =Power!Y35 -> 0 | Z80: =Power!Z35 -> 0 | AA80: =Power!AA35 -> -57200000 | AB80: =Power!AB35 -> -102960000
B81: Salary for dedicated Staff | E81: =Employee!E29 -> 4439070 | F81: =Employee!F29 -> 4550046.8 | G81: =Employee!G29 -> 4663797.9 | H81: =Employee!H29 -> 4780392.9 | I81: =Employee!I29 -> 18433308 | J81: =Employee!J29 -> 4899902.7 | K81: =Employee!K29 -> 5022400.3 | L81: =Employee!L29 -> 5147960.3 | ... AB81: =Employee!AB29 -> 7096520.1
B82: Other Cost | C82: 35 | E82: =$C82*Sugar!E$23 -> 0 | F82: =$C82*Sugar!F$23 -> 0 | G82: =$C82*Sugar!G$23 -> 8820000 | H82: =$C82*Sugar!H$23 -> 10780000 | J82: =$C82*Sugar!J$23 -> 0 | K82: =$C82*Sugar!K$23 -> 0 | L82: =$C82*Sugar!L$23 -> 9450000 | M82: =$C82*Sugar!M$23 -> 13650000 | O82: =$C82*Sugar!O$23 -> 0 | P82: =$C82*Sugar!P$23 -> 0 | Q82: =$C82*Sugar!Q$23 -> 11200000 | R82: =$C82*Sugar!R$23 -> 15680000 | T82: =$C82*Sugar!T$23 -> 0 | U82: =$C82*Sugar!U$23 -> 0 | V82: =$C82*Sugar!V$23 -> 12180000 | W82: =$C82*Sugar!W$23 -> 19488000 | Y82: =$C82*Sugar!Y$23 -> 0 | Z82: =$C82*Sugar!Z$23 -> 0 | AA82: =$C82*Sugar!AA$23 -> 13300000 | AB82: =$C82*Sugar!AB$23 -> 23940000
B84: Avg Cost/ kg of production | G84: =SUM(E78:H82)/SUM(E42:H42)/1000 -> 32.051365 | L84: =SUM(J78:M82)/SUM(J42:M42)/1000 -> 28.957184 | Q84: =SUM(O78:R82)/SUM(O42:R42)/1000 -> 29.085766 | V84: =SUM(U78:X82)/SUM(U42:X42)/1000 -> 29.239458 | AA84: =SUM(Y78:AB82)/SUM(Y42:AB42)/1000 -> 29.035434
B87: Suger Stock | C87: 1410000000
B88: Price | C88: 28
B89: Tons | C89: =C87/C88/1000 -> 50357.143
B91: Molasses Stock | C91: 93600000
B92: Price | C92: 12
C93: =C91/C92/1000 -> 7800
B95: Press Mud
B100: Bagasse | C100: =100000000+1831753 -> 101831753
C101: 1.2
C102: =C100/C101/1000 -> 84859.794
C103: =C100+C91+C87 -> 1605431753
C104: =C103-BS!C11 -> 0.4000001

Sheet Power
B1: No..of days of operation(days) | E1: 0 | F1: 0 | G1: =330/4 -> 82.5 | H1: =330/4 -> 82.5 | J1: =330/4 -> 82.5 | K1: =330/4 -> 82.5 | L1: =330/4 -> 82.5 | M1: =330/4 -> 82.5 | O1: =330/4 -> 82.5 | P1: =330/4 -> 82.5 | Q1: =330/4 -> 82.5 | R1: =330/4 -> 82.5 | T1: =330/4 -> 82.5 | U1: =330/4 -> 82.5 | V1: =330/4 -> 82.5 | W1: =330/4 -> 82.5 | Y1: =330/4 -> 82.5 | Z1: =330/4 -> 82.5 | AA1: =330/4 -> 82.5 | AB1: =330/4 -> 82.5
B2: Days of Suger Plant Operation | E2: =Sugar!E6 -> 0 | F2: =Sugar!F6 -> 0 | G2: =Sugar!G6 -> 45 | H2: =Sugar!H6 -> 55 | J2: =Sugar!J6 -> 0 | K2: =Sugar!K6 -> 0 | L2: =Sugar!L6 -> 45 | M2: =Sugar!M6 -> 65 | O2: =Sugar!O6 -> 0 | P2: =Sugar!P6 -> 0 | Q2: =Sugar!Q6 -> 50 | R2: =Sugar!R6 -> 70 | T2: =Sugar!T6 -> 0 | U2: =Sugar!U6 -> 0 | V2: =Sugar!V6 -> 50 | W2: =Sugar!W6 -> 80 | Y2: =Sugar!Y6 -> 0 | Z2: =Sugar!Z6 -> 0 | AA2: =Sugar!AA6 -> 50 | AB2: =Sugar!AB6 -> 90
B3: Production quaterly | E3: 45838 | F3: =EOMONTH(E3,3) -> 45930 | G3: =EOMONTH(F3,3) -> 46022 | H3: =EOMONTH(G3,3) -> 46112 | J3: =EOMONTH(H3,3) -> 46203 | K3: =EOMONTH(J3,3) -> 46295 | L3: =EOMONTH(K3,3) -> 46387 | M3: =EOMONTH(L3,3) -> 46477 | O3: =EOMONTH(M3,3) -> 46568 | P3: =EOMONTH(O3,3) -> 46660 | Q3: =EOMONTH(P3,3) -> 46752 | R3: =EOMONTH(Q3,3) -> 46843 | T3: =EOMONTH(R3,3) -> 46934 | U3: =EOMONTH(T3,3) -> 47026 | V3: =EOMONTH(U3,3) -> 47118 | W3: =EOMONTH(V3,3) -> 47208 | Y3: =EOMONTH(W3,3) -> 47299 | Z3: =EOMONTH(Y3,3) -> 47391 | AA3: =EOMONTH(Z3,3) -> 47483 | AB3: =EOMONTH(AA3,3) -> 47573
B5: Bagasse | C5: tons | D5: 1500
B6: Coal | C6: tons | D6: 5000
B7: Bagasse req per MW | C7: KG | D7: 1433
B8: Coal req per MW | C8: KG | D8: 430
B10: Steam | D10: 7.2 | E10: tons
B11: Bagasse | D11: =D10/2 -> 3.6 | E11: tons
B12: Rice Husk | D12: =D10/3.5 -> 2.0571429 | E12: tons
B13: Coal | D13: =D10/5 -> 1.44 | E13: tons
B15: Steam Requirement | D15: Ton/hr
B16: Suger | D16: 120
B17: Ethanol | D17: 55
B19: Suger Plant- Electricity Capacity | C19: =D16/D10 -> 16.666667 | D19: MW
B20: Ethanol-Electricity Capacity | C20: =D17/D10 -> 7.6388889 | D20: MW
B22: Steam for Suger Plant
B23: Steam Requirement | C23: =D16 -> 120 | D23: TPH
B24: Steam-Requirement | C24: =C23*24 -> 2880 | D24: TPD
B25: Bagasse Required | C25: =C24/2 -> 1440 | D25: TPD
B27: Electricity produced | C27: =C24/D10*1000 -> 400000 | D27: KWH/day
B29: Electricty production | E29: =$C27*E2 -> 0 | F29: =$C27*F2 -> 0 | G29: =$C27*G2 -> 18000000 | H29: =$C27*H2 -> 22000000 | J29: =$C27*J2 -> 0 | K29: =$C27*K2 -> 0 | L29: =$C27*L2 -> 18000000 | M29: =$C27*M2 -> 26000000 | O29: =$C27*O2 -> 0 | P29: =$C27*P2 -> 0 | Q29: =$C27*Q2 -> 20000000 | R29: =$C27*R2 -> 28000000 | T29: =$C27*T2 -> 0 | U29: =$C27*U2 -> 0 | V29: =$C27*V2 -> 20000000 | W29: =$C27*W2 -> 32000000 | Y29: =$C27*Y2 -> 0 | Z29: =$C27*Z2 -> 0 | AA29: =$C27*AA2 -> 20000000 | AB29: =$C27*AB2 -> 36000000
B30: Used for the Plant | C30: =8*24*1000 -> 192000 | D30: KWH/Day | E30: =E2*$C30 -> 0 | F30: =F2*$C30 -> 0 | G30: =G2*$C30 -> 8640000 | H30: =H2*$C30 -> 10560000 | J30: =J2*$C30 -> 0 | K30: =K2*$C30 -> 0 | L30: =L2*$C30 -> 8640000 | M30: =M2*$C30 -> 12480000 | O30: =O2*$C30 -> 0 | P30: =P2*$C30 -> 0 | Q30: =Q2*$C30 -> 9600000 | R30: =R2*$C30 -> 13440000 | T30: =T2*$C30 -> 0 | U30: =U2*$C30 -> 0 | V30: =V2*$C30 -> 9600000 | W30: =W2*$C30 -> 15360000 | Y30: =Y2*$C30 -> 0 | Z30: =Z2*$C30 -> 0 | AA30: =AA2*$C30 -> 9600000 | AB30: =AB2*$C30 -> 17280000
B31: Electricty sold to Grid | E31: =E29-E30 -> 0 | F31: =F29-F30 -> 0 | G31: =G29-G30 -> 9360000 | H31: =H29-H30 -> 11440000 | J31: =J29-J30 -> 0 | K31: =K29-K30 -> 0 | L31: =L29-L30 -> 9360000 | M31: =M29-M30 -> 13520000 | O31: =O29-O30 -> 0 | P31: =P29-P30 -> 0 | Q31: =Q29-Q30 -> 10400000 | R31: =R29-R30 -> 14560000 | T31: =T29-T30 -> 0 | U31: =U29-U30 -> 0 | V31: =V29-V30 -> 10400000 | W31: =W29-W30 -> 16640000 | Y31: =Y29-Y30 -> 0 | Z31: =Z29-Z30 -> 0 | AA31: =AA29-AA30 -> 10400000 | AB31: =AB29-AB30 -> 18720000
B33: Revenue From selling | C33: 5.5 | E33: =E31*$C33 -> 0 | F33: =F31*$C33 -> 0 | G33: =G31*$C33 -> 51480000 | H33: =H31*$C33 -> 62920000 | J33: =J31*$C33 -> 0 | K33: =K31*$C33 -> 0 | L33: =L31*$C33 -> 51480000 | M33: =M31*$C33 -> 74360000 | O33: =O31*$C33 -> 0 | P33: =P31*$C33 -> 0 | Q33: =Q31*$C33 -> 57200000 | R33: =R31*$C33 -> 80080000 | T33: =T31*$C33 -> 0 | U33: =U31*$C33 -> 0 | V33: =V31*$C33 -> 57200000 | W33: =W31*$C33 -> 91520000 | Y33: =Y31*$C33 -> 0 | Z33: =Z31*$C33 -> 0 | AA33: =AA31*$C33 -> 57200000 | AB33: =AB31*$C33 -> 102960000
B35: Cost of Electricity to Suger Plant | E35: =-E33 -> 0 | F35: =-F33 -> 0 | G35: =-G33 -> -51480000 | H35: =-H33 -> -62920000 | J35: =-J33 -> 0 | K35: =-K33 -> 0 | L35: =-L33 -> -51480000 | M35: =-M33 -> -74360000 | O35: =-O33 -> 0 | P35: =-P33 -> 0 | Q35: =-Q33 -> -57200000 | R35: =-R33 -> -80080000 | T35: =-T33 -> 0 | U35: =-U33 -> 0 | V35: =-V33 -> -57200000 | W35: =-W33 -> -91520000 | Y35: =-Y33 -> 0 | Z35: =-Z33 -> 0 | AA35: =-AA33 -> -57200000 | AB35: =-AB33 -> -102960000
B37: Steam for Ethanol Plant
B38: Steam Requirement | C38: =D17 -> 55 | D38: TPH
B39: Steam Requirement | C39: =C38*24 -> 1320 | D39: TPD
B40: Bagasse Required | C40: =C39/2 -> 660 | D40: TPD
B42: Electricity produced | C42: =C40/D11*1000 -> 183333.33 | D42: KWH/day
B44: Electricty production | E44: =$C42*E1 -> 0 | F44: =$C42*F1 -> 0 | G44: =$C42*G1 -> 15125000 | H44: =$C42*H1 -> 15125000 | J44: =$C42*J1 -> 15125000 | K44: =$C42*K1 -> 15125000 | L44: =$C42*L1 -> 15125000 | M44: =$C42*M1 -> 15125000 | O44: =$C42*O1 -> 15125000 | P44: =$C42*P1 -> 15125000 | Q44: =$C42*Q1 -> 15125000 | R44: =$C42*R1 -> 15125000 | T44: =$C42*T1 -> 15125000 | U44: =$C42*U1 -> 15125000 | V44: =$C42*V1 -> 15125000 | W44: =$C42*W1 -> 15125000 | Y44: =$C42*Y1 -> 15125000 | Z44: =$C42*Z1 -> 15125000 | AA44: =$C42*AA1 -> 15125000 | AB44: =$C42*AB1 -> 15125000
B45: Used for the Plant | C45: =5*24*1000 -> 120000 | D45: =D42 -> KWH/day | E45: =E1*$C45 -> 0 | F45: =F1*$C45 -> 0 | G45: =G1*$C45 -> 9900000 | H45: =H1*$C45 -> 9900000 | J45: =J1*$C45 -> 9900000 | K45: =K1*$C45 -> 9900000 | L45: =L1*$C45 -> 9900000 | M45: =M1*$C45 -> 9900000 | O45: =O1*$C45 -> 9900000 | P45: =P1*$C45 -> 9900000 | Q45: =Q1*$C45 -> 9900000 | R45: =R1*$C45 -> 9900000 | T45: =T1*$C45 -> 9900000 | U45: =U1*$C45 -> 9900000 | V45: =V1*$C45 -> 9900000 | W45: =W1*$C45 -> 9900000 | Y45: =Y1*$C45 -> 9900000 | Z45: =Z1*$C45 -> 9900000 | AA45: =AA1*$C45 -> 9900000 | AB45: =AB1*$C45 -> 9900000
B46: Electricty sold to Grid | E46: =E44-E45 -> 0 | F46: =F44-F45 -> 0 | G46: =G44-G45 -> 5225000 | H46: =H44-H45 -> 5225000 | J46: =J44-J45 -> 5225000 | K46: =K44-K45 -> 5225000 | L46: =L44-L45 -> 5225000 | M46: =M44-M45 -> 5225000 | O46: =O44-O45 -> 5225000 | P46: =P44-P45 -> 5225000 | Q46: =Q44-Q45 -> 5225000 | R46: =R44-R45 -> 5225000 | T46: =T44-T45 -> 5225000 | U46: =U44-U45 -> 5225000 | V46: =V44-V45 -> 5225000 | W46: =W44-W45 -> 5225000 | Y46: =Y44-Y45 -> 5225000 | Z46: =Z44-Z45 -> 5225000 | AA46: =AA44-AA45 -> 5225000 | AB46: =AB44-AB45 -> 5225000
B48: Revenue From selling | C48: 5.5 | D48: INR/KWH | E48: =E46*$C48 -> 0 | F48: =F46*$C48 -> 0 | G48: =G46*$C48 -> 28737500 | H48: =H46*$C48 -> 28737500 | J48: =J46*$C48 -> 28737500 | K48: =K46*$C48 -> 28737500 | L48: =L46*$C48 -> 28737500 | M48: =M46*$C48 -> 28737500 | O48: =O46*$C48 -> 28737500 | P48: =P46*$C48 -> 28737500 | Q48: =Q46*$C48 -> 28737500 | R48: =R46*$C48 -> 28737500 | T48: =T46*$C48 -> 28737500 | U48: =U46*$C48 -> 28737500 | V48: =V46*$C48 -> 28737500 | W48: =W46*$C48 -> 28737500 | Y48: =Y46*$C48 -> 28737500 | Z48: =Z46*$C48 -> 28737500 | AA48: =AA46*$C48 -> 28737500 | AB48: =AB46*$C48 -> 28737500
B52: Cost of Alternate Fuel
B53: Rice straw | C53: 4500 | D53: Price /ton | E53: =$C53*E77 -> 0 | F53: =$C53*F77 -> 0 | G53: =$C53*G77 -> 0 | H53: =$C53*H77 -> 0 | J53: =$C53*J77 -> 0 | K53: =$C53*K77 -> 0 | L53: =$C53*L77 -> 0 | M53: =$C53*M77 -> 0 | O53: =$C53*O77 -> 0 | P53: =$C53*P77 -> 29469101 | Q53: =$C53*Q77 -> 0 | R53: =$C53*R77 -> 0 | T53: =$C53*T77 -> 0 | U53: =$C53*U77 -> 51120000 | V53: =$C53*V77 -> 0 | W53: =$C53*W77 -> 0 | Y53: =$C53*Y77 -> 0 | Z53: =$C53*Z77 -> 0 | AA53: =$C53*AA77 -> 0 | AB53: =$C53*AB77 -> 0
B55: Cost of Electricity to Ethanol Plant | E55: =-E48+E53 -> 0 | F55: =-F48+F53 -> 0 | G55: =-G48+G53 -> -28737500 | H55: =-H48+H53 -> -28737500 | J55: =-J48+J53 -> -28737500 | K55: =-K48+K53 -> -28737500 | L55: =-L48+L53 -> -28737500 | M55: =-M48+M53 -> -28737500 | O55: =-O48+O53 -> -28737500 | P55: =-P48+P53 -> 731600.71 | Q55: =-Q48+Q53 -> -28737500 | R55: =-R48+R53 -> -28737500 | T55: =-T48+T53 -> -28737500 | U55: =-U48+U53 -> 22382500 | V55: =-V48+V53 -> -28737500 | W55: =-W48+W53 -> -28737500 | Y55: =-Y48+Y53 -> -28737500 | Z55: =-Z48+Z53 -> -28737500 | AA55: =-AA48+AA53 -> -28737500 | AB55: =-AB48+AB53 -> -28737500
B58: Steam Requirement Module
B59: Suger Plant | E59: =E44*$D$10 -> 0 | F59: =F44*$D$10 -> 0 | G59: =G29*$D$10/1000 -> 129600 | H59: =H29*$D$10/1000 -> 158400 | J59: =J29*$D$10/1000 -> 0 | K59: =K29*$D$10/1000 -> 0 | L59: =L29*$D$10/1000 -> 129600 | M59: =M29*$D$10/1000 -> 187200 | O59: =O29*$D$10/1000 -> 0 | P59: =P29*$D$10/1000 -> 0 | Q59: =Q29*$D$10/1000 -> 144000 | R59: =R29*$D$10/1000 -> 201600 | T59: =T29*$D$10/1000 -> 0 | U59: =U29*$D$10/1000 -> 0 | V59: =V29*$D$10/1000 -> 144000 | W59: =W29*$D$10/1000 -> 230400 | Y59: =Y29*$D$10/1000 -> 0 | Z59: =Z29*$D$10/1000 -> 0 | AA59: =AA29*$D$10/1000 -> 144000 | AB59: =AB29*$D$10/1000 -> 259200
B60: Ethanol Plant | G60: =G44*$D$10/1000 -> 108900 | H60: =H44*$D$10/1000 -> 108900 | J60: =J44*$D$10/1000 -> 108900 | K60: =K44*$D$10/1000 -> 108900 | L60: =L44*$D$10/1000 -> 108900 | M60: =M44*$D$10/1000 -> 108900 | O60: =O44*$D$10/1000 -> 108900 | P60: =P44*$D$10/1000 -> 108900 | Q60: =Q44*$D$10/1000 -> 108900 | R60: =R44*$D$10/1000 -> 108900 | T60: =T44*$D$10/1000 -> 108900 | U60: =U44*$D$10/1000 -> 108900 | V60: =V44*$D$10/1000 -> 108900 | W60: =W44*$D$10/1000 -> 108900 | Y60: =Y44*$D$10/1000 -> 108900 | Z60: =Z44*$D$10/1000 -> 108900 | AA60: =AA44*$D$10/1000 -> 108900 | AB60: =AB44*$D$10/1000 -> 108900
G61: =SUM(G59:G60) -> 238500 | H61: =SUM(H59:H60) -> 267300 | J61: =SUM(J59:J60) -> 108900 | K61: =SUM(K59:K60) -> 108900 | L61: =SUM(L59:L60) -> 238500 | M61: =SUM(M59:M60) -> 296100 | O61: =SUM(O59:O60) -> 108900 | P61: =SUM(P59:P60) -> 108900 | Q61: =SUM(Q59:Q60) -> 252900 | R61: =SUM(R59:R60) -> 310500 | T61: =SUM(T59:T60) -> 108900 | U61: =SUM(U59:U60) -> 108900 | V61: =SUM(V59:V60) -> 252900 | W61: =SUM(W59:W60) -> 339300 | Y61: =SUM(Y59:Y60) -> 108900 | Z61: =SUM(Z59:Z60) -> 108900 | AA61: =SUM(AA59:AA60) -> 252900 | AB61: =SUM(AB59:AB60) -> 368100
B63: Bagasse Required- Suger | G63: =G59/$D65 -> 36000 | H63: =H59/$D65 -> 44000 | J63: =J59/$D65 -> 0 | K63: =K59/$D65 -> 0 | L63: =L59/$D65 -> 36000 | M63: =M59/$D65 -> 52000 | O63: =O59/$D65 -> 0 | P63: =P59/$D65 -> 0 | Q63: =Q59/$D65 -> 40000 | R63: =R59/$D65 -> 56000 | T63: =T59/$D65 -> 0 | U63: =U59/$D65 -> 0 | V63: =V59/$D65 -> 40000 | W63: =W59/$D65 -> 64000 | Y63: =Y59/$D65 -> 0 | Z63: =Z59/$D65 -> 0 | AA63: =AA59/$D65 -> 40000 | AB63: =AB59/$D65 -> 72000
B64: Bagasse Required- Ethanol | G64: =G60/$D65 -> 30250 | H64: =H60/$D65 -> 30250 | J64: =J60/$D65 -> 30250 | K64: =K60/$D65 -> 30250 | L64: =L60/$D65 -> 30250 | M64: =M60/$D65 -> 30250 | O64: =O60/$D65 -> 30250 | P64: =P60/$D65 -> 30250 | Q64: =Q60/$D65 -> 30250 | R64: =R60/$D65 -> 30250 | T64: =T60/$D65 -> 30250 | U64: =U60/$D65 -> 30250 | V64: =V60/$D65 -> 30250 | W64: =W60/$D65 -> 30250 | Y64: =Y60/$D65 -> 30250 | Z64: =Z60/$D65 -> 30250 | AA64: =AA60/$D65 -> 30250 | AB64: =AB60/$D65 -> 30250
B65: Steam From Available bagasse | D65: =D11 -> 3.6 | G65: =SUM(G63:G64) -> 66250 | H65: =SUM(H63:H64) -> 74250 | J65: =SUM(J63:J64) -> 30250 | K65: =SUM(K63:K64) -> 30250 | L65: =SUM(L63:L64) -> 66250 | M65: =SUM(M63:M64) -> 82250 | O65: =SUM(O63:O64) -> 30250 | P65: =SUM(P63:P64) -> 30250 | Q65: =SUM(Q63:Q64) -> 70250 | R65: =SUM(R63:R64) -> 86250 | T65: =SUM(T63:T64) -> 30250 | U65: =SUM(U63:U64) -> 30250 | V65: =SUM(V63:V64) -> 70250 | W65: =SUM(W63:W64) -> 94250 | Y65: =SUM(Y63:Y64) -> 30250 | Z65: =SUM(Z63:Z64) -> 30250 | AA65: =SUM(AA63:AA64) -> 70250 | AB65: =SUM(AB63:AB64) -> 102250
B69: Bagasse Stock
B70: Opening Stock | E70: =D74 -> 84859.794 | F70: =E74 -> 84859.794 | G70: =F74 -> 84859.794 | H70: =G74 -> 89169.794 | J70: =H74 -> 88839.794 | K70: =J74 -> 58589.794 | L70: =K74 -> 28339.794 | M70: =L74 -> 37689.794 | O70: =M74 -> 49039.794 | P70: =O74 -> 18789.794 | Q70: =P74 -> 0 | R70: =Q74 -> 19350 | T70: =R74 -> 40620 | U70: =T74 -> 10370 | V70: =U74 -> 0 | W70: =V74 -> 27190 | Y70: =W74 -> 66572 | Z70: =Y74 -> 36322 | AA70: =Z74 -> 6072 | AB70: =AA74 -> 42222
B71: Add: produced | E71: =Sugar!E27 -> 0 | F71: =Sugar!F27 -> 0 | G71: =Sugar!G27 -> 70560 | H71: =Sugar!H27 -> 73920 | J71: =Sugar!J27 -> 0 | K71: =Sugar!K27 -> 0 | L71: =Sugar!L27 -> 75600 | M71: =Sugar!M27 -> 93600 | O71: =Sugar!O27 -> 0 | P71: =Sugar!P27 -> 0 | Q71: =Sugar!Q27 -> 89600 | R71: =Sugar!R27 -> 107520 | T71: =Sugar!T27 -> 0 | U71: =Sugar!U27 -> 0 | V71: =Sugar!V27 -> 97440 | W71: =Sugar!W27 -> 133632 | Y71: =Sugar!Y27 -> 0 | Z71: =Sugar!Z27 -> 0 | AA71: =Sugar!AA27 -> 106400 | AB71: =Sugar!AB27 -> 164160
B72: Utilised for Suger Plant | D72: =D11 -> 3.6 | G72: =G63 -> 36000 | H72: =H63 -> 44000 | J72: =J63 -> 0 | K72: =K63 -> 0 | L72: =L63 -> 36000 | M72: =M63 -> 52000 | O72: =O63 -> 0 | P72: =P63 -> 0 | Q72: =Q63 -> 40000 | R72: =R63 -> 56000 | T72: =T63 -> 0 | U72: =U63 -> 0 | V72: =V63 -> 40000 | W72: =W63 -> 64000 | Y72: =Y63 -> 0 | Z72: =Z63 -> 0 | AA72: =AA63 -> 40000 | AB72: =AB63 -> 72000
B73: Utilised for Ethanol Plant | D73: =D72 -> 3.6 | G73: =MIN(G64,G70+G71-G72) -> 30250 | H73: =MIN(H64,H70+H71-H72) -> 30250 | J73: =MIN(J64,J70+J71-J72) -> 30250 | K73: =MIN(K64,K70+K71-K72) -> 30250 | L73: =MIN(L64,L70+L71-L72) -> 30250 | M73: =MIN(M64,M70+M71-M72) -> 30250 | O73: =MIN(O64,O70+O71-O72) -> 30250 | P73: =MIN(P64,P70+P71-P72) -> 18789.794 | Q73: =MIN(Q64,Q70+Q71-Q72) -> 30250 | R73: =MIN(R64,R70+R71-R72) -> 30250 | T73: =MIN(T64,T70+T71-T72) -> 30250 | U73: =MIN(U64,U70+U71-U72) -> 10370 | V73: =MIN(V64,V70+V71-V72) -> 30250 | W73: =MIN(W64,W70+W71-W72) -> 30250 | Y73: =MIN(Y64,Y70+Y71-Y72) -> 30250 | Z73: =MIN(Z64,Z70+Z71-Z72) -> 30250 | AA73: =MIN(AA64,AA70+AA71-AA72) -> 30250 | AB73: =MIN(AB64,AB70+AB71-AB72) -> 30250
B74: Closing Stock | D74: =Sugar!C102 -> 84859.794 | E74: =E70+E71-E72-E73 -> 84859.794 | F74: =F70+F71-F72-F73 -> 84859.794 | G74: =G70+G71-G72-G73 -> 89169.794 | H74: =H70+H71-H72-H73 -> 88839.794 | J74: =J70+J71-J72-J73 -> 58589.794 | K74: =K70+K71-K72-K73 -> 28339.794 | L74: =L70+L71-L72-L73 -> 37689.794 | M74: =M70+M71-M72-M73 -> 49039.794 | O74: =O70+O71-O72-O73 -> 18789.794 | P74: =P70+P71-P72-P73 -> 0 | Q74: =Q70+Q71-Q72-Q73 -> 19350 | R74: =R70+R71-R72-R73 -> 40620 | T74: =T70+T71-T72-T73 -> 10370 | U74: =U70+U71-U72-U73 -> 0 | V74: =V70+V71-V72-V73 -> 27190 | W74: =W70+W71-W72-W73 -> 66572 | Y74: =Y70+Y71-Y72-Y73 -> 36322 | Z74: =Z70+Z71-Z72-Z73 -> 6072 | AA74: =AA70+AA71-AA72-AA73 -> 42222 | AB74: =AB70+AB71-AB72-AB73 -> 104132
B76: Additional bagasse required | G76: =IF(G73<G64,G64-G73,0) -> 0 | H76: =IF(H73<H64,H64-H73,0) -> 0 | J76: =IF(J73<J64,J64-J73,0) -> 0 | K76: =IF(K73<K64,K64-K73,0) -> 0 | L76: =IF(L73<L64,L64-L73,0) -> 0 | M76: =IF(M73<M64,M64-M73,0) -> 0 | O76: =IF(O73<O64,O64-O73,0) -> 0 | P76: =IF(P73<P64,P64-P73,0) -> 11460.206 | Q76: =IF(Q73<Q64,Q64-Q73,0) -> 0 | R76: =IF(R73<R64,R64-R73,0) -> 0 | T76: =IF(T73<T64,T64-T73,0) -> 0 | U76: =IF(U73<U64,U64-U73,0) -> 19880 | V76: =IF(V73<V64,V64-V73,0) -> 0 | W76: =IF(W73<W64,W64-W73,0) -> 0 | Y76: =IF(Y73<Y64,Y64-Y73,0) -> 0 | Z76: =IF(Z73<Z64,Z64-Z73,0) -> 0 | AA76: =IF(AA73<AA64,AA64-AA73,0) -> 0 | AB76: =IF(AB73<AB64,AB64-AB73,0) -> 0
B77: Additional Feed Bought | D77: =D12 -> 2.0571429 | E77: =E76*$D77/$D73 -> 0 | F77: =F76*$D77/$D73 -> 0 | G77: =G76*$D77/$D73 -> 0 | H77: =H76*$D77/$D73 -> 0 | J77: =J76*$D77/$D73 -> 0 | K77: =K76*$D77/$D73 -> 0 | L77: =L76*$D77/$D73 -> 0 | M77: =M76*$D77/$D73 -> 0 | O77: =O76*$D77/$D73 -> 0 | P77: =P76*$D77/$D73 -> 6548.689 | Q77: =Q76*$D77/$D73 -> 0 | R77: =R76*$D77/$D73 -> 0 | T77: =T76*$D77/$D73 -> 0 | U77: =U76*$D77/$D73 -> 11360 | V77: =V76*$D77/$D73 -> 0 | W77: =W76*$D77/$D73 -> 0 | Y77: =Y76*$D77/$D73 -> 0 | Z77: =Z76*$D77/$D73 -> 0 | AA77: =AA76*$D77/$D73 -> 0 | AB77: =AB76*$D77/$D73 -> 0

Sheet Employee
H1: =365*1.33/4 -> 121.3625
B2: No..of days of operation(days) | E2: =300/4 -> 75 | F2: =300/4 -> 75 | G2: =300/4 -> 75 | H2: =300/4 -> 75 | J2: =300/4 -> 75 | K2: =300/4 -> 75 | L2: =300/4 -> 75 | M2: =300/4 -> 75 | O2: =300/4 -> 75 | P2: =300/4 -> 75 | Q2: =300/4 -> 75 | R2: =300/4 -> 75 | T2: =300/4 -> 75 | U2: =300/4 -> 75 | V2: =300/4 -> 75 | W2: =300/4 -> 75 | Y2: =300/4 -> 75 | Z2: =300/4 -> 75 | AA2: =300/4 -> 75 | AB2: =300/4 -> 75
B3: Column counter | E3: 1 | F3: =E3+1 -> 2 | G3: =F3+1 -> 3 | H3: =G3+1 -> 4 | J3: =H3+1 -> 5 | K3: =J3+1 -> 6 | L3: =K3+1 -> 7 | M3: =L3+1 -> 8 | O3: =M3+1 -> 9 | P3: =O3+1 -> 10 | Q3: =P3+1 -> 11 | R3: =Q3+1 -> 12 | T3: =R3+1 -> 13 | U3: =T3+1 -> 14 | V3: =U3+1 -> 15 | W3: =V3+1 -> 16 | Y3: =W3+1 -> 17 | Z3: =Y3+1 -> 18 | AA3: =Z3+1 -> 19 | AB3: =AA3+1 -> 20
B4: Production quaterly | D4: pm | E4: 45838 | F4: =EOMONTH(E4,3) -> 45930 | G4: =EOMONTH(F4,3) -> 46022 | H4: =EOMONTH(G4,3) -> 46112 | I4: FY 25-26 | J4: =EOMONTH(H4,3) -> 46203 | K4: =EOMONTH(J4,3) -> 46295 | L4: =EOMONTH(K4,3) -> 46387 | M4: =EOMONTH(L4,3) -> 46477 | N4: FY 26-27 | O4: =EOMONTH(M4,3) -> 46568 | P4: =EOMONTH(O4,3) -> 46660 | Q4: =EOMONTH(P4,3) -> 46752 | R4: =EOMONTH(Q4,3) -> 46843 | S4: FY 27-28 | T4: =EOMONTH(R4,3) -> 46934 | U4: =EOMONTH(T4,3) -> 47026 | V4: =EOMONTH(U4,3) -> 47118 | W4: =EOMONTH(V4,3) -> 47208 | X4: FY 28-29 | Y4: =EOMONTH(W4,3) -> 47299 | Z4: =EOMONTH(Y4,3) -> 47391 | AA4: =EOMONTH(Z4,3) -> 47483 | AB4: =EOMONTH(AA4,3) -> 47573 | AC4: FY 29-30
A6: #
B7: MD and Top Management | D7: 275000 | E7: 4 | F7: =E7 -> 4 | G7: =F7 -> 4 | H7: =G7 -> 4 | I7: =H7 -> 4 | J7: =I7 -> 4 | K7: =J7 -> 4 | L7: =K7 -> 4 | M7: =L7 -> 4 | ... AC7: =AB7 -> 4
B8: Acounts and Finance | D8: 45000 | E8: 9 | F8: =E8 -> 9 | G8: =F8 -> 9 | H8: =G8 -> 9 | I8: =H8 -> 9 | J8: =I8 -> 9 | K8: =J8 -> 9 | L8: =K8 -> 9 | M8: =L8 -> 9 | ... AC8: =AB8 -> 9
B9: Corporate Office | D9: 25000 | E9: 9 | F9: =E9 -> 9 | G9: =F9 -> 9 | H9: =G9 -> 9 | I9: =H9 -> 9 | J9: =I9 -> 9 | K9: =J9 -> 9 | L9: =K9 -> 9 | M9: =L9 -> 9 | ... AC9: =AB9 -> 9
B10: Support Staff | D10: 20200 | E10: 23 | F10: =E10 -> 23 | G10: =F10 -> 23 | H10: =G10 -> 23 | I10: =H10 -> 23 | J10: =I10 -> 23 | K10: =J10 -> 23 | L10: =K10 -> 23 | M10: =L10 -> 23 | ... AC10: =AB10 -> 23
B12: Suger Plant
B13: Boiler | D13: 20000 | E13: 9 | F13: =E13 -> 9 | G13: =F13 -> 9 | H13: =G13 -> 9 | I13: =H13 -> 9 | J13: =I13 -> 9 | K13: =J13 -> 9 | L13: =K13 -> 9 | M13: =L13 -> 9 | ... AC13: =AB13 -> 9
B14: Boiling House | D14: 35000 | E14: 5 | F14: =E14 -> 5 | G14: =F14 -> 5 | H14: =G14 -> 5 | I14: =H14 -> 5 | J14: =I14 -> 5 | K14: =J14 -> 5 | L14: =K14 -> 5 | M14: =L14 -> 5 | ... AC14: =AB14 -> 5
B15: Sugercane | D15: 20000 | E15: 32 | F15: =E15 -> 32 | G15: =F15 -> 32 | H15: =G15 -> 32 | I15: =H15 -> 32 | J15: =I15 -> 32 | K15: =J15 -> 32 | L15: =K15 -> 32 | M15: =L15 -> 32 | ... AC15: =AB15 -> 32
B16: Civil | D16: 15000 | E16: 2 | F16: =E16 -> 2 | G16: =F16 -> 2 | H16: =G16 -> 2 | I16: =H16 -> 2 | J16: =I16 -> 2 | K16: =J16 -> 2 | L16: =K16 -> 2 | M16: =L16 -> 2 | ... AC16: =AB16 -> 2
B17: EDP | D17: 16400 | E17: 4 | F17: =E17 -> 4 | G17: =F17 -> 4 | H17: =G17 -> 4 | I17: =H17 -> 4 | J17: =I17 -> 4 | K17: =J17 -> 4 | L17: =K17 -> 4 | M17: =L17 -> 4 | ... AC17: =AB17 -> 4
B18: Electrical | D18: 22000 | E18: 4 | F18: =E18 -> 4 | G18: =F18 -> 4 | H18: =G18 -> 4 | I18: =H18 -> 4 | J18: =I18 -> 4 | K18: =J18 -> 4 | L18: =K18 -> 4 | M18: =L18 -> 4 | ... AC18: =AB18 -> 4
B19: Production | D19: 25000 | E19: 4 | F19: =E19 -> 4 | G19: =F19 -> 4 | H19: =G19 -> 4 | I19: =H19 -> 4 | J19: =I19 -> 4 | K19: =J19 -> 4 | L19: =K19 -> 4 | M19: =L19 -> 4 | ... AC19: =AB19 -> 4
B20: Mill House | D20: 15000 | E20: 11 | F20: =E20 -> 11 | G20: =F20 -> 11 | H20: =G20 -> 11 | I20: =H20 -> 11 | J20: =I20 -> 11 | K20: =J20 -> 11 | L20: =K20 -> 11 | M20: =L20 -> 11 | ... AC20: =AB20 -> 11
B22: Ethanol Plant
B23: Project People | D23: 25000 | E23: 43 | F23: =E23 -> 43 | G23: 55 | H23: 60 | I23: =H23 -> 60 | J23: =I23 -> 60 | K23: =J23 -> 60 | L23: =K23 -> 60 | M23: =L23 -> 60 | N23: =M23 -> 60 | O23: =N23 -> 60 | P23: =O23 -> 60 | ... AC23: =AB23 -> 60
B24: Instrumentation | D24: 26000 | E24: 2 | F24: =E24 -> 2 | G24: =F24 -> 2 | H24: =G24 -> 2 | I24: =H24 -> 2 | J24: =I24 -> 2 | K24: =J24 -> 2 | L24: =K24 -> 2 | M24: =L24 -> 2 | ... AC24: =AB24 -> 2
B26: Salary Increment | D26: 0.025 | E26: =1*(1+$D26) -> 1.025 | F26: =E26*(1+$D26) -> 1.050625 | G26: =F26*(1+$D26) -> 1.0768906 | H26: =G26*(1+$D26) -> 1.1038129 | J26: =H26*(1+$D26) -> 1.1314082 | K26: =J26*(1+$D26) -> 1.1596934 | L26: =K26*(1+$D26) -> 1.1886858 | M26: =L26*(1+$D26) -> 1.2184029 | O26: =M26*(1+$D26) -> 1.248863 | P26: =O26*(1+$D26) -> 1.2800845 | Q26: =P26*(1+$D26) -> 1.3120867 | R26: =Q26*(1+$D26) -> 1.3448888 | T26: =R26*(1+$D26) -> 1.378511 | U26: =T26*(1+$D26) -> 1.4129738 | V26: =U26*(1+$D26) -> 1.4482982 | W26: =V26*(1+$D26) -> 1.4845056 | Y26: =W26*(1+$D26) -> 1.5216183 | Z26: =Y26*(1+$D26) -> 1.5596587 | AA26: =Z26*(1+$D26) -> 1.5986502 | AB26: =AA26*(1+$D26) -> 1.6386164
B28: Corporate Staff | D28: =SUM(E28:AC28) -> 3.4477088e+08 | E28: =SUMPRODUCT(E7:E10,$D7:$D10)*3*E$26 -> 6748395 | F28: =SUMPRODUCT(F7:F10,$D7:$D10)*3*F$26 -> 6917104.9 | G28: =SUMPRODUCT(G7:G10,$D7:$D10)*3*G$26 -> 7090032.5 | H28: =SUMPRODUCT(H7:H10,$D7:$D10)*3*H$26 -> 7267283.3 | I28: =SUM(E28:H28) -> 28022816 | J28: =SUMPRODUCT(J7:J10,$D7:$D10)*3*J$26 -> 7448965.4 | K28: =SUMPRODUCT(K7:K10,$D7:$D10)*3*K$26 -> 7635189.5 | L28: =SUMPRODUCT(L7:L10,$D7:$D10)*3*L$26 -> 7826069.3 | M28: =SUMPRODUCT(M7:M10,$D7:$D10)*3*M$26 -> 8021721 | N28: =SUM(J28:M28) -> 30931945 | O28: =SUMPRODUCT(O7:O10,$D7:$D10)*3*O$26 -> 8222264 | P28: =SUMPRODUCT(P7:P10,$D7:$D10)*3*P$26 -> 8427820.6 | Q28: =SUMPRODUCT(Q7:Q10,$D7:$D10)*3*Q$26 -> 8638516.1 | R28: =SUMPRODUCT(R7:R10,$D7:$D10)*3*R$26 -> 8854479 | S28: =SUM(O28:R28) -> 34143080 | T28: =SUMPRODUCT(T7:T10,$D7:$D10)*3*T$26 -> 9075841 | U28: =SUMPRODUCT(U7:U10,$D7:$D10)*3*U$26 -> 9302737 | V28: =SUMPRODUCT(V7:V10,$D7:$D10)*3*V$26 -> 9535305.5 | W28: =SUMPRODUCT(W7:W10,$D7:$D10)*3*W$26 -> 9773688.1 | X28: =SUM(T28:W28) -> 37687572 | Y28: =SUMPRODUCT(Y7:Y10,$D7:$D10)*3*Y$26 -> 10018030 | Z28: =SUMPRODUCT(Z7:Z10,$D7:$D10)*3*Z$26 -> 10268481 | AA28: =SUMPRODUCT(AA7:AA10,$D7:$D10)*3*AA$26 -> 10525193 | AB28: =SUMPRODUCT(AB7:AB10,$D7:$D10)*3*AB$26 -> 10788323 | AC28: =SUM(Y28:AB28) -> 41600027
B29: Suger Plant | D29: =SUM(E29:AC29) -> 2.2678905e+08 | E29: =SUMPRODUCT(E13:E20,$D13:$D20)*3*E$26 -> 4439070 | F29: =SUMPRODUCT(F13:F20,$D13:$D20)*3*F$26 -> 4550046.8 | G29: =SUMPRODUCT(G13:G20,$D13:$D20)*3*G$26 -> 4663797.9 | H29: =SUMPRODUCT(H13:H20,$D13:$D20)*3*H$26 -> 4780392.9 | I29: =SUM(E29:H29) -> 18433308 | J29: =SUMPRODUCT(J13:J20,$D13:$D20)*3*J$26 -> 4899902.7 | K29: =SUMPRODUCT(K13:K20,$D13:$D20)*3*K$26 -> 5022400.3 | L29: =SUMPRODUCT(L13:L20,$D13:$D20)*3*L$26 -> 5147960.3 | M29: =SUMPRODUCT(M13:M20,$D13:$D20)*3*M$26 -> 5276659.3 | N29: =SUM(J29:M29) -> 20346922 | O29: =SUMPRODUCT(O13:O20,$D13:$D20)*3*O$26 -> 5408575.8 | P29: =SUMPRODUCT(P13:P20,$D13:$D20)*3*P$26 -> 5543790.1 | Q29: =SUMPRODUCT(Q13:Q20,$D13:$D20)*3*Q$26 -> 5682384.9 | R29: =SUMPRODUCT(R13:R20,$D13:$D20)*3*R$26 -> 5824444.5 | S29: =SUM(O29:R29) -> 22459195 | T29: =SUMPRODUCT(T13:T20,$D13:$D20)*3*T$26 -> 5970055.6 | U29: =SUMPRODUCT(U13:U20,$D13:$D20)*3*U$26 -> 6119307 | V29: =SUMPRODUCT(V13:V20,$D13:$D20)*3*V$26 -> 6272289.7 | W29: =SUMPRODUCT(W13:W20,$D13:$D20)*3*W$26 -> 6429096.9 | X29: =SUM(T29:W29) -> 24790749 | Y29: =SUMPRODUCT(Y13:Y20,$D13:$D20)*3*Y$26 -> 6589824.4 | Z29: =SUMPRODUCT(Z13:Z20,$D13:$D20)*3*Z$26 -> 6754570 | AA29: =SUMPRODUCT(AA13:AA20,$D13:$D20)*3*AA$26 -> 6923434.2 | AB29: =SUMPRODUCT(AB13:AB20,$D13:$D20)*3*AB$26 -> 7096520.1 | AC29: =SUM(Y29:AB29) -> 27364349
B30: Ethanol Plant | D30: =SUM(E30:AC30) -> 2.3771814e+08 | E30: =SUMPRODUCT(E23:E24,$D23:$D24)*3*E$26 -> 3465525 | F30: =SUMPRODUCT(F23:F24,$D23:$D24)*3*F$26 -> 3552163.1 | G30: =SUMPRODUCT(G23:G24,$D23:$D24)*3*G$26 -> 4610168.8 | H30: =SUMPRODUCT(H23:H24,$D23:$D24)*3*H$26 -> 5139352.8 | I30: =SUM(E30:H30) -> 16767210 | J30: =SUMPRODUCT(J23:J24,$D23:$D24)*3*J$26 -> 5267836.6 | K30: =SUMPRODUCT(K23:K24,$D23:$D24)*3*K$26 -> 5399532.6 | L30: =SUMPRODUCT(L23:L24,$D23:$D24)*3*L$26 -> 5534520.9 | M30: =SUMPRODUCT(M23:M24,$D23:$D24)*3*M$26 -> 5672883.9 | N30: =SUM(J30:M30) -> 21874774 | O30: =SUMPRODUCT(O23:O24,$D23:$D24)*3*O$26 -> 5814706 | P30: =SUMPRODUCT(P23:P24,$D23:$D24)*3*P$26 -> 5960073.6 | Q30: =SUMPRODUCT(Q23:Q24,$D23:$D24)*3*Q$26 -> 6109075.5 | R30: =SUMPRODUCT(R23:R24,$D23:$D24)*3*R$26 -> 6261802.4 | S30: =SUM(O30:R30) -> 24145657 | T30: =SUMPRODUCT(T23:T24,$D23:$D24)*3*T$26 -> 6418347.4 | U30: =SUMPRODUCT(U23:U24,$D23:$D24)*3*U$26 -> 6578806.1 | V30: =SUMPRODUCT(V23:V24,$D23:$D24)*3*V$26 -> 6743276.3 | W30: =SUMPRODUCT(W23:W24,$D23:$D24)*3*W$26 -> 6911858.2 | X30: =SUM(T30:W30) -> 26652288 | Y30: =SUMPRODUCT(Y23:Y24,$D23:$D24)*3*Y$26 -> 7084654.6 | Z30: =SUMPRODUCT(Z23:Z24,$D23:$D24)*3*Z$26 -> 7261771 | AA30: =SUMPRODUCT(AA23:AA24,$D23:$D24)*3*AA$26 -> 7443315.3 | AB30: =SUMPRODUCT(AB23:AB24,$D23:$D24)*3*AB$26 -> 7629398.1 | AC30: =SUM(Y30:AB30) -> 29419139
B31: Total | D31: =SUM(D28:D30) -> 8.0927806e+08 | E31: =SUM(E28:E30) -> 14652990 | F31: =SUM(F28:F30) -> 15019315 | G31: =SUM(G28:G30) -> 16363999 | H31: =SUM(H28:H30) -> 17187029 | I31: =SUM(I28:I30) -> 63223333 | J31: =SUM(J28:J30) -> 17616705 | K31: =SUM(K28:K30) -> 18057122 | ... AC31: =SUM(AC28:AC30) -> 98383515
G33: On | H33: 10000000 | I33: pm
G34: Off | H34: 4000000 | I34: pm
H35: including labour
G36: Ethonol add | H36: 3500000

Sheet Sheet1
F9: Ethanol PAT | G9: 38.00396 | H9: 128.12186 | I9: 179.44506 | J9: 193.86962 | K9: 201.83752
F10: Sugar PAT | G10: 38.445317 | H10: 42.004937 | I10: 67.553271 | J10: 82.466648 | K10: 99.610868
F11: Total PAT | G11: 76.449276 | H11: 170.1268 | I11: 246.99833 | J11: 276.33627 | K11: 301.44838

Sheet PAT(Proj)

Sheet Assumptions
D1: 10000000
A2: Production of ethanol | N2: Starch Content (%) | O2: 60.72
A3: Ethanol | N3: Fermentation Efficiency (%) | O3: 94
A4: Operational days | C4: 300 | D4: days | N4: Liqification effecency (%) | O4: 99
A5: Capacity | C5: 410338.89 | D5: liters | N5: Step | O5: Value
A6: Corn(Grain) | C6: 1 ton | N6: Weight ratio (Ethanol to Starch) | O6: 0.56823928
A7: Starch content | C7: 0.6 | D7: per ton | N7: Theoretical Yield of Ethanol (kg) | O7: =O6*O2*10 -> 345.03489 | Q7: =Ethanol!$E$10 -> 0 | R7: =Q7/O12 -> 0 | S7: =R7*1000 -> 0
A8: Ethanol produce | C8: =O9 -> 406.95751 | D8: liters/ton | N8: Actual Yield of Ethanol (kg) | O8: =O7*O3%*O4% -> 321.08947
A9: Sell of ethanol | C9: 71.86 | D9: per liter | N9: Actual Yield of Ethanol (liters) | O9: =O8/0.789 -> 406.95751
A10: Total sale value | C10: =C8*C9 -> 29243.966 | D10: per ton
N12: Ethanol | O12: =C5/1000 -> 410.33889 | P12: KLD
A13: DDGS | N13: Starch | O13: =O12/O6 -> 722.12341 | P13: KLD
A14: Produce | C14: 280 | D14: kg/ton | N14: Mix | O14: =O13/O2% -> 1189.2678 | P14: KLD
A15: Sell of DDGS | C15: 14.5 | D15: per kg
A16: Sale value | C16: =C14*C15 -> 4060 | D16: per ton
A19: Sugar
A20: =A$4 -> Operational days | C20: =C$4 -> 300 | D20: =D$4 -> days
A21: Total sugarcane crushed | C21: 55 | D21: lakhs quintal/year
A22: Total sugarcane crushed | C22: 800000 | D22: ton/year
A23: Sugar recovery | C23: 11 | D23: per quintal cane
A24: Sugar rate | C24: 35 | D24: per kg
A25: Sugar Revenue | C25: =C24*C23 -> 385 | D25: Crore/quintal
A26: Sugarcane procument cost | C26: 350 | D26: per quintal cane
A29: Molasses
A30: =A$21 -> Total sugarcane crushed | C30: =C22 -> 800000 | D30: =D22 -> ton/year
A31: Molasses Recovery | C31: 0.05 | D31: per qunital of cane
A32: Molasses rate | C32: 12 | D32: per kg
A35: Power Generation
A36: Baggas
A37: Power Generated | C37: 9.6643028 | D37: MW
A38: Captive consumption | C38: 5
A39: For Selling | C39: 4.6643028 | D39: MW
A40: For Selling | D40: Units
A41: Cost for 1 MW | C41: 4000 | D41: Rs..
A42: Predefined price | C42: 4.5 | D42: per unit

Sheet CMA
L1: 10000000
A2: Mahakaushal Sugar & Power Industries Limited
A3: Regd. Office: Bhopal, Madhya Pradesh
A5: ASSESSMENT OF WORKING CAPITAL REQUIREMENT
K6: Rs. In Crore
A7: PARTICULARS | D7: 2021 - 22 | E7: 2022 - 23 | F7: 2023 - 24 | G7: 2024 - 25 | H7: 2025 - 26 | I7: 2026- 27 | J7: 2027 - 28 | K7: 2028 - 29 | L7: 2029 - 30
D8: Audited | G8: Estimated
D9: 1 | E9: =D9+1 -> 2 | F9: =E9+1 -> 3 | G9: =F9+1 -> 4 | H9: =G9+1 -> 5 | I9: =H9+1 -> 6 | J9: =I9+1 -> 7 | K9: =J9+1 -> 8 | L9: =K9+1 -> 9
A11: FORM-II – OPERATING STATEMENT
A13: 1 | B13: GROSS SALES:
B14: a. Sale of products
B15: i) | C15: Sale of Sugar | D15: =1299970479/L1 -> 129.99705 | E15: =2414875798.8/L1 -> 241.48758 | F15: =2104965615.95/$L$1 -> 210.49656 | G15: =3150000000/L1 -> 315 | H15: =ROUND(G15*1.1,2) -> 346.5 | I15: =ROUND(H15*1.1,2) -> 381.15 | J15: =ROUND(I15*1.1,2) -> 419.27 | K15: =ROUND(J15*1.1,2) -> 461.2 | L15: =ROUND(K15*1.1,2) -> 507.32
B16: ii) | C16: Sale of Molasess | D16: =229070798/L1 -> 22.90708 | E16: =218758045/L1 -> 21.875805 | F16: =253363395.5/L1 -> 25.33634 | G16: =ROUND(G15*0.111111111111111,0) -> 35 | H16: =ROUND(G16*1.1,2) -> 38.5 | I16: =ROUND(H16*1.1,2) -> 42.35 | J16: =ROUND(I16*1.1,2) -> 46.59 | K16: =ROUND(J16*1.1,2) -> 51.25 | L16: =ROUND(K16*1.1,2) -> 56.38
B17: iii) | C17: Sale of Biomass Press Mud | D17: =0/L1 -> 0 | E17: =409773/L1 -> 0.0409773 | F17: =838038.6/L1 -> 0.08380386 | G17: =1000000/L1 -> 0.1 | H17: =ROUND(G17*1.1,2) -> 0.11 | I17: =ROUND(H17*1.1,2) -> 0.12 | J17: =ROUND(I17*1.1,2) -> 0.13 | K17: =ROUND(J17*1.1,2) -> 0.14 | L17: =ROUND(K17*1.1,2) -> 0.15
B18: iv) | C18: Sale of Press Mud | D18: =439726.7/L1 -> 0.04397267 | E18: =1272097.89/L1 -> 0.12720979 | F18: =0/$L$1 -> 0 | G18: 0 | H18: =ROUND(G18*1.1,2) -> 0 | I18: =ROUND(H18*1.1,2) -> 0 | J18: =ROUND(I18*1.1,2) -> 0 | K18: =ROUND(J18*1.1,2) -> 0 | L18: =ROUND(K18*1.1,2) -> 0
B19: v) | C19: Sale of Ethanol | D19: =0/$L$1 -> 0 | E19: =0/$L$1 -> 0 | F19: =0/$L$1 -> 0 | G19: =0/$L$1 -> 0 | H19: =6000000000/L1 -> 600 | I19: =H19*1.05 -> 630 | J19: =I19*1.05 -> 661.5 | K19: =J19*1.05 -> 694.575 | L19: =K19*1.05 -> 729.30375
C20: Total a | D20: =SUM(D15:D19) -> 152.9481 | E20: =SUM(E15:E19) -> 263.53157 | F20: =SUM(F15:F19) -> 235.91671 | G20: =SUM(G15:G19) -> 350.1 | H20: =SUM(H15:H19) -> 985.11 | I20: =SUM(I15:I19) -> 1053.62 | J20: =SUM(J15:J19) -> 1127.49 | K20: =SUM(K15:K19) -> 1207.165 | L20: =SUM(L15:L19) -> 1293.1537
B21: b. Sale of Services
B22: i) | C22: Sale of MAEQ Quota | D22: =0/$L$1 -> 0 | E22: =19750512.93/$L$1 -> 1.9750513 | F22: =2872774.14/L1 -> 0.28727741 | G22: =0/$L$1 -> 0 | H22: =0/$L$1 -> 0 | I22: =0/$L$1 -> 0 | J22: =0/$L$1 -> 0 | K22: =0/$L$1 -> 0 | L22: =0/$L$1 -> 0
B23: ii) | C23: Commission Earned on Export of Sugar | D23: =0/$L$1 -> 0 | E23: =625829.52/$L$1 -> 0.062582952 | F23: =0/$L$1 -> 0 | G23: =0/$L$1 -> 0 | H23: =0/$L$1 -> 0 | I23: =0/$L$1 -> 0 | J23: =0/$L$1 -> 0 | K23: =0/$L$1 -> 0 | L23: =0/$L$1 -> 0
B24: iii) | C24: Deemed Export of Molassas | D24: =5418610.91/$L$1 -> 0.54186109 | E24: =0/$L$1 -> 0 | F24: =0/$L$1 -> 0 | G24: =0/$L$1 -> 0 | H24: =0/$L$1 -> 0 | I24: =0/$L$1 -> 0 | J24: =0/$L$1 -> 0 | K24: =0/$L$1 -> 0 | L24: =0/$L$1 -> 0
C25: Total b | D25: =SUM(D21:D24) -> 0.54186109 | E25: =SUM(E21:E24) -> 2.0376342 | F25: =SUM(F21:F24) -> 0.28727741 | G25: =SUM(G21:G24) -> 0 | H25: =SUM(H21:H24) -> 0 | I25: =SUM(I21:I24) -> 0 | J25: =SUM(J21:J24) -> 0 | K25: =SUM(K21:K24) -> 0 | L25: =SUM(L21:L24) -> 0
B26: c. Sale of Power | D26: =46115473.8/$L$1 -> 4.6115474 | E26: =65901724.04/L1 -> 6.5901724 | F26: =110609926.09/$L$1 -> 11.060993 | G26: =ROUND(F26*SUM(G15:G18)/SUM(F15:F18),2) -> 16.41 | H26: =ROUND(G26*SUM(H15:H18)/SUM(G15:G18),2) -> 18.05 | I26: =ROUND(H26*SUM(I15:I18)/SUM(H15:H18),2) -> 19.85 | J26: =ROUND(I26*SUM(J15:J18)/SUM(I15:I18),2) -> 21.84 | K26: =ROUND(J26*SUM(K15:K18)/SUM(J15:J18),2) -> 24.02 | L26: =ROUND(K26*SUM(L15:L18)/SUM(K15:K18),2) -> 26.42
B27: d. Gross Sales (a + b + c) | D27: =D25+D20+D26 -> 158.10151 | E27: =E25+E20+E26 -> 272.15938 | F27: =F25+F20+F26 -> 247.26498 | G27: =G25+G20+G26 -> 366.51 | H27: =H25+H20+H26 -> 1003.16 | I27: =I25+I20+I26 -> 1073.47 | J27: =J25+J20+J26 -> 1149.33 | K27: =K25+K20+K26 -> 1231.185 | L27: =L25+L20+L26 -> 1319.5738
B28: e. Less : GST | D28: =728430.11/L1 -> 0.072843011 | E28: =166068639.83/L1 -> 16.606864 | F28: =113523497.92/$L$1 -> 11.35235 | G28: =F28*G27/F27 -> 16.827089 | H28: =G28*H27/G27 -> 46.056758 | I28: =H28*I27/H27 -> 49.284808 | J28: =I28*J27/I27 -> 52.767668 | K28: =J28*K27/J27 -> 56.525769 | L28: =K28*L27/K27 -> 60.583844
C29: Total | D29: =D27-D28 -> 158.02867 | E29: =E27-E28 -> 255.55251 | F29: =F27-F28 -> 235.91263 | G29: =G27-G28 -> 349.68291 | H29: =H27-H28 -> 957.10324 | I29: =I27-I28 -> 1024.1852 | J29: =J27-J28 -> 1096.5623 | K29: =K27-K28 -> 1174.6592 | L29: =L27-L28 -> 1258.9899
A31: 2 | B31: Other Operating Revenue
B32: a | C32: Sale of Iron Scrap | D32: =0/L1 -> 0 | E32: =215592.61/L1 -> 0.021559261 | F32: =631547.8/L1 -> 0.06315478 | G32: =500000/$L$1 -> 0.05 | H32: =500000/$L$1 -> 0.05 | I32: =500000/$L$1 -> 0.05 | J32: =500000/$L$1 -> 0.05 | K32: =500000/$L$1 -> 0.05 | L32: =500000/$L$1 -> 0.05
B33: b | C33: Scrap Sales | D33: =4602455.6/$L$1 -> 0.46024556 | F33: =4245720.24/L1 -> 0.42457202 | G33: =1000000/$L$1 -> 0.1 | H33: =1000000/$L$1 -> 0.1 | I33: =1000000/$L$1 -> 0.1 | J33: =1000000/$L$1 -> 0.1 | K33: =1000000/$L$1 -> 0.1 | L33: =1000000/$L$1 -> 0.1
B34: c | C34: Buffer Stock Subsidy | D34: =3459393/$L$1 -> 0.3459393 | E34: =0/$L$1 -> 0 | F34: =0/$L$1 -> 0 | G34: =0/$L$1 -> 0 | H34: =0/$L$1 -> 0 | I34: =0/$L$1 -> 0 | J34: =0/$L$1 -> 0 | K34: =0/$L$1 -> 0 | L34: =0/$L$1 -> 0
B35: d | C35: Subsidy Received | D35: =81600000/$L$1 -> 8.16 | E35: =40100000/$L$1 -> 4.01 | F35: =700000/$L$1 -> 0.07 | G35: =0/$L$1 -> 0 | H35: =0/$L$1 -> 0 | I35: =0/$L$1 -> 0 | J35: =0/$L$1 -> 0 | K35: =0/$L$1 -> 0 | L35: =0/$L$1 -> 0
B36: e | C36: Discount Received | D36: =233872.47/$L$1 -> 0.023387247 | E36: =807/$L$1 -> 8.07e-05 | F36: =38905.6/$L$1 -> 0.00389056 | G36: =0/$L$1 -> 0 | H36: =0/$L$1 -> 0 | I36: =0/$L$1 -> 0 | J36: =0/$L$1 -> 0 | K36: =0/$L$1 -> 0 | L36: =0/$L$1 -> 0
B37: f | C37: Creditors W/o | D37: =2981039.81/$L$1 -> 0.29810398 | E37: =0/$L$1 -> 0 | F37: =(1326488+7896399+5.35)/$L$1 -> 0.92228923 | G37: =0/$L$1 -> 0 | H37: =0/$L$1 -> 0 | I37: =0/$L$1 -> 0 | J37: =0/$L$1 -> 0 | K37: =0/$L$1 -> 0 | L37: =0/$L$1 -> 0
D38: =SUM(D32:D37) -> 9.2876761 | E38: =SUM(E32:E37) -> 4.03164 | F38: =SUM(F32:F37) -> 1.4839066 | G38: =SUM(G32:G37) -> 0.15 | H38: =SUM(H32:H37) -> 0.15 | I38: =SUM(I32:I37) -> 0.15 | J38: =SUM(J32:J37) -> 0.15 | K38: =SUM(K32:K37) -> 0.15 | L38: =SUM(L32:L37) -> 0.15
A39: 3 | C39: Net Sales (1-2) | D39: =D38+D29 -> 167.31634 | E39: =E38+E29 -> 259.58415 | F39: =F38+F29 -> 237.39653 | G39: =G38+G29 -> 349.83291 | H39: =H38+H29 -> 957.25324 | I39: =I38+I29 -> 1024.3352 | J39: =J38+J29 -> 1096.7123 | K39: =K38+K29 -> 1174.8092 | L39: =L38+L29 -> 1259.1399
A40: 4 | C40: % age rise (+) or fall (-) in net sales
C41: as compared to previous year | E41: =(E39-D39)/D39 -> 0.55145726 | F41: =(F39-E39)/E39 -> -0.085473716 | G41: =(G39-F39)/F39 -> 0.47362267 | H41: =(H39-G39)/G39 -> 1.7363156 | I41: =(I39-H39)/H39 -> 0.070077538 | J41: =(J39-I39)/I39 -> 0.070657672 | K41: =(K39-J39)/J39 -> 0.071210013 | L41: =(L39-K39)/K39 -> 0.071782441
A42: 5 | B42: Cost of Sales
B43: i) | C43: Cost of Raw Materials Consumed | D43: =1491591886.5/$L$1 -> 149.15919 | E43: =2026988750.82/$L$1 -> 202.69888 | F43: =2199369361.47/$L$1 -> 219.93694 | G43: =G20*0.805 -> 281.8305 | H43: =ROUND(0.805*SUM(H15:H18),2)+(H19*0.77) -> 772.01 | I43: =ROUND(0.73*SUM(I15:I18),2)+(I19*0.71) -> 756.54 | J43: =ROUND(0.73*SUM(J15:J18),2)+(J19*0.722) -> 817.773 | K43: =ROUND(0.73*SUM(K15:K18),2)+(K19*0.732) -> 882.6189 | L43: =ROUND(0.73*SUM(L15:L18),2)+(L19*0.742) -> 952.75338
B44: ii) | C44: Purchase of Stock in Trade | D44: =0/$L$1 -> 0 | E44: =0/$L$1 -> 0 | F44: =0/$L$1 -> 0 | G44: =0/$L$1 -> 0 | H44: =0/$L$1 -> 0 | I44: =0/$L$1 -> 0 | J44: =0/$L$1 -> 0 | K44: =0/$L$1 -> 0 | L44: =0/$L$1 -> 0
B45: iii) | C45: Changes in Inventories | D45: =-244497557.37/$L$1 -> -24.449756 | E45: =8684807.45/$L$1 -> 0.86848074 | F45: =-476197595.31/$L$1 -> -47.61976 | G45: =(F112-G112) -> -25.109292 | H45: =(G112-H112) -> -96.685 | I45: =(H112-I112) -> -21.75 | J45: =(I112-J112) -> -23.815 | K45: =(J112-K112) -> -26.05625 | L45: =(K112-L112) -> -28.524062
B46: iv) | C46: Other Direct Mfg. Expenses | D46: =(71702559.62+4394000)/$L$1 -> 7.609656 | E46: =(107552637.45+5642989)/L1 -> 11.319563 | F46: =(110643425.09+3036830)/$L$1 -> 11.368026 | G46: =ROUND(F46*G20/F20,2) -> 16.87 | H46: =ROUND(G46*H20/G20,2) -> 47.47 | I46: =ROUND(H46*I20/H20,2) -> 50.77 | J46: =ROUND(I46*J20/I20,2) -> 54.33 | K46: =ROUND(J46*K20/J20,2) -> 58.17 | L46: =ROUND(K46*L20/K20,2) -> 62.31
B47: v) | C47: Depreciation | D47: =96279680.53/L1 -> 9.6279681 | E47: =168397540/L1 -> 16.839754 | F47: =141241671/$L$1 -> 14.124167 | G47: =120000000/L1 -> 12 | H47: =(100000000)/$L$1+(380000000/$L$1) -> 48 | I47: =ROUND(H47*0.875,2) -> 42 | J47: =ROUND(I47*0.875,2) -> 36.75 | K47: =ROUND(J47*0.875,2) -> 32.16 | L47: =ROUND(K47*0.875,2) -> 28.14
B48: vi) | C48: Sub - Total (I to VI) | D48: =SUM(D43:D47) -> 141.94706 | E48: =SUM(E43:E47) -> 231.72667 | F48: =SUM(F43:F47) -> 197.80937 | G48: =SUM(G43:G47) -> 285.59121 | H48: =SUM(H43:H47) -> 770.795 | I48: =SUM(I43:I47) -> 827.56 | J48: =SUM(J43:J47) -> 885.038 | K48: =SUM(K43:K47) -> 946.89265 | L48: =SUM(L43:L47) -> 1014.6793
A50: 6 | B50: a | C50: Employee Benefit Expenses | D50: =47148061/L1 -> 4.7148061 | E50: =33111301/L1 -> 3.3111301 | F50: =64781846/$L$1 -> 6.4781846 | G50: =70000000/L1 -> 7 | H50: =100000000/L1 -> 10 | I50: =ROUND(H50*1.1,2) -> 11 | J50: =ROUND(I50*1.1,2) -> 12.1 | K50: =ROUND(J50*1.1,2) -> 13.31 | L50: =ROUND(K50*1.1,2) -> 14.64
B51: b | C51: Other Selling, General & Administrative Exp. | D51: =(21263444.1)/L1 -> 2.1263444 | E51: =27385034.14/L1 -> 2.7385034 | F51: =30755255.28/$L$1 -> 3.0755255 | G51: =ROUND(F51*1.2,20) -> 3.6906306 | H51: =ROUND(G51*1.8,20) -> 6.6431351 | I51: =ROUND(H51*1.2,20) -> 7.9717622 | J51: =ROUND(I51*1.2,20) -> 9.5661146 | K51: =ROUND(J51*1.2,20) -> 11.479338 | L51: =ROUND(K51*1.2,20) -> 13.775205
D52: =SUM(D50:D51) -> 6.8411505 | E52: =SUM(E50:E51) -> 6.0496335 | F52: =SUM(F50:F51) -> 9.5537101 | G52: =SUM(G50:G51) -> 10.690631 | H52: =SUM(H50:H51) -> 16.643135 | I52: =SUM(I50:I51) -> 18.971762 | J52: =SUM(J50:J51) -> 21.666115 | K52: =SUM(K50:K51) -> 24.789338 | L52: =SUM(L50:L51) -> 28.415205
A53: 7 | C53: Sub - Total (5+6) | D53: =D48+D52 -> 148.78821 | E53: =E48+E52 -> 237.77631 | F53: =F48+F52 -> 207.36308 | G53: =G48+G52 -> 296.28184 | H53: =H48+H52 -> 787.43814 | I53: =I48+I52 -> 846.53176 | J53: =J48+J52 -> 906.70411 | K53: =K48+K52 -> 971.68199 | L53: =L48+L52 -> 1043.0945
A54: 8 | C54: Operating profit before interest (3-7) | D54: =D39-D53 -> 18.528134 | E54: =E39-E53 -> 21.807848 | F54: =F39-F53 -> 30.033452 | G54: =G39-G53 -> 53.551073 | H54: =H39-H53 -> 169.81511 | I54: =I39-I53 -> 177.80343 | J54: =J39-J53 -> 190.00822 | K54: =K39-K53 -> 203.12724 | L54: =L39-L53 -> 216.04538
A55: 9 | C55: Interest (on Working Capital & Term Loan) | D55: =94634149.1/L1 -> 9.4634149 | E55: =105257852.93/L1 -> 10.525785 | F55: =102527966.02/$L$1 -> 10.252797 | G55: =90000000/L1 -> 9 | H55: =300000000/L1 -> 30 | I55: =ROUND(H55*0.9,20) -> 27 | J55: =ROUND(I55*0.9,20) -> 24.3 | K55: =ROUND(J55*0.9,20) -> 21.87 | L55: =ROUND(K55*0.9,20) -> 19.683
A56: 10 | C56: Operating profit after interest (8 - 9) | D56: =SUM(D54-D55) -> 9.0647196 | E56: =SUM(E54-E55) -> 11.282063 | F56: =SUM(F54-F55) -> 19.780656 | G56: =SUM(G54-G55) -> 44.551073 | H56: =SUM(H54-H55) -> 139.81511 | I56: =SUM(I54-I55) -> 150.80343 | J56: =SUM(J54-J55) -> 165.70822 | K56: =SUM(K54-K55) -> 181.25724 | L56: =SUM(L54-L55) -> 196.36238
A57: 11 | B57: I) | C57: Add other non-operating income
B58: a) | C58: Interest on FDR | D58: =2649713/$L$1 -> 0.2649713 | E58: =2026582.33/$L$1 -> 0.20265823 | F58: =(1931968.8+399696)/$L$1 -> 0.23316648 | G58: =F58 -> 0.23316648 | H58: =G58 -> 0.23316648 | I58: =H58 -> 0.23316648 | J58: =I58 -> 0.23316648 | K58: =J58 -> 0.23316648 | L58: =K58 -> 0.23316648
B59: b) | C59: Rent Income | D59: =2397500/$L$1 -> 0.23975 | E59: =1596055/$L$1 -> 0.1596055 | F59: =0/$L$1 -> 0 | G59: =0/$L$1 -> 0 | H59: =0/$L$1 -> 0 | I59: =0/$L$1 -> 0 | J59: =0/$L$1 -> 0 | K59: =0/$L$1 -> 0 | L59: =0/$L$1 -> 0
B60: c) | C60: Other Income | D60: =(1329937)/$L$1 -> 0.1329937 | E60: =14818513/$L$1 -> 1.4818513 | F60: =(18+3302024)/$L$1 -> 0.3302042 | G60: =0/$L$1 -> 0 | H60: =0/$L$1 -> 0 | I60: =0/$L$1 -> 0 | J60: =0/$L$1 -> 0 | K60: =0/$L$1 -> 0 | L60: =0/$L$1 -> 0
C61: Sub-total (Income) | D61: =SUM(D58:D60) -> 0.637715 | E61: =SUM(E58:E60) -> 1.844115 | F61: =SUM(F58:F60) -> 0.56337068 | G61: =SUM(G58:G60) -> 0.23316648 | H61: =SUM(H58:H60) -> 0.23316648 | I61: =SUM(I58:I60) -> 0.23316648 | J61: =SUM(J58:J60) -> 0.23316648 | K61: =SUM(K58:K60) -> 0.23316648 | L61: =SUM(L58:L60) -> 0.23316648
B62: ii) | C62: Deduct other non-operating expenses
B63: a)
